Workbook

Sheet Overview
B2: Project Summary | E2: Returns
B3: Deal Name | C3: =Assumptions!C3 -> 6719 N Lamar BLVD | E3: Net Profit | G3: ='Draw Schedule'!D171 -> 4992185.3
B4: Address | C4: =Assumptions!C4 -> 6719 N Lamar BLVD | E4: Equity Multiple | G4: ='Draw Schedule'!D172 -> 1.6615642
B5: City/State/Zip | C5: =Assumptions!C5 -> Austin, TX | E5: IRR | G5: ='Draw Schedule'!D173 -> 0.086374065
B6: Neighborhood | C6: =Assumptions!C6 -> 0 | E6: Stabilized Yield on Cost | G6: ='Net CF Post TCO'!D33 -> 0.053028021
B7: Lot Size | C7: =Assumptions!F13 -> 0
B8: Gross Building SF | C8: =Assumptions!D20 -> 106058.78
B9: Net Building SF | C9: =C11+C10 -> 53151
B10: Net Retail SF | C10: =Assumptions!F16 -> 4400
B11: Net Residential SF | C11: =Assumptions!F17 -> 48751
B12: Residentail Units | C12: =Assumptions!C29 -> 66
B13: Parking Spaces | C13: =Assumptions!F32 -> 63
B14: Project Timeline | C14: =Assumptions!J12+Assumptions!F36+Assumptions!F37 -> 83
B15: Trending? | C15: =Assumptions!L8 -> Yes
B16: Ground Lease? | C16: =Assumptions!Q24 -> No
B18: Sources & Uses
B19: Uses | C19: Total | D19: =Assumptions!U3 -> % | E19: =Assumptions!V3 -> $/GSF | F19: =Assumptions!W3 -> $/NSF | G19: =Assumptions!X3 -> $/Unit
B20: =Assumptions!S4 -> Site Acquisition | C20: =Assumptions!T4 -> 3500000 | D20: =Assumptions!U4 -> 0.11595496 | E20: =Assumptions!V4 -> 33.000569 | F20: =Assumptions!W4 -> 65.850125 | G20: =Assumptions!X4 -> 53030.303
B21: =Assumptions!S5 -> Hard Costs | C21: =Assumptions!T5 -> 19519500 | D21: =Assumptions!U5 -> 0.6466808 | E21: =Assumptions!V5 -> 184.04417 | F21: =Assumptions!W5 -> 367.24615 | G21: =Assumptions!X5 -> 295750
B22: =Assumptions!S6 -> Soft Costs | C22: =Assumptions!T6 -> 5033193.3 | D22: =Assumptions!U6 -> 0.16674963 | E22: =Assumptions!V6 -> 47.456641 | F22: =Assumptions!W6 -> 94.696117 | G22: =Assumptions!X6 -> 76260.505
B23: =Assumptions!S7 -> DS/GL Reserve | C23: =Assumptions!T7 -> 2131440.8 | D23: =Assumptions!U7 -> 0.070614609 | E23: =Assumptions!V7 -> 20.096789 | F23: =Assumptions!W7 -> 40.101613 | G23: =Assumptions!X7 -> 32294.558
B24: =Assumptions!S8 -> NOI Shortfall | C24: =Assumptions!T8 -> 0 | D24: =Assumptions!U8 -> 0 | E24: =Assumptions!V8 -> 0 | F24: =Assumptions!W8 -> 0 | G24: =Assumptions!X8 -> 0
B25: =Assumptions!S9 -> Total Uses | C25: =Assumptions!T9 -> 30184134 | D25: =Assumptions!U9 -> 1 | E25: =Assumptions!V9 -> 284.59817 | F25: =Assumptions!W9 -> 567.894 | G25: =Assumptions!X9 -> 457335.37
B27: =Assumptions!S17 -> Equity | C27: =Assumptions!T17 -> 7546033.5 | D27: =Assumptions!U17 -> 0.25 | E27: =Assumptions!V17 -> 71.149543 | F27: =Assumptions!W17 -> 141.9735 | G27: =Assumptions!X17 -> 114333.84
B28: =Assumptions!S13 -> Acquisition Loan | C28: =Assumptions!T13 -> 1750000 | D28: =Assumptions!U13 -> 0.057977479 | E28: =Assumptions!V13 -> 16.500284 | F28: =Assumptions!W13 -> 32.925063 | G28: =Assumptions!X13 -> 26515.152
B29: =Assumptions!S14 -> Construction Loan | C29: =Assumptions!T14 -> 20888101 | D29: =Assumptions!U14 -> 0.69202252 | E29: =Assumptions!V14 -> 196.94834 | F29: =Assumptions!W14 -> 392.99544 | G29: =Assumptions!X14 -> 316486.37
B30: =Assumptions!S15 -> Mezz Loan | C30: =Assumptions!T15 -> 0 | D30: =Assumptions!U15 -> 0 | E30: =Assumptions!V15 -> 0 | F30: =Assumptions!W15 -> 0 | G30: =Assumptions!X15 -> 0
B31: =Assumptions!S16 -> Ground Lease | C31: =Assumptions!T16 -> 0 | D31: =Assumptions!U16 -> 0 | E31: =Assumptions!V16 -> 0 | F31: =Assumptions!W16 -> 0 | G31: =Assumptions!X16 -> 0
B32: =Assumptions!S18 -> Total Sourses | C32: =SUM(C27:C31) -> 30184134 | D32: =SUM(D27:D31) -> 1 | E32: =SUM(E27:E31) -> 284.59817 | F32: =SUM(F27:F31) -> 567.894 | G32: =SUM(G27:G31) -> 457335.37

Sheet Assumptions
B2: Deal Info | H2: Rent Assumptions | N2: Financing | S2: Uses
B3: Deal Name | C3: 6719 N Lamar BLVD | I3: Margin | K3: Rent | L3: Growth | N3: Acquisition Loan | T3: $ | U3: % | V3: $/GSF | W3: $/NSF | X3: $/Unit
B4: Address | C4: 6719 N Lamar BLVD | H4: Residential | J4: $/NSF | K4: ='Unit Mix'!I24 -> 3.2694304 | L4: 0.03 | N4: Proceeds | Q4: =F9*Q6 -> 1750000 | S4: Site Acquisition | T4: =F9 -> 3500000 | U4: =T4/$T$9 -> 0.11595496 | V4: =T4/Assumptions!$D$20 -> 33.000569 | W4: =T4/$F$20 -> 65.850125 | X4: =T4/$C$29 -> 53030.303
B5: City/State/Zip | C5: Austin, TX | H5: Retail | J5: $/NSF | K5: 2.7 | L5: 0.03 | N5: Intro Month | P5: =EDATE($F$35,Q5) -> 46023 | Q5: 0 | S5: Hard Costs | T5: ='Construction Costs'!E11 -> 19519500 | U5: =T5/$T$9 -> 0.6466808 | V5: =T5/Assumptions!$D$20 -> 184.04417 | W5: =T5/$F$20 -> 367.24615 | X5: =T5/$C$29 -> 295750
B6: Neighborhood | H6: Parking Spaces | I6: 1 | J6: $/Space/Mo | K6: 0 | L6: 0.03 | N6: LTC (Land) | Q6: 0.5 | S6: Soft Costs | T6: ='Construction Costs'!E36-T7-T8 -> 5033193.3 | U6: =T6/$T$9 -> 0.16674963 | V6: =T6/Assumptions!$D$20 -> 47.456641 | W6: =T6/$F$20 -> 94.696117 | X6: =T6/$C$29 -> 76260.505
H7: Misc. Income | J7: $/Unit/Mo | K7: 150 | L7: 0.03 | N7: Interest Rate | Q7: 0.06 | S7: DS/GL Reserve | T7: =-'Draw Schedule'!D16-'Draw Schedule'!D15 -> 2131440.8 | U7: =T7/$T$9 -> 0.070614609 | V7: =T7/Assumptions!$D$20 -> 20.096789 | W7: =T7/$F$20 -> 40.101613 | X7: =T7/$C$29 -> 32294.558
B8: Acquisition | H8: Trended? | K8: Y/N | L8: Yes | N8: Takeout Month | P8: =EDATE($F$35,Q8) -> 46631 | Q8: 20 | S8: NOI Shortfall | T8: =-'Draw Schedule'!D14 -> 0 | U8: =T8/$T$9 -> 0 | V8: =T8/Assumptions!$D$20 -> 0 | W8: =T8/$F$20 -> 0 | X8: =T8/$C$29 -> 0
B9: Land Price | F9: 3500000 | S9: Total Uses | T9: =SUM(T4:T8) -> 30184134 | U9: =T9/$T$9 -> 1 | V9: =T9/Assumptions!$D$20 -> 284.59817 | W9: =T9/$F$20 -> 567.894 | X9: =T9/$C$29 -> 457335.37
B10: Land Price (Per Unit) | F10: =F9/C29 -> 53030.303 | H10: Sale Assumptions (Fee Simple) | N10: Construction Loan
I11: Sale Month Post TCO | K11: Cap Rate | L11: Sale Cost | N11: Proceeds | Q11: =IF(Q24="No",T9*Q13-Q4,Q13*(T9-T4)) -> 20888101 | S11: Sources
B12: Size Metrics | H12: Residential | J12: 48 | K12: 0.05 | L12: 0.01 | N12: Intro Month | P12: =EDATE($F$35,Q12) -> 46569 | Q12: 18 | T12: $ | U12: % | V12: $/GSF | W12: $/NSF | X12: $/Unit
B13: Land | H13: Retail | J13: 48 | K13: 0.055 | L13: 0.035 | N13: LTC | Q13: 0.75 | S13: Acquisition Loan | T13: =Q4 -> 1750000 | U13: =T13/$T$18 -> 0.057977479 | V13: =T13/D$20 -> 16.500284 | W13: =T13/$F$20 -> 32.925063 | X13: =T13/$C$29 -> 26515.152
B14: Stories | N14: Interest Rate | Q14: 0.075 | S14: Construction Loan | T14: =Q11 -> 20888101 | U14: =T14/$T$18 -> 0.69202252 | V14: =T14/D$20 -> 196.94834 | W14: =T14/$F$20 -> 392.99544 | X14: =T14/$C$29 -> 316486.37
D15: GSF | E15: Efficiency | F15: NSF | H15: Lease Up Schedule | S15: Mezz Loan | T15: =Q17 -> 0 | U15: =T15/$T$18 -> 0 | V15: =T15/D$20 -> 0 | W15: =T15/$F$20 -> 0 | X15: =T15/$C$29 -> 0
B16: Retail | D16: 4400 | E16: 1 | F16: =D16*E16 -> 4400 | K16: Resi | L16: Retail | N16: Mezz Loan | S16: Ground Lease | T16: =IF(Q24="Yes",Q25,0) -> 0 | U16: =T16/$T$18 -> 0 | V16: =T16/D$20 -> 0 | W16: =T16/$F$20 -> 0 | X16: =T16/$C$29 -> 0
B17: Residential | D17: =F17/0.9 -> 54167.778 | E17: =F17/D17 -> 0.9 | F17: =F29 -> 48751 | H17: Occupancy at TCO | K17: 0.35 | L17: 0.5 | N17: Proceeds | Q17: =T9*Q19 -> 0 | S17: Equity | T17: =T9-SUM(T13:T16) -> 7546033.5 | U17: =T17/$T$18 -> 0.25 | V17: =T17/D$20 -> 71.149543 | W17: =T17/$F$20 -> 141.9735 | X17: =T17/$C$29 -> 114333.84
B18: Structured Parking | D18: 34000 | E18: 0 | F18: =D18*E18 -> 0 | H18: Lease Up Per Month Post TCO | K18: 0.1 | L18: 0.15 | N18: Intro Month | P18: =EDATE($F$35,Q18) -> 46388 | Q18: 12 | S18: Total Sourses | T18: =SUM(T13:T17) -> 30184134 | U18: =T18/$T$18 -> 1 | V18: =T18/D$20 -> 284.59817 | W18: =T18/$F$20 -> 567.894 | X18: =T18/$C$29 -> 457335.37
B19: Amenity / Circ. BOH | D19: =11345+2146 -> 13491 | E19: 0 | F19: =D19*E19 -> 0 | H19: Stabilized Occupancy | K19: 0.95 | L19: 1 | N19: LTC | Q19: 0 | S19: Check | T19: =T18+'Draw Schedule'!D17+T9-'Draw Schedule'!D24 -> 0.00022627413
B20: Total | D20: =SUM(D16:D19) -> 106058.78 | E20: =F20/D20 -> 0.50114664 | F20: =SUM(F16:F19) -> 53151 | N20: Interest Rate | Q20: 0.12
H21: Operating Assumptions
B22: Unit Mix / Parking Spaces | H22: Utilities | J22: $/Unit | K22: 800 | L22: =K22*$C$29 -> 52800 | N22: Ground Lease
C23: # | D23: % | E23: Avg. SF | F23: Total SF | H23: Repairs and Maintenance | J23: $/Unit | K23: 500 | L23: =K23*$C$29 -> 33000 | N23: Ground Lease
B24: Studio | C24: ='Unit Mix'!C6+'Unit Mix'!C15 -> 0 | D24: =C24/$C$29 -> 0 | E24: =F24/C24 -> #DIV/0! | F24: ='Unit Mix'!F6+'Unit Mix'!F15 -> 0 | H24: Labor | J24: $/Unit | K24: 900 | L24: =K24*$C$29 -> 59400 | N24: GL? | P24: Y/N | Q24: No
B25: 1 BR | C25: ='Unit Mix'!C30+'Unit Mix'!C31+'Unit Mix'!C32+'Unit Mix'!C38 -> 24 | D25: =C25/$C$29 -> 0.36363636 | E25: =F25/C25 -> 583.375 | F25: ='Unit Mix'!E30+'Unit Mix'!E31+'Unit Mix'!E32+'Unit Mix'!E38 -> 14001 | H25: Insurance | J25: $/Unit | K25: 350 | L25: =K25*$C$29 -> 23100 | N25: Proceeds | Q25: 0
B26: 2 BR | C26: ='Unit Mix'!C33+'Unit Mix'!C34+'Unit Mix'!C39 -> 42 | D26: =C26/$C$29 -> 0.63636364 | E26: =F26/C26 -> 827.38095 | F26: ='Unit Mix'!E33+'Unit Mix'!E34+'Unit Mix'!E39 -> 34750 | H26: G&A / Service Contracts | J26: $/Unit | K26: 350 | L26: =K26*$C$29 -> 23100 | N26: Intro Month | P26: =EDATE($F$35,Q26) -> 46023 | Q26: 0
B27: 3 BR | C27: 0 | D27: =C27/$C$29 -> 0 | E27: 1200 | F27: =E27*C27 -> 0 | H27: Marketing/Leasing | J27: $/Unit | K27: 300 | L27: =K27*$C$29 -> 19800 | N27: Growth Rate | Q27: 0.02
B28: 4 BR | C28: 0 | D28: =C28/$C$29 -> 0 | E28: 1400 | F28: =E28*C28 -> 0 | H28: Turnover | J28: $/Unit | K28: 0 | L28: =K28*$C$29 -> 0 | N28: LTC | Q28: =Q25/T9 -> 0
B29: Total / Avg. | C29: =SUM(C24:C28) -> 66 | D29: =C29/$C$29 -> 1 | E29: =F29/C29 -> 738.65152 | F29: =SUM(F24:F28) -> 48751 | H29: Capital Reserves | J29: $/Unit | K29: 100 | L29: =K29*$C$29 -> 6600 | N29: Ground Lease Rent | Q29: 0.048
B30: Residential Parking Spaces | F30: 63 | H30: Management Fee | J30: %/GI | K30: 0.02 | N30: Cap Rate Increase | Q30: 0.0025
B31: Retail Parking Spaces | F31: 0 | H31: Opex Contingency | J31: %/OE | K31: 0.025
B32: Total Parking Spaces | E32: =(D18+D19)/F32 -> 753.8254 | F32: =SUM(F30:F31) -> 63 | H32: Annual Expense Increase | K32: =L4 -> 0.03 | N32: Refinance Loan
H33: Asset Management Fee | K33: 0.01 | N33: Refi? | P33: Y/N | Q33: No
B34: Key Timing | H34: Concessions | N34: DSCR or Debt Yield | Q34: DSCR
B35: Model Start Date* | F35: 46023 | H35: Retail Months Free | L35: 2 | N35: Interest Only or Amortizing | Q35: Amortizing
B36: Preconstruction (in Months) | F36: 15 | H36: Resi Months Free | L36: 1 | N36: Intro Month Post TCO | P36: =EDATE($F$38,Q36) -> 47453 | Q36: 12 | R36: *Must be multiple of 12
B37: Construction (in Month) | F37: 20 | H37: Real Estate Taxes | N37: Proceeds | Q37: =IF(Q33="Yes",IF(Q34="DSCR",-PV(Q41,Q42,Q44/Q40),Q44/Q43),0) -> 0
B38: TCO Date | F38: =EDATE(F35,(F36+F37)) -> 47088 | H38: Payment (Calc on Other Tab) | K38: $ | L38: =Taxes!E28 -> 432399.64 | N38: Closing Costs | Q38: =-'Closing Costs'!E53 -> 0
B39: Resi Stabilization Date | F39: =EDATE(F38,ROUNDUP((K19-K17)/K18,0)) -> 47270 | H39: Assessment as % of Construction | K39: % | L39: =Taxes!E9 -> 0.7 | N39: Net Proceeds | Q39: =SUM(Q37:Q38) -> 0
B40: Resi Sales Date | F40: =EDATE($F$38,J12) -> 48549 | H40: Tax Rate | K40: % | L40: =Taxes!E26/100 -> 0.02046485 | N40: DSCR | Q40: 1.2
B41: Retail Sales Date | F41: =EDATE($F$38,J13) -> 48549 | H41: Early Payment Discount | L41: 0.04 | N41: Interest Rate | Q41: 0.0375
B42: *Assuming closing at model start | H42: Tax Reassessment at Sale | N42: Amortization | Q42: 30
H43: Reassessment at Sale? | L43: No | N43: Debt Yield | Q43: 0.07
B44: Existing Retail | H44: Assessment as % of Price | L44: 0.75 | N44: NOI | Q44: =SUMIF('Draw Schedule'!$F$5:$BZ$5,ROUND((12+Q36)/12,0),'Draw Schedule'!$F$77:$BZ$77) -> 1570775
B45: Storage Spaces | H45: Tax Rate | L45: 0.02 | N45: Annual Debt Service | Q45: =IF(Q35="Amortizing",PMT(Q41/12,Q42*12,-Q37)*12,Q37*Q41) -> 0
H46: Early Payment Discount | L46: 0.04
B95: Yes
B96: No
B98: DSCR
B99: Debt Yield
B101: Interest Only
B102: Amortizing

Sheet Unit Mix
B2: MARKET RATE UNIT MIX
E4: Avg Unit | F4: Total | G4: Unit Monthly | H4: Yearly | I4: Monthly | J4: Monthly | K4: Misc Income
B5: Description | C5: # of Units | D5: % of Total | E5: Sq. Ft. | F5: Rentable Area | G5: Avg. Rent | H5: Avg. Unit Rent/SF | I5: Avg. Unit Rent/SF | J5: Income | K5: Per Unit/mo
B6: Studio | C6: 0 | D6: =+C6/$C$9 -> 0 | E6: 384 | F6: =E6*C6 -> 0 | G6: 1500 | H6: =G6*12/E6 -> 46.875 | I6: =H6/12 -> 3.90625 | J6: =C6*G6 -> 0 | K6: 0 | M6: 35
B7: 1 | C7: 86 | D7: =+C7/$C$9 -> 0.68253968 | E7: 730 | F7: =E7*C7 -> 62780 | G7: 1950 | H7: =G7*12/E7 -> 32.054795 | I7: =H7/12 -> 2.6712329 | J7: =C7*G7 -> 167700 | K7: 0 | M7: 85
B8: 2 | C8: 40 | D8: =+C8/$C$9 -> 0.31746032 | E8: 1100 | F8: =E8*C8 -> 44000 | G8: 2850 | H8: =G8*12/E8 -> 31.090909 | I8: =H8/12 -> 2.5909091 | J8: =C8*G8 -> 114000 | K8: 0 | M8: 35
B9: Total | C9: =SUM(C6:C8) -> 126 | D9: =+C9/$C$9 -> 1 | E9: =SUMPRODUCT(E6:E8,C6:C8)/C9 -> 847.46032 | F9: =SUM(F6:F8) -> 106780 | G9: =SUMPRODUCT(G6:G8,C6:C8)/C9 -> 2235.7143 | H9: =G9*12/E9 -> 31.657614 | I9: =H9/12 -> 2.6381345 | J9: =SUM(J6:J8) -> 281700 | K9: =SUMPRODUCT(K6:K8,$C$6:$C$8)/$C$9 -> 0
B11: AFFORDABLE HOUSING UNIT MIX - 60% AMI
E13: Avg Unit | F13: Total | G13: Unit Monthly | H13: Yearly | I13: Monthly | J13: Monthly | K13: Misc Income
B14: Description | C14: # of Units | D14: % of Total | E14: Sq. Ft. | F14: Rentable Area | G14: Avg. Rent | H14: Avg. Unit Rent/SF | I14: Avg. Unit Rent/SF | J14: Income | K14: Per Unit/mo
B15: Studio | C15: 0 | D15: =+C15/$C$18 -> 0 | E15: =E6 -> 384 | F15: =E15*C15 -> 0 | G15: =1159*1.05 -> 1216.95 | H15: =G15*12/E15 -> 38.029688 | I15: =H15/12 -> 3.1691406 | J15: =C15*G15 -> 0 | K15: 0 | M15: =M6*0.12 -> 4.2
B16: 1 | C16: 10 | D16: =+C16/$C$18 -> 0.58823529 | E16: 730 | F16: =E16*C16 -> 7300 | G16: =1159*1.05 -> 1216.95 | H16: =G16*12/E16 -> 20.004658 | I16: =H16/12 -> 1.6670548 | J16: =C16*G16 -> 12169.5 | K16: 0 | M16: =M7*0.12 -> 10.2
B17: 2 | C17: 7 | D17: =+C17/$C$18 -> 0.41176471 | E17: =E8 -> 1100 | F17: =E17*C17 -> 7700 | G17: =1324*1.05 -> 1390.2 | H17: =G17*12/E17 -> 15.165818 | I17: =H17/12 -> 1.2638182 | J17: =C17*G17 -> 9731.4 | K17: 0 | M17: =M8*0.12 -> 4.2
B18: Total | C18: =SUM(C15:C17) -> 17 | D18: =+C18/$C$18 -> 1 | E18: =SUMPRODUCT(E15:E17,C15:C17)/C18 -> 882.35294 | F18: =SUM(F15:F17) -> 15000 | G18: =SUMPRODUCT(G15:G17,C15:C17)/C18 -> 1288.2882 | H18: =G18*12/E18 -> 17.52072 | I18: =H18/12 -> 1.46006 | J18: =SUM(J15:J17) -> 21900.9 | K18: =SUMPRODUCT(K15:K17,$C$15:$C$17)/$C$18 -> 0
C21: Units | D21: % | E21: NSF | F21: % | G21: $ | H21: $/PSF | I21: $/PSF
B22: Market | C22: =C35 -> 60 | D22: =C22/$C$24 -> 0.90909091 | E22: =E35 -> 44181 | F22: =E22/$E$24 -> 0.90625833 | G22: =H35 -> 1813200 | H22: =G22/E22 -> 41.040266 | I22: =H22/12 -> 3.4200222
B23: AH (60%) | C23: =C40 -> 6 | D23: =C23/$C$24 -> 0.090909091 | E23: =E40 -> 4570 | F23: =E23/$E$24 -> 0.093741667 | G23: =H40 -> 99456 | H23: =G23/E23 -> 21.762801 | I23: =H23/12 -> 1.8135667
B24: Total | C24: =C22+C23 -> 66 | D24: =C24/$C$24 -> 1 | E24: =SUM(E22:E23) -> 48751 | F24: =E24/$E$24 -> 1 | G24: =SUM(G22:G23) -> 1912656 | H24: =G24/E24 -> 39.233164 | I24: =H24/12 -> 3.2694304
E25: =E24/C24 -> 738.65152
B28: Free market
B29: Condo Project | C29: # Units | D29: Avg SF | E29: Total SF | F29: Rent | G29: Total Rent income | H29: Yearly income | I29: yearly psf | J29: Montly $/SF
B30: 1BR – A (Compact) | C30: 1 | D30: 546 | E30: =C30*D30 -> 546 | F30: 1850 | G30: =F30*C30 -> 1850 | H30: =G30*12 -> 22200 | I30: =H30/E30 -> 40.659341 | J30: =I30/12 -> 3.3882784
B31: 1BR – B (Mid) | C31: 21 | D31: 585 | E31: =C31*D31 -> 12285 | F31: 1950 | G31: =F31*C31 -> 40950 | H31: =G31*12 -> 491400 | I31: =H31/E31 -> 40 | J31: =I31/12 -> 3.3333333
B32: 1BR – C (Large) | C32: 0 | D32: 713 | E32: =C32*D32 -> 0 | F32: 2100 | G32: =F32*C32 -> 0 | H32: =G32*12 -> 0 | I32: =H32/E32 -> #DIV/0! | J32: =I32/12 -> #DIV/0!
B33: 2BR – A (Compact) | C33: 38 | D33: 825 | E33: =C33*D33 -> 31350 | F33: 2850 | G33: =F33*C33 -> 108300 | H33: =G33*12 -> 1299600 | I33: =H33/E33 -> 41.454545 | J33: =I33/12 -> 3.4545455
B34: 2BR – B (Large) | C34: 0 | D34: 996 | E34: =C34*D34 -> 0 | F34: 2850 | G34: =F34*C34 -> 0 | H34: =G34*12 -> 0 | I34: =H34/E34 -> #DIV/0! | J34: =I34/12 -> #DIV/0!
B35: Total / Average | C35: =SUM(C30:C34) -> 60 | D35: =E35/C35 -> 736.35 | E35: =SUM(E30:E34) -> 44181 | G35: =SUM(G30:G34) -> 151100 | H35: =SUM(H30:H34) -> 1813200
B37: affordable | C37: # Units | D37: Avg SF | E37: Total SF | F37: Rent | G37: Total Rent income | H37: Yearly income | I37: yearly psf | J37: Montly $/SF
B38: 1BR – A (Compact) | C38: 2 | D38: 585 | E38: =D38*C38 -> 1170 | F38: 1244 | G38: =F38*C38 -> 2488 | H38: =G38*12 -> 29856 | I38: =H38/E38 -> 25.517949 | J38: =I38/12 -> 2.1264957
B39: 2BR – A (Compact) | C39: 4 | D39: 850 | E39: =D39*C39 -> 3400 | F39: 1450 | G39: =F39*C39 -> 5800 | H39: =G39*12 -> 69600 | I39: =H39/E39 -> 20.470588 | J39: =I39/12 -> 1.7058824
C40: =SUM(C38:C39) -> 6 | E40: =SUM(E38:E39) -> 4570 | H40: =SUM(H38:H39) -> 99456
C42: =C40+C35 -> 66 | E42: =E40+E35 -> 48751 | H42: =H40+H35 -> 1912656
E43: =E42/C42 -> 738.65152

Sheet Construction Costs
B2: Land Costs
B3: Total Land Costs | E3: =Assumptions!F9 -> 3500000
B5: Hard Costs | H5: Cost per unit
E6: Total | F6: $/GSF | G6: $/NSF
B7: Hard Costs apartments | E7: =H7*Assumptions!C29 -> 16500000 | F7: =E7/Assumptions!D20 -> 155.57411 | G7: =E7/Assumptions!F17 -> 338.4546 | H7: 250000
B8: Hard Costs podium | E8: =H8*Assumptions!F30 -> 1890000 | F8: =E8/Assumptions!D18 -> 55.588235 | H8: 30000
B9: FF&E | E9: 200000
B10: Contingency | C10: 0.05 | D10: HC | E10: =SUM(E7:E9)*C10 -> 929500
B11: Total | E11: =SUM(E7:E10) -> 19519500 | F11: =E11/Assumptions!D20 -> 184.04417 | G11: =E11/Assumptions!$F$20 -> 367.24615 | H11: =E11/161 -> 121239.13
B13: Soft Costs | I13: Impact Fees
E14: $ | F14: $/GSF | G14: $/NSF | I14: Parkland Dedication | J14: =4700*Assumptions!C29 -> 310200
B15: Architects/Engineers | E15: =950000 -> 950000 | F15: =E15/Assumptions!$D$20 -> 8.9572973 | G15: =E15/Assumptions!$F$20 -> 17.873605 | I15: Austin City Impact Fee | J15: 30000
B16: Impact Fees | E16: =J17 -> 350200 | F16: =E16/Assumptions!$D$20 -> 3.3019426 | G16: =E16/Assumptions!$F$20 -> 6.5887754 | I16: Waste Water Impact Fee | J16: 10000
B17: Permits & Expediting | E17: 150000 | F17: =E17/Assumptions!$D$20 -> 1.4143101 | G17: =E17/Assumptions!$F$20 -> 2.8221482 | I17: Total | J17: =SUM(J14:J16) -> 350200
B18: Supervision, Local Partner Expenses, and Investor Relations | E18: 350000 | F18: =E18/Assumptions!$D$20 -> 3.3000569 | G18: =E18/Assumptions!$F$20 -> 6.5850125
B19: Inspections and Testing | E19: 100000 | F19: =E19/Assumptions!$D$20 -> 0.9428734 | G19: =E19/Assumptions!$F$20 -> 1.8814321
B20: Professional/Legal Fees | E20: 75000 | F20: =E20/Assumptions!$D$20 -> 0.70715505 | G20: =E20/Assumptions!$F$20 -> 1.4110741
B21: Owners Rep | E21: 250000 | F21: =E21/Assumptions!$D$20 -> 2.3571835 | G21: =E21/Assumptions!$F$20 -> 4.7035804
B22: Audit and Reporting | E22: 50000 | F22: =E22/Assumptions!$D$20 -> 0.4714367 | G22: =E22/Assumptions!$F$20 -> 0.94071607
B23: Marketing / Model Unit | E23: 70000 | F23: =E23/Assumptions!$D$20 -> 0.66001138 | G23: =E23/Assumptions!$F$20 -> 1.3170025
B24: Insurance | E24: 100000 | F24: =E24/Assumptions!$D$20 -> 0.9428734 | G24: =E24/Assumptions!$F$20 -> 1.8814321
B25: RE Taxes During Construction** | C25: 53000 | D25: 2 | E25: =C25*D25 -> 106000 | F25: =E25/Assumptions!$D$20 -> 0.9994458 | G25: =E25/Assumptions!$F$20 -> 1.9943181 | H25: *First Year covered by tenant
B26: Retail Leasing Commission | C26: 0.06 | D26: 5 | E26: =C26*D26*Assumptions!K5*12*Assumptions!F16 -> 42768 | F26: =E26/Assumptions!$D$20 -> 0.40324809 | G26: =E26/Assumptions!$F$20 -> 0.8046509
B27: Retail Tenant Improvements | C27: 20 | D27: NSF | E27: =C27*Assumptions!F16 -> 88000 | F27: =E27/Assumptions!$D$20 -> 0.82972859 | G27: =E27/Assumptions!$F$20 -> 1.6556603
B28: Working Capital During Leasing Period | C28: 1.5 | D28: GSF | E28: =C28*Assumptions!D20 -> 159088.17 | F28: =E28/Assumptions!$D$20 -> 1.5 | G28: =E28/Assumptions!$F$20 -> 2.9931359
B29: Closing Costs | E29: ='Closing Costs'!E46 -> 681788.21 | F29: =E29/Assumptions!$D$20 -> 6.4283997 | G29: =E29/Assumptions!$F$20 -> 12.827383
B30: Contingency | C30: 0.05 | D30: SC | E30: =SUM(E15:E29,E35)*C30 -> 239675.87 | F30: =E30/Assumptions!$D$20 -> 2.25984 | G30: =E30/Assumptions!$F$20 -> 4.5093389
B31: Capitalized Interest | E31: =-'Draw Schedule'!D16 -> 2131440.8 | F31: =E31/Assumptions!$D$20 -> 20.096789 | G31: =E31/Assumptions!$F$20 -> 40.101613
B32: Capitalized Ground Rent | E32: =-'Draw Schedule'!D15 -> 0 | F32: =E32/Assumptions!$D$20 -> 0 | G32: =E32/Assumptions!$F$20 -> 0
B33: NOI Shortfall | E33: =-'Draw Schedule'!D14 -> 0 | F33: =E33/Assumptions!$D$20 -> 0 | G33: =E33/Assumptions!$F$20 -> 0
B34: Total Soft Costs Before Developer Fee | E34: =SUM(E15:E33) -> 5893961.1 | F34: =E34/Assumptions!$D$20 -> 55.572591 | G34: =E34/Assumptions!$F$20 -> 110.89088
B35: Developer Fee | C35: 0.05 | D35: HC and SC | E35: =C35*(E11+E34) -> 1270673.1 | F35: =E35/Assumptions!$D$20 -> 11.980838 | G35: =E35/Assumptions!$F$20 -> 23.906851
B36: Total Soft Costs | E36: =E34+E35 -> 7164634.1 | F36: =E36/Assumptions!$D$20 -> 67.553429 | G36: =E36/Assumptions!$F$20 -> 134.79773
B38: Total Costs | E38: =E3+E11+E36 -> 30184134 | F38: =E38/Assumptions!$D$20 -> 284.59817 | G38: =E38/Assumptions!$F$20 -> 567.894

Sheet Hard Costs
A5: Design | C5: 75000 | D5: =C5/Assumptions!$D$20 -> 0.70715505
A6: Mobilization | C6: 142000 | D6: =C6/Assumptions!$D$20 -> 1.3388802
A7: Concrete | B7: Podium | C7: 5000000 | D7: =C7/Assumptions!$D$20 -> 47.14367
B8: Residntial | C8: =40*11000*13 -> 5720000 | D8: =C8/Assumptions!$D$20 -> 53.932358
A9: Masonary | C9: =D9*Assumptions!$D$17 -> 417993.05 | D9: =2585706/335082 -> 7.7166365
A10: Metal | C10: =D10*Assumptions!$D$17 -> 135419.44 | D10: 2.5
A11: Carpentry | C11: =D11*Assumptions!$D$17 -> 1300026.7 | D11: 24
A12: Thermal moister protection | C12: =D12*Assumptions!$D$17 -> 297922.78 | D12: 5.5
A13: openings | C13: =D13*Assumptions!$D$17 -> 270838.89 | D13: 5
A14: Finishes | C14: =D14*Assumptions!$D$17 -> 758348.89 | D14: 14
A15: speciality | C15: =D15*Assumptions!$D$17 -> 54167.778 | D15: 1
A16: equipment | C16: =D16*Assumptions!$D$17 -> 135419.44 | D16: 2.5
A17: furnishing | C17: =D17*Assumptions!$D$17 -> 270838.89 | D17: 5
A18: special construction | C18: =D18*Assumptions!$D$17 -> 541677.78 | D18: 10
A19: elevators | C19: =D19*Assumptions!$D$17 -> 108335.56 | D19: 2
A20: fire suppression | C20: =D20*Assumptions!$D$17 -> 135419.44 | D20: 2.5
A21: plumbing | C21: =D21*Assumptions!$D$17 -> 487510 | D21: 9
... A30: Insurance | C30: =D30*Assumptions!$D$17 -> 108335.56 | D30: 2
A31: Subtotal | C31: =SUM(C5:C30) -> 17584287
A32: Contingency | B32: 0.05 | C32: =C31*B32 -> 879214.37
A33: GC Fee | B33: 0.1 | C33: =C31*B33 -> 1758428.7 | E33: GSF | F33: NGF
A34: Total | C34: =C31+C32+C33 -> 20221931 | E34: =C34/Assumptions!D20 -> 190.6672 | F34: =C34/Assumptions!F17 -> 414.80032

Sheet Closing Costs
B2: Land Closing
B3: Transaction Legal | E3: 7000
B4: Title Insurance | C4: 0.0015 | D4: of PP | E4: =C4*Assumptions!$F$9 -> 5250
B5: Acquisition Fee | C5: 0.02 | D5: of PP | E5: =C5*Assumptions!$F$9 -> 70000
B6: Real Estate Broker | C6: 0.01 | D6: of PP | E6: =C6*Assumptions!$F$9 -> 35000
B7: Due Diligence | E7: 30000
B8: Total | E8: =SUM(E3:E7) -> 147250
B10: Acquisition Loan Closing
B11: Bank Fee | C11: 0 | D11: of Mtg | E11: =C11*Assumptions!$Q$4 -> 0
B12: Mortgage Broker Fee | C12: 0 | D12: of Mtg | E12: =C12*Assumptions!$Q$4 -> 0
B13: Mortgage Recording Tax | C13: 0 | D13: of Mtg | E13: =C13*Assumptions!$Q$4 -> 0
B14: Title Insurance | C14: 0 | D14: of Mtg | E14: =C14*Assumptions!$Q$4 -> 0
B15: Appraisal & Environmental | E15: 0
B16: Lender Legal | E16: 0
B17: General Loan Closing Costs | E17: 0
B18: Total | E18: =SUM(E11:E17) -> 0
B20: Construction Loan Closing
B21: Bank Fee | C21: 0.01 | D21: of Mtg | E21: =C21*Assumptions!$Q$11 -> 208881.01
B22: Mortgage Broker Fee | C22: 0.01 | D22: of Mtg | E22: =C22*Assumptions!$Q$11 -> 208881.01
B23: Mortgage Recording Tax | C23: 0.0005 | D23: of Mtg | E23: =C23*Assumptions!$Q$11 -> 10444.05
B24: Title Insurance | C24: 0.0015 | D24: of Mtg | E24: =C24*Assumptions!$Q$11 -> 31332.151
B25: Appraisal & Environmental | E25: 25000
B26: Lender Legal | E26: 25000
B27: General Loan Closing Costs | E27: 25000
B28: Total | E28: =SUM(E21:E27) -> 534538.21
B30: Mezzanine Loan Closing
B31: Mezz Bank Fee | C31: 0.01 | D31: of Mezz | E31: =C31*Assumptions!$Q$17 -> 0
B32: Mezz Broker Fee | C32: 0.005 | D32: of Mezz | E32: =C32*Assumptions!$Q$17 -> 0
B33: Title Insurance | C33: 0.0055 | D33: of Mezz | E33: =C33*Assumptions!$Q$17 -> 0
B34: Lender Legal | E34: 0
B35: General Closing Costs | E35: 0
B36: Total | E36: =SUM(E31:E35) -> 0
B38: Ground Lease Loan Closing
B39: Ground Lease Fee | C39: =IF(Assumptions!$Q$33="Yes",'Closing Costs'!H39,0) -> 0 | D39: of GL | E39: =IF(Assumptions!$Q$24="No",0,C39*Assumptions!$Q$25) -> 0
B40: Ground Lease Broker Fee | C40: 0.005 | D40: of GL | E40: =IF(Assumptions!$Q$24="No",0,C40*Assumptions!$Q$25) -> 0
B41: Title Insurance | C41: 0.0055 | D41: of GL | E41: =IF(Assumptions!$Q$24="No",0,C41*Assumptions!$Q$25) -> 0
B42: Ground Lease Legal | E42: 0
B43: General Loan Closing Costs | E43: 0
B44: Total | E44: =SUM(E39:E43) -> 0
B46: Total Closing Costs | E46: =E8+E18+E28+E36+E44 -> 681788.21
B48: Refinance Closing
B49: Bank Fee | C49: 0.01 | D49: of Mtg | E49: =C49*Assumptions!$Q$37 -> 0
B50: Broker Fee | C50: 0.005 | D50: of Mtg | E50: =C50*Assumptions!$Q$37 -> 0
B51: Lender Legal | E51: 0
B52: General Loan Closing Costs | E52: 0
B53: Total | E53: =SUM(E49:E52) -> 0

Sheet Taxes
B2: Taxes - Toomey Apartments - Austin, TX
B3: Land Purchase Price | E3: ='Construction Costs'!E3 -> 3500000
B4: Hard Costs | E4: ='Construction Costs'!E11 -> 19519500
B5: Soft Costs | C5: Include? | D5: Y | E5: =IF(D5="Y",'Construction Costs'!E36-E6-E7,0) -> 4351405.1
B6: Construction Interest | C6: Include? | D6: Y | E6: =IF(D5="Y",'Construction Costs'!E31+'Construction Costs'!E32,0) -> 2131440.8
B7: Financing Fees | C7: Include? | D7: Y | E7: =IF(D5="Y",'Construction Costs'!E29,0) -> 681788.21
B9: Assessment Percentage | E9: 0.7
B11: Assessed Value | E11: =SUM(E3:E7)*E9 -> 21128894
B13: Year 1 Millage Rates | E13: (All Millage Rates should be divided by 100)
B14: Travis County | E14: 0.375845
B15: City of Austin | E15: 0.524017
B16: Austin ISD | E16: 0.9252
B17: Travis County Healthcare Dist | E17: 0.118023
B18: Austin Comm College | E18: 0.1034
B19: blank | E19: 0
B20: blank | E20: 0
B21: Blank 1 | E21: 0
B22: Blank 2 | E22: 0
B23: Blank 3 | E23: 0
B24: Blank 4 | E24: 0
B25: Blank 5 | E25: 0
B26: Total | E26: =SUM(E14:E25) -> 2.046485
B28: Stabilized Tax Expense | E28: =E11*E26/100 -> 432399.64

Sheet Draw Schedule
B2: Monthly Cash Flows
B3: Month | D3: Total | F3: 1 | G3: =F3+1 -> 2 | H3: =G3+1 -> 3 | I3: =H3+1 -> 4 | J3: =I3+1 -> 5 | K3: =J3+1 -> 6 | L3: =K3+1 -> 7 | M3: =L3+1 -> 8 | N3: =M3+1 -> 9 | ... ET3: =ES3+1 -> 145
B4: Year | F4: =ROUNDUP(F3/12,0) -> 1 | G4: =ROUNDUP(G3/12,0) -> 1 | H4: =ROUNDUP(H3/12,0) -> 1 | I4: =ROUNDUP(I3/12,0) -> 1 | J4: =ROUNDUP(J3/12,0) -> 1 | K4: =ROUNDUP(K3/12,0) -> 1 | L4: =ROUNDUP(L3/12,0) -> 1 | M4: =ROUNDUP(M3/12,0) -> 1 | ... ET4: =ROUNDUP(ET3/12,0) -> 13
B5: Year Post TCO | F5: =IF(F6>=Assumptions!$F$38,ROUNDUP(YEARFRAC(Assumptions!$F$38-1,'Draw Schedule'!F6),0),0) -> 0 | G5: =IF(G6>=Assumptions!$F$38,ROUNDUP(YEARFRAC(Assumptions!$F$38-1,'Draw Schedule'!G6),0),0) -> 0 | H5: =IF(H6>=Assumptions!$F$38,ROUNDUP(YEARFRAC(Assumptions!$F$38-1,'Draw Schedule'!H6),0),0) -> 0 | I5: =IF(I6>=Assumptions!$F$38,ROUNDUP(YEARFRAC(Assumptions!$F$38-1,'Draw Schedule'!I6),0),0) -> 0 | J5: =IF(J6>=Assumptions!$F$38,ROUNDUP(YEARFRAC(Assumptions!$F$38-1,'Draw Schedule'!J6),0),0) -> 0 | K5: =IF(K6>=Assumptions!$F$38,ROUNDUP(YEARFRAC(Assumptions!$F$38-1,'Draw Schedule'!K6),0),0) -> 0 | L5: =IF(L6>=Assumptions!$F$38,ROUNDUP(YEARFRAC(Assumptions!$F$38-1,'Draw Schedule'!L6),0),0) -> 0 | M5: =IF(M6>=Assumptions!$F$38,ROUNDUP(YEARFRAC(Assumptions!$F$38-1,'Draw Schedule'!M6),0),0) -> 0 | ... ET5: =IF(ET6>=Assumptions!$F$38,ROUNDUP(YEARFRAC(Assumptions!$F$38-1,'Draw Schedule'!ET6),0),0) -> 10
B6: Date | F6: =Assumptions!F35 -> 46023 | G6: =EDATE(F6,1) -> 46054 | H6: =EDATE(G6,1) -> 46082 | I6: =EDATE(H6,1) -> 46113 | J6: =EDATE(I6,1) -> 46143 | K6: =EDATE(J6,1) -> 46174 | L6: =EDATE(K6,1) -> 46204 | M6: =EDATE(L6,1) -> 46235 | N6: =EDATE(M6,1) -> 46266 | ... ET6: =EDATE(ES6,1) -> 50406
B8: Uses
B9: Acquisition | D9: =SUM(F9:ET9) -> -3500000 | F9: =-IF(F$6=Assumptions!$F$35,Assumptions!$F$9,0) -> -3500000 | G9: =IF(G6=Assumptions!$F$35,Assumptions!$F$9,0) -> 0 | H9: =IF(H6=Assumptions!$F$35,Assumptions!$F$9,0) -> 0 | I9: =IF(I6=Assumptions!$F$35,Assumptions!$F$9,0) -> 0 | J9: =IF(J6=Assumptions!$F$35,Assumptions!$F$9,0) -> 0 | K9: =IF(K6=Assumptions!$F$35,Assumptions!$F$9,0) -> 0 | L9: =IF(L6=Assumptions!$F$35,Assumptions!$F$9,0) -> 0 | M9: =IF(M6=Assumptions!$F$35,Assumptions!$F$9,0) -> 0 | N9: =IF(N6=Assumptions!$F$35,Assumptions!$F$9,0) -> 0 | ... ET9: =IF(ET6=Assumptions!$F$35,Assumptions!$F$9,0) -> 0
B10: Closing Soft Costs | D10: =SUM(F10:ET10) -> -681788.21 | F10: =-(IF(F$6=Assumptions!$F$35,'Closing Costs'!$E$8,0)+IF(F$6=Assumptions!$P$5,'Closing Costs'!$E$18,0)+IF(F$6=Assumptions!$P$12,'Closing Costs'!$E$28,0)+IF(F$6=Assumptions!$P$18,'Closing Costs'!$E$36,0)+IF(F$6=Assumptions!$P$26,'Closing Costs'!$E$44,0)) -> -147250 | G10: =-(IF(G$6=Assumptions!$F$35,'Closing Costs'!$E$8,0)+IF(G$6=Assumptions!$P$5,'Closing Costs'!$E$18,0)+IF(G$6=Assumptions!$P$12,'Closing Costs'!$E$28,0)+IF(G$6=Assumptions!$P$18,'Closing Costs'!$E$36,0)+IF(G$6=Assumptions!$P$26,'Closing Costs'!$E$44,0)) -> 0 | H10: =-(IF(H$6=Assumptions!$F$35,'Closing Costs'!$E$8,0)+IF(H$6=Assumptions!$P$5,'Closing Costs'!$E$18,0)+IF(H$6=Assumptions!$P$12,'Closing Costs'!$E$28,0)+IF(H$6=Assumptions!$P$18,'Closing Costs'!$E$36,0)+IF(H$6=Assumptions!$P$26,'Closing Costs'!$E$44,0)) -> 0 | I10: =-(IF(I$6=Assumptions!$F$35,'Closing Costs'!$E$8,0)+IF(I$6=Assumptions!$P$5,'Closing Costs'!$E$18,0)+IF(I$6=Assumptions!$P$12,'Closing Costs'!$E$28,0)+IF(I$6=Assumptions!$P$18,'Closing Costs'!$E$36,0)+IF(I$6=Assumptions!$P$26,'Closing Costs'!$E$44,0)) -> 0 | J10: =-(IF(J$6=Assumptions!$F$35,'Closing Costs'!$E$8,0)+IF(J$6=Assumptions!$P$5,'Closing Costs'!$E$18,0)+IF(J$6=Assumptions!$P$12,'Closing Costs'!$E$28,0)+IF(J$6=Assumptions!$P$18,'Closing Costs'!$E$36,0)+IF(J$6=Assumptions!$P$26,'Closing Costs'!$E$44,0)) -> 0 | K10: =-(IF(K$6=Assumptions!$F$35,'Closing Costs'!$E$8,0)+IF(K$6=Assumptions!$P$5,'Closing Costs'!$E$18,0)+IF(K$6=Assumptions!$P$12,'Closing Costs'!$E$28,0)+IF(K$6=Assumptions!$P$18,'Closing Costs'!$E$36,0)+IF(K$6=Assumptions!$P$26,'Closing Costs'!$E$44,0)) -> 0 | L10: =-(IF(L$6=Assumptions!$F$35,'Closing Costs'!$E$8,0)+IF(L$6=Assumptions!$P$5,'Closing Costs'!$E$18,0)+IF(L$6=Assumptions!$P$12,'Closing Costs'!$E$28,0)+IF(L$6=Assumptions!$P$18,'Closing Costs'!$E$36,0)+IF(L$6=Assumptions!$P$26,'Closing Costs'!$E$44,0)) -> 0 | M10: =-(IF(M$6=Assumptions!$F$35,'Closing Costs'!$E$8,0)+IF(M$6=Assumptions!$P$5,'Closing Costs'!$E$18,0)+IF(M$6=Assumptions!$P$12,'Closing Costs'!$E$28,0)+IF(M$6=Assumptions!$P$18,'Closing Costs'!$E$36,0)+IF(M$6=Assumptions!$P$26,'Closing Costs'!$E$44,0)) -> 0 | ... ET10: =-(IF(ET$6=Assumptions!$F$35,'Closing Costs'!$E$8,0)+IF(ET$6=Assumptions!$P$5,'Closing Costs'!$E$18,0)+IF(ET$6=Assumptions!$P$12,'Closing Costs'!$E$28,0)+IF(ET$6=Assumptions!$P$18,'Closing Costs'!$E$36,0)+IF(ET$6=Assumptions!$P$26,'Closing Costs'!$E$44,0)) -> 0
B11: Construction Soft Costs | D11: =SUM(F11:ET11) -> -3080732 | F11: =-IF(F$3<=SUM(Assumptions!$F$36:$F$37),('Construction Costs'!$E$34-'Construction Costs'!$E$29-'Construction Costs'!$E$31-'Construction Costs'!$E$32-'Construction Costs'!$E$33)/SUM(Assumptions!$F$36:$F$37),0) -> -88020.915 | G11: =-IF(G$3<=SUM(Assumptions!$F$36:$F$37),('Construction Costs'!$E$34-'Construction Costs'!$E$29-'Construction Costs'!$E$31-'Construction Costs'!$E$32-'Construction Costs'!$E$33)/SUM(Assumptions!$F$36:$F$37),0) -> -88020.915 | H11: =-IF(H$3<=SUM(Assumptions!$F$36:$F$37),('Construction Costs'!$E$34-'Construction Costs'!$E$29-'Construction Costs'!$E$31-'Construction Costs'!$E$32-'Construction Costs'!$E$33)/SUM(Assumptions!$F$36:$F$37),0) -> -88020.915 | I11: =-IF(I$3<=SUM(Assumptions!$F$36:$F$37),('Construction Costs'!$E$34-'Construction Costs'!$E$29-'Construction Costs'!$E$31-'Construction Costs'!$E$32-'Construction Costs'!$E$33)/SUM(Assumptions!$F$36:$F$37),0) -> -88020.915 | J11: =-IF(J$3<=SUM(Assumptions!$F$36:$F$37),('Construction Costs'!$E$34-'Construction Costs'!$E$29-'Construction Costs'!$E$31-'Construction Costs'!$E$32-'Construction Costs'!$E$33)/SUM(Assumptions!$F$36:$F$37),0) -> -88020.915 | K11: =-IF(K$3<=SUM(Assumptions!$F$36:$F$37),('Construction Costs'!$E$34-'Construction Costs'!$E$29-'Construction Costs'!$E$31-'Construction Costs'!$E$32-'Construction Costs'!$E$33)/SUM(Assumptions!$F$36:$F$37),0) -> -88020.915 | L11: =-IF(L$3<=SUM(Assumptions!$F$36:$F$37),('Construction Costs'!$E$34-'Construction Costs'!$E$29-'Construction Costs'!$E$31-'Construction Costs'!$E$32-'Construction Costs'!$E$33)/SUM(Assumptions!$F$36:$F$37),0) -> -88020.915 | M11: =-IF(M$3<=SUM(Assumptions!$F$36:$F$37),('Construction Costs'!$E$34-'Construction Costs'!$E$29-'Construction Costs'!$E$31-'Construction Costs'!$E$32-'Construction Costs'!$E$33)/SUM(Assumptions!$F$36:$F$37),0) -> -88020.915 | ... ET11: =-IF(ET$3<=SUM(Assumptions!$F$36:$F$37),('Construction Costs'!$E$34-'Construction Costs'!$E$29-'Construction Costs'!$E$31-'Construction Costs'!$E$32-'Construction Costs'!$E$33)/SUM(Assumptions!$F$36:$F$37),0) -> 0
B12: Developer Fee Soft Cost | D12: =SUM(F12:ET12) -> -1270673.1 | F12: =-IF(F$3<=SUM(Assumptions!$F$36:$F$37),'Construction Costs'!$E$35/SUM(Assumptions!$F$36:$F$37),0) -> -36304.944 | G12: =-IF(G$3<=SUM(Assumptions!$F$36:$F$37),'Construction Costs'!$E$35/SUM(Assumptions!$F$36:$F$37),0) -> -36304.944 | H12: =-IF(H$3<=SUM(Assumptions!$F$36:$F$37),'Construction Costs'!$E$35/SUM(Assumptions!$F$36:$F$37),0) -> -36304.944 | I12: =-IF(I$3<=SUM(Assumptions!$F$36:$F$37),'Construction Costs'!$E$35/SUM(Assumptions!$F$36:$F$37),0) -> -36304.944 | J12: =-IF(J$3<=SUM(Assumptions!$F$36:$F$37),'Construction Costs'!$E$35/SUM(Assumptions!$F$36:$F$37),0) -> -36304.944 | K12: =-IF(K$3<=SUM(Assumptions!$F$36:$F$37),'Construction Costs'!$E$35/SUM(Assumptions!$F$36:$F$37),0) -> -36304.944 | L12: =-IF(L$3<=SUM(Assumptions!$F$36:$F$37),'Construction Costs'!$E$35/SUM(Assumptions!$F$36:$F$37),0) -> -36304.944 | M12: =-IF(M$3<=SUM(Assumptions!$F$36:$F$37),'Construction Costs'!$E$35/SUM(Assumptions!$F$36:$F$37),0) -> -36304.944 | ... ET12: =-IF(ET$3<=SUM(Assumptions!$F$36:$F$37),'Construction Costs'!$E$35/SUM(Assumptions!$F$36:$F$37),0) -> 0
B13: Hard Costs | D13: =SUM(F13:ET13) -> -19519500 | F13: =-IF(F$3<=Assumptions!$F$36,0,IF(F$3<=SUM(Assumptions!$F$36:$F$37),'Construction Costs'!$E$11/Assumptions!$F$37,0)) -> 0 | G13: =-IF(G$3<=Assumptions!$F$36,0,IF(G$3<=SUM(Assumptions!$F$36:$F$37),'Construction Costs'!$E$11/Assumptions!$F$37,0)) -> 0 | H13: =-IF(H$3<=Assumptions!$F$36,0,IF(H$3<=SUM(Assumptions!$F$36:$F$37),'Construction Costs'!$E$11/Assumptions!$F$37,0)) -> 0 | I13: =-IF(I$3<=Assumptions!$F$36,0,IF(I$3<=SUM(Assumptions!$F$36:$F$37),'Construction Costs'!$E$11/Assumptions!$F$37,0)) -> 0 | J13: =-IF(J$3<=Assumptions!$F$36,0,IF(J$3<=SUM(Assumptions!$F$36:$F$37),'Construction Costs'!$E$11/Assumptions!$F$37,0)) -> 0 | K13: =-IF(K$3<=Assumptions!$F$36,0,IF(K$3<=SUM(Assumptions!$F$36:$F$37),'Construction Costs'!$E$11/Assumptions!$F$37,0)) -> 0 | L13: =-IF(L$3<=Assumptions!$F$36,0,IF(L$3<=SUM(Assumptions!$F$36:$F$37),'Construction Costs'!$E$11/Assumptions!$F$37,0)) -> 0 | M13: =-IF(M$3<=Assumptions!$F$36,0,IF(M$3<=SUM(Assumptions!$F$36:$F$37),'Construction Costs'!$E$11/Assumptions!$F$37,0)) -> 0 | ... ET13: =-IF(ET$3<=Assumptions!$F$36,0,IF(ET$3<=SUM(Assumptions!$F$36:$F$37),'Construction Costs'!$E$11/Assumptions!$F$37,0)) -> 0
B14: NOI Shortfall | D14: =SUM(F14:ET14) -> 0 | F14: =IF(F63+F73<0,F63+F73,0) -> 0 | G14: =IF(G63+G73<0,G63+G73,0) -> 0 | H14: =IF(H63+H73<0,H63+H73,0) -> 0 | I14: =IF(I63+I73<0,I63+I73,0) -> 0 | J14: =IF(J63+J73<0,J63+J73,0) -> 0 | K14: =IF(K63+K73<0,K63+K73,0) -> 0 | L14: =IF(L63+L73<0,L63+L73,0) -> 0 | M14: =IF(M63+M73<0,M63+M73,0) -> 0 | ... ET14: =IF(ET63+ET73<0,ET63+ET73,0) -> 0
B15: Capitalized Ground Lease Rent | D15: =SUM(F15:ET15) -> 0 | F15: =-F141 -> 0 | G15: =-G141 -> 0 | H15: =-H141 -> 0 | I15: =-I141 -> 0 | J15: =-J141 -> 0 | K15: =-K141 -> 0 | L15: =-L141 -> 0 | M15: =-M141 -> 0 | ... ET15: =-ET141 -> 0
B16: Capitalized Interest | D16: =SUM(F16:ET16) -> -2131440.8 | F16: =-(F115+F125+F133) -> 0 | G16: =-(G115+G125+G133) -> -8750 | H16: =-(H115+H125+H133) -> -8750 | I16: =-(I115+I125+I133) -> -8750 | J16: =-(J115+J125+J133) -> -8750 | K16: =-(K115+K125+K133) -> -8750 | L16: =-(L115+L125+L133) -> -8750 | M16: =-(M115+M125+M133) -> -8750 | ... ET16: =-(ET115+ET125+ET133) -> 0
B17: Total Uses | D17: =SUM(F17:ET17) -> -30184134 | F17: =SUM(F9:F16) -> -3771575.9 | G17: =SUM(G9:G16) -> -133075.86 | H17: =SUM(H9:H16) -> -133075.86 | I17: =SUM(I9:I16) -> -133075.86 | J17: =SUM(J9:J16) -> -133075.86 | K17: =SUM(K9:K16) -> -133075.86 | L17: =SUM(L9:L16) -> -133075.86 | M17: =SUM(M9:M16) -> -133075.86 | ... ET17: =SUM(ET9:ET16) -> 0
B19: Sources
B20: Equity Contribution | D20: =SUM(F20:ET20) -> 7546033.5 | F20: =-F89 -> 2021575.9 | G20: =-G89 -> 133075.86 | H20: =-H89 -> 133075.86 | I20: =-I89 -> 133075.86 | J20: =-J89 -> 133075.86 | K20: =-K89 -> 133075.86 | L20: =-L89 -> 133075.86 | M20: =-M89 -> 133075.86 | ... ET20: =-ET89 -> 0
B21: Mezz Loan | D21: =SUM(F21:ET21) -> 0 | F21: =-F95 -> 0 | G21: =-G95 -> 0 | H21: =-H95 -> 0 | I21: =-I95 -> 0 | J21: =-J95 -> 0 | K21: =-K95 -> 0 | L21: =-L95 -> 0 | M21: =-M95 -> 0 | ... ET21: =-ET95 -> 0
B22: Ground Lease Contribution | D22: =SUM(F22:ET22) -> 0 | F22: =-F101 -> 0 | G22: =-G101 -> 0 | H22: =-H101 -> 0 | I22: =-I101 -> 0 | J22: =-J101 -> 0 | K22: =-K101 -> 0 | L22: =-L101 -> 0 | M22: =-M101 -> 0 | ... ET22: =-ET101 -> 0
B23: Senior Loan | D23: =SUM(F23:ET23) -> 22638101 | F23: =F114+F122 -> 1750000 | G23: =G114+G122 -> 0 | H23: =H114+H122 -> 0 | I23: =I114+I122 -> 0 | J23: =J114+J122 -> 0 | K23: =K114+K122 -> 0 | L23: =L114+L122 -> 0 | M23: =M114+M122 -> 0 | ... ET23: =ET114+ET122 -> 0
B24: Total Sources | D24: =SUM(F24:ET24) -> 30184134 | F24: =SUM(F19:F23) -> 3771575.9 | G24: =SUM(G19:G23) -> 133075.86 | H24: =SUM(H19:H23) -> 133075.86 | I24: =SUM(I19:I23) -> 133075.86 | J24: =SUM(J19:J23) -> 133075.86 | K24: =SUM(K19:K23) -> 133075.86 | L24: =SUM(L19:L23) -> 133075.86 | M24: =SUM(M19:M23) -> 133075.86 | ... ET24: =SUM(ET19:ET23) -> 0
B26: Check | D26: =D17+D24 -> -0.00024098903 | F26: =F17+F24 -> 0 | G26: =G17+G24 -> -8.7311491e-10 | H26: =H17+H24 -> -8.7311491e-10 | I26: =I17+I24 -> -8.7311491e-10 | J26: =J17+J24 -> -8.7311491e-10 | K26: =K17+K24 -> -8.7311491e-10 | L26: =L17+L24 -> -8.7311491e-10 | M26: =M17+M24 -> -8.7311491e-10 | ... ET26: =ET17+ET24 -> 0
B29: Proforma Rental Cash Flow
B30: Residential Occupancy
B31: Occupancy | F31: =E31+F32 -> 0 | G31: =F31+G32 -> 0 | H31: =G31+H32 -> 0 | I31: =H31+I32 -> 0 | J31: =I31+J32 -> 0 | K31: =J31+K32 -> 0 | L31: =K31+L32 -> 0 | M31: =L31+M32 -> 0 | ... ET31: =ES31+ET32 -> 0.95
B32: Lease Up | F32: =IF(F$6=Assumptions!$F$38,Assumptions!$K$17,IF(F$6>Assumptions!$F$38,MIN(Assumptions!$K$18,Assumptions!$K$19-SUM($E$32:E32)),0)) -> 0 | G32: =IF(G$6=Assumptions!$F$38,Assumptions!$K$17,IF(G$6>Assumptions!$F$38,MIN(Assumptions!$K$18,Assumptions!$K$19-SUM($E$32:F32)),0)) -> 0 | H32: =IF(H$6=Assumptions!$F$38,Assumptions!$K$17,IF(H$6>Assumptions!$F$38,MIN(Assumptions!$K$18,Assumptions!$K$19-SUM($E$32:G32)),0)) -> 0 | I32: =IF(I$6=Assumptions!$F$38,Assumptions!$K$17,IF(I$6>Assumptions!$F$38,MIN(Assumptions!$K$18,Assumptions!$K$19-SUM($E$32:H32)),0)) -> 0 | J32: =IF(J$6=Assumptions!$F$38,Assumptions!$K$17,IF(J$6>Assumptions!$F$38,MIN(Assumptions!$K$18,Assumptions!$K$19-SUM($E$32:I32)),0)) -> 0 | K32: =IF(K$6=Assumptions!$F$38,Assumptions!$K$17,IF(K$6>Assumptions!$F$38,MIN(Assumptions!$K$18,Assumptions!$K$19-SUM($E$32:J32)),0)) -> 0 | L32: =IF(L$6=Assumptions!$F$38,Assumptions!$K$17,IF(L$6>Assumptions!$F$38,MIN(Assumptions!$K$18,Assumptions!$K$19-SUM($E$32:K32)),0)) -> 0 | M32: =IF(M$6=Assumptions!$F$38,Assumptions!$K$17,IF(M$6>Assumptions!$F$38,MIN(Assumptions!$K$18,Assumptions!$K$19-SUM($E$32:L32)),0)) -> 0 | ... ET32: =IF(ET$6=Assumptions!$F$38,Assumptions!$K$17,IF(ET$6>Assumptions!$F$38,MIN(Assumptions!$K$18,Assumptions!$K$19-SUM($E$32:ES32)),0)) -> 0
B34: Retail Occupancy
B35: Occupancy | F35: =E35+F36 -> 0 | G35: =F35+G36 -> 0 | H35: =G35+H36 -> 0 | I35: =H35+I36 -> 0 | J35: =I35+J36 -> 0 | K35: =J35+K36 -> 0 | L35: =K35+L36 -> 0 | M35: =L35+M36 -> 0 | ... ET35: =ES35+ET36 -> 1
B36: Lease Up | F36: =IF(F$6=Assumptions!$F$38,Assumptions!$L$17,IF(F$6>Assumptions!$F$38,MIN(Assumptions!$L$18,Assumptions!$L$19-SUM($E$36:E36)),0)) -> 0 | G36: =IF(G$6=Assumptions!$F$38,Assumptions!$L$17,IF(G$6>Assumptions!$F$38,MIN(Assumptions!$L$18,Assumptions!$L$19-SUM($E$36:F36)),0)) -> 0 | H36: =IF(H$6=Assumptions!$F$38,Assumptions!$L$17,IF(H$6>Assumptions!$F$38,MIN(Assumptions!$L$18,Assumptions!$L$19-SUM($E$36:G36)),0)) -> 0 | I36: =IF(I$6=Assumptions!$F$38,Assumptions!$L$17,IF(I$6>Assumptions!$F$38,MIN(Assumptions!$L$18,Assumptions!$L$19-SUM($E$36:H36)),0)) -> 0 | J36: =IF(J$6=Assumptions!$F$38,Assumptions!$L$17,IF(J$6>Assumptions!$F$38,MIN(Assumptions!$L$18,Assumptions!$L$19-SUM($E$36:I36)),0)) -> 0 | K36: =IF(K$6=Assumptions!$F$38,Assumptions!$L$17,IF(K$6>Assumptions!$F$38,MIN(Assumptions!$L$18,Assumptions!$L$19-SUM($E$36:J36)),0)) -> 0 | L36: =IF(L$6=Assumptions!$F$38,Assumptions!$L$17,IF(L$6>Assumptions!$F$38,MIN(Assumptions!$L$18,Assumptions!$L$19-SUM($E$36:K36)),0)) -> 0 | M36: =IF(M$6=Assumptions!$F$38,Assumptions!$L$17,IF(M$6>Assumptions!$F$38,MIN(Assumptions!$L$18,Assumptions!$L$19-SUM($E$36:L36)),0)) -> 0 | ... ET36: =IF(ET$6=Assumptions!$F$38,Assumptions!$L$17,IF(ET$6>Assumptions!$F$38,MIN(Assumptions!$L$18,Assumptions!$L$19-SUM($E$36:ES36)),0)) -> 0
B38: Rental Rates
B39: Residential Market/NSF (Trended) | F39: =IF(Assumptions!$L$8="Yes",IF(F$6>=Assumptions!$F$35,Assumptions!$K$4*(1+Assumptions!$L$4)^ROUNDDOWN(YEARFRAC(F$6,Assumptions!$F$35),0),0),IF(F$6>=Assumptions!$F$38,Assumptions!$K$4*(1+Assumptions!$L$4)^ROUNDDOWN(YEARFRAC(F$6,Assumptions!$F$38),0),0)) -> 3.2694304 | G39: =IF(Assumptions!$L$8="Yes",IF(G$6>=Assumptions!$F$35,Assumptions!$K$4*(1+Assumptions!$L$4)^ROUNDDOWN(YEARFRAC(G$6,Assumptions!$F$35),0),0),IF(G$6>=Assumptions!$F$38,Assumptions!$K$4*(1+Assumptions!$L$4)^ROUNDDOWN(YEARFRAC(G$6,Assumptions!$F$38),0),0)) -> 3.2694304 | H39: =IF(Assumptions!$L$8="Yes",IF(H$6>=Assumptions!$F$35,Assumptions!$K$4*(1+Assumptions!$L$4)^ROUNDDOWN(YEARFRAC(H$6,Assumptions!$F$35),0),0),IF(H$6>=Assumptions!$F$38,Assumptions!$K$4*(1+Assumptions!$L$4)^ROUNDDOWN(YEARFRAC(H$6,Assumptions!$F$38),0),0)) -> 3.2694304 | I39: =IF(Assumptions!$L$8="Yes",IF(I$6>=Assumptions!$F$35,Assumptions!$K$4*(1+Assumptions!$L$4)^ROUNDDOWN(YEARFRAC(I$6,Assumptions!$F$35),0),0),IF(I$6>=Assumptions!$F$38,Assumptions!$K$4*(1+Assumptions!$L$4)^ROUNDDOWN(YEARFRAC(I$6,Assumptions!$F$38),0),0)) -> 3.2694304 | J39: =IF(Assumptions!$L$8="Yes",IF(J$6>=Assumptions!$F$35,Assumptions!$K$4*(1+Assumptions!$L$4)^ROUNDDOWN(YEARFRAC(J$6,Assumptions!$F$35),0),0),IF(J$6>=Assumptions!$F$38,Assumptions!$K$4*(1+Assumptions!$L$4)^ROUNDDOWN(YEARFRAC(J$6,Assumptions!$F$38),0),0)) -> 3.2694304 | K39: =IF(Assumptions!$L$8="Yes",IF(K$6>=Assumptions!$F$35,Assumptions!$K$4*(1+Assumptions!$L$4)^ROUNDDOWN(YEARFRAC(K$6,Assumptions!$F$35),0),0),IF(K$6>=Assumptions!$F$38,Assumptions!$K$4*(1+Assumptions!$L$4)^ROUNDDOWN(YEARFRAC(K$6,Assumptions!$F$38),0),0)) -> 3.2694304 | L39: =IF(Assumptions!$L$8="Yes",IF(L$6>=Assumptions!$F$35,Assumptions!$K$4*(1+Assumptions!$L$4)^ROUNDDOWN(YEARFRAC(L$6,Assumptions!$F$35),0),0),IF(L$6>=Assumptions!$F$38,Assumptions!$K$4*(1+Assumptions!$L$4)^ROUNDDOWN(YEARFRAC(L$6,Assumptions!$F$38),0),0)) -> 3.2694304 | M39: =IF(Assumptions!$L$8="Yes",IF(M$6>=Assumptions!$F$35,Assumptions!$K$4*(1+Assumptions!$L$4)^ROUNDDOWN(YEARFRAC(M$6,Assumptions!$F$35),0),0),IF(M$6>=Assumptions!$F$38,Assumptions!$K$4*(1+Assumptions!$L$4)^ROUNDDOWN(YEARFRAC(M$6,Assumptions!$F$38),0),0)) -> 3.2694304 | ... ET39: =IF(Assumptions!$L$8="Yes",IF(ET$6>=Assumptions!$F$35,Assumptions!$K$4*(1+Assumptions!$L$4)^ROUNDDOWN(YEARFRAC(ET$6,Assumptions!$F$35),0),0),IF(ET$6>=Assumptions!$F$38,Assumptions!$K$4*(1+Assumptions!$L$4)^ROUNDDOWN(YEARFRAC(ET$6,Assumptions!$F$38),0),0)) -> 4.6614259
B40: Retail/NSF | F40: =IF(F$6>=Assumptions!$F$38,Assumptions!$K$5*(1+Assumptions!$L$5)^ROUNDDOWN(YEARFRAC(F$6,Assumptions!$F$38),0),0) -> 0 | G40: =IF(G$6>=Assumptions!$F$38,Assumptions!$K$5*(1+Assumptions!$L$5)^ROUNDDOWN(YEARFRAC(G$6,Assumptions!$F$38),0),0) -> 0 | H40: =IF(H$6>=Assumptions!$F$38,Assumptions!$K$5*(1+Assumptions!$L$5)^ROUNDDOWN(YEARFRAC(H$6,Assumptions!$F$38),0),0) -> 0 | I40: =IF(I$6>=Assumptions!$F$38,Assumptions!$K$5*(1+Assumptions!$L$5)^ROUNDDOWN(YEARFRAC(I$6,Assumptions!$F$38),0),0) -> 0 | J40: =IF(J$6>=Assumptions!$F$38,Assumptions!$K$5*(1+Assumptions!$L$5)^ROUNDDOWN(YEARFRAC(J$6,Assumptions!$F$38),0),0) -> 0 | K40: =IF(K$6>=Assumptions!$F$38,Assumptions!$K$5*(1+Assumptions!$L$5)^ROUNDDOWN(YEARFRAC(K$6,Assumptions!$F$38),0),0) -> 0 | L40: =IF(L$6>=Assumptions!$F$38,Assumptions!$K$5*(1+Assumptions!$L$5)^ROUNDDOWN(YEARFRAC(L$6,Assumptions!$F$38),0),0) -> 0 | M40: =IF(M$6>=Assumptions!$F$38,Assumptions!$K$5*(1+Assumptions!$L$5)^ROUNDDOWN(YEARFRAC(M$6,Assumptions!$F$38),0),0) -> 0 | ... ET40: =IF(ET$6>=Assumptions!$F$38,Assumptions!$K$5*(1+Assumptions!$L$5)^ROUNDDOWN(YEARFRAC(ET$6,Assumptions!$F$38),0),0) -> 3.5228876
B41: Parking/Spot | F41: =IF(F$6>=Assumptions!$F$38,Assumptions!$K$6*(1+Assumptions!$L$6)^ROUNDDOWN(YEARFRAC(F$6,Assumptions!$F$38),0),0) -> 0 | G41: =IF(G$6>=Assumptions!$F$38,Assumptions!$K$6*(1+Assumptions!$L$6)^ROUNDDOWN(YEARFRAC(G$6,Assumptions!$F$38),0),0) -> 0 | H41: =IF(H$6>=Assumptions!$F$38,Assumptions!$K$6*(1+Assumptions!$L$6)^ROUNDDOWN(YEARFRAC(H$6,Assumptions!$F$38),0),0) -> 0 | I41: =IF(I$6>=Assumptions!$F$38,Assumptions!$K$6*(1+Assumptions!$L$6)^ROUNDDOWN(YEARFRAC(I$6,Assumptions!$F$38),0),0) -> 0 | J41: =IF(J$6>=Assumptions!$F$38,Assumptions!$K$6*(1+Assumptions!$L$6)^ROUNDDOWN(YEARFRAC(J$6,Assumptions!$F$38),0),0) -> 0 | K41: =IF(K$6>=Assumptions!$F$38,Assumptions!$K$6*(1+Assumptions!$L$6)^ROUNDDOWN(YEARFRAC(K$6,Assumptions!$F$38),0),0) -> 0 | L41: =IF(L$6>=Assumptions!$F$38,Assumptions!$K$6*(1+Assumptions!$L$6)^ROUNDDOWN(YEARFRAC(L$6,Assumptions!$F$38),0),0) -> 0 | M41: =IF(M$6>=Assumptions!$F$38,Assumptions!$K$6*(1+Assumptions!$L$6)^ROUNDDOWN(YEARFRAC(M$6,Assumptions!$F$38),0),0) -> 0 | ... ET41: =IF(ET$6>=Assumptions!$F$38,Assumptions!$K$6*(1+Assumptions!$L$6)^ROUNDDOWN(YEARFRAC(ET$6,Assumptions!$F$38),0),0) -> 0
B42: Misc Income/Unit | F42: =IF(F$6>=Assumptions!$F$38,Assumptions!$K$7*(1+Assumptions!$L$7)^ROUNDDOWN(YEARFRAC(F$6,Assumptions!$F$38),0),0) -> 0 | G42: =IF(G$6>=Assumptions!$F$38,Assumptions!$K$7*(1+Assumptions!$L$7)^ROUNDDOWN(YEARFRAC(G$6,Assumptions!$F$38),0),0) -> 0 | H42: =IF(H$6>=Assumptions!$F$38,Assumptions!$K$7*(1+Assumptions!$L$7)^ROUNDDOWN(YEARFRAC(H$6,Assumptions!$F$38),0),0) -> 0 | I42: =IF(I$6>=Assumptions!$F$38,Assumptions!$K$7*(1+Assumptions!$L$7)^ROUNDDOWN(YEARFRAC(I$6,Assumptions!$F$38),0),0) -> 0 | J42: =IF(J$6>=Assumptions!$F$38,Assumptions!$K$7*(1+Assumptions!$L$7)^ROUNDDOWN(YEARFRAC(J$6,Assumptions!$F$38),0),0) -> 0 | K42: =IF(K$6>=Assumptions!$F$38,Assumptions!$K$7*(1+Assumptions!$L$7)^ROUNDDOWN(YEARFRAC(K$6,Assumptions!$F$38),0),0) -> 0 | L42: =IF(L$6>=Assumptions!$F$38,Assumptions!$K$7*(1+Assumptions!$L$7)^ROUNDDOWN(YEARFRAC(L$6,Assumptions!$F$38),0),0) -> 0 | M42: =IF(M$6>=Assumptions!$F$38,Assumptions!$K$7*(1+Assumptions!$L$7)^ROUNDDOWN(YEARFRAC(M$6,Assumptions!$F$38),0),0) -> 0 | ... ET42: =IF(ET$6>=Assumptions!$F$38,Assumptions!$K$7*(1+Assumptions!$L$7)^ROUNDDOWN(YEARFRAC(ET$6,Assumptions!$F$38),0),0) -> 195.71598
B44: Gross Potential Residential Income | D44: =SUM(F44:ET44) -> 27371720 | F44: =F39*Assumptions!$F$17 -> 159388 | G44: =G39*Assumptions!$F$17 -> 159388 | H44: =H39*Assumptions!$F$17 -> 159388 | I44: =I39*Assumptions!$F$17 -> 159388 | J44: =J39*Assumptions!$F$17 -> 159388 | K44: =K39*Assumptions!$F$17 -> 159388 | L44: =L39*Assumptions!$F$17 -> 159388 | M44: =M39*Assumptions!$F$17 -> 159388 | ... ET44: =ET39*Assumptions!$F$17 -> 227249.18
B45: Gross Potential Parking Income | D45: =SUM(F45:ET45) -> 0 | F45: =F41*Assumptions!$F$30*Assumptions!$I$6 -> 0 | G45: =G41*Assumptions!$F$30*Assumptions!$I$6 -> 0 | H45: =H41*Assumptions!$F$30*Assumptions!$I$6 -> 0 | I45: =I41*Assumptions!$F$30*Assumptions!$I$6 -> 0 | J45: =J41*Assumptions!$F$30*Assumptions!$I$6 -> 0 | K45: =K41*Assumptions!$F$30*Assumptions!$I$6 -> 0 | L45: =L41*Assumptions!$F$30*Assumptions!$I$6 -> 0 | M45: =M41*Assumptions!$F$30*Assumptions!$I$6 -> 0 | ... ET45: =ET41*Assumptions!$F$30*Assumptions!$I$6 -> 0
B46: Gross Potential Misc Income | D46: =SUM(F46:ET46) -> 1232736.3 | F46: =F42*Assumptions!$C$29 -> 0 | G46: =G42*Assumptions!$C$29 -> 0 | H46: =H42*Assumptions!$C$29 -> 0 | I46: =I42*Assumptions!$C$29 -> 0 | J46: =J42*Assumptions!$C$29 -> 0 | K46: =K42*Assumptions!$C$29 -> 0 | L46: =L42*Assumptions!$C$29 -> 0 | M46: =M42*Assumptions!$C$29 -> 0 | ... ET46: =ET42*Assumptions!$C$29 -> 12917.255
B47: Vacancy Loss | D47: =SUM(F47:ET47) -> -7269318 | F47: =-SUM(F44:F46)*(1-F31) -> -159388 | G47: =-SUM(G44:G46)*(1-G31) -> -159388 | H47: =-SUM(H44:H46)*(1-H31) -> -159388 | I47: =-SUM(I44:I46)*(1-I31) -> -159388 | J47: =-SUM(J44:J46)*(1-J31) -> -159388 | K47: =-SUM(K44:K46)*(1-K31) -> -159388 | L47: =-SUM(L44:L46)*(1-L31) -> -159388 | M47: =-SUM(M44:M46)*(1-M31) -> -159388 | ... ET47: =-SUM(ET44:ET46)*(1-ET31) -> -12008.322
B48: Residential Concessions | D48: =SUM(F48:ET48) -> -69644.329 | F48: =IF(F6<=Assumptions!$F$39,SUM(F44:F47)*-Assumptions!$L$36/12,0) -> 0 | G48: =IF(G6<=Assumptions!$F$39,SUM(G44:G47)*-Assumptions!$L$36/12,0) -> 0 | H48: =IF(H6<=Assumptions!$F$39,SUM(H44:H47)*-Assumptions!$L$36/12,0) -> 0 | I48: =IF(I6<=Assumptions!$F$39,SUM(I44:I47)*-Assumptions!$L$36/12,0) -> 0 | J48: =IF(J6<=Assumptions!$F$39,SUM(J44:J47)*-Assumptions!$L$36/12,0) -> 0 | K48: =IF(K6<=Assumptions!$F$39,SUM(K44:K47)*-Assumptions!$L$36/12,0) -> 0 | L48: =IF(L6<=Assumptions!$F$39,SUM(L44:L47)*-Assumptions!$L$36/12,0) -> 0 | M48: =IF(M6<=Assumptions!$F$39,SUM(M44:M47)*-Assumptions!$L$36/12,0) -> 0 | ... ET48: =IF(ET6<=Assumptions!$F$39,SUM(ET44:ET47)*-Assumptions!$L$36/12,0) -> 0
B49: Effective Net Revenue | D49: =SUM(F49:ET49) -> 21265494 | F49: =SUM(F44:F48) -> 0 | G49: =SUM(G44:G48) -> 0 | H49: =SUM(H44:H48) -> 0 | I49: =SUM(I44:I48) -> 0 | J49: =SUM(J44:J48) -> 0 | K49: =SUM(K44:K48) -> 0 | L49: =SUM(L44:L48) -> 0 | M49: =SUM(M44:M48) -> 0 | ... ET49: =SUM(ET44:ET48) -> 228158.11
B50: Utilities | D50: =SUM(F50:ET50) -> -547882.81 | F50: =-IF(F$6>=Assumptions!$F$38,Assumptions!$L22/12*(1+Assumptions!$K$32)^ROUNDDOWN(YEARFRAC(F$6,Assumptions!$F$38),0),0) -> 0 | G50: =-IF(G$6>=Assumptions!$F$38,Assumptions!$L22/12*(1+Assumptions!$K$32)^ROUNDDOWN(YEARFRAC(G$6,Assumptions!$F$38),0),0) -> 0 | H50: =-IF(H$6>=Assumptions!$F$38,Assumptions!$L22/12*(1+Assumptions!$K$32)^ROUNDDOWN(YEARFRAC(H$6,Assumptions!$F$38),0),0) -> 0 | I50: =-IF(I$6>=Assumptions!$F$38,Assumptions!$L22/12*(1+Assumptions!$K$32)^ROUNDDOWN(YEARFRAC(I$6,Assumptions!$F$38),0),0) -> 0 | J50: =-IF(J$6>=Assumptions!$F$38,Assumptions!$L22/12*(1+Assumptions!$K$32)^ROUNDDOWN(YEARFRAC(J$6,Assumptions!$F$38),0),0) -> 0 | K50: =-IF(K$6>=Assumptions!$F$38,Assumptions!$L22/12*(1+Assumptions!$K$32)^ROUNDDOWN(YEARFRAC(K$6,Assumptions!$F$38),0),0) -> 0 | L50: =-IF(L$6>=Assumptions!$F$38,Assumptions!$L22/12*(1+Assumptions!$K$32)^ROUNDDOWN(YEARFRAC(L$6,Assumptions!$F$38),0),0) -> 0 | M50: =-IF(M$6>=Assumptions!$F$38,Assumptions!$L22/12*(1+Assumptions!$K$32)^ROUNDDOWN(YEARFRAC(M$6,Assumptions!$F$38),0),0) -> 0 | ... ET50: =-IF(ET$6>=Assumptions!$F$38,Assumptions!$L22/12*(1+Assumptions!$K$32)^ROUNDDOWN(YEARFRAC(ET$6,Assumptions!$F$38),0),0) -> -5741.002
B51: Repairs and Maintenance | D51: =SUM(F51:ET51) -> -342426.75 | F51: =-IF(F$6>=Assumptions!$F$38,Assumptions!$L23/12*(1+Assumptions!$K$32)^ROUNDDOWN(YEARFRAC(F$6,Assumptions!$F$38),0),0) -> 0 | G51: =-IF(G$6>=Assumptions!$F$38,Assumptions!$L23/12*(1+Assumptions!$K$32)^ROUNDDOWN(YEARFRAC(G$6,Assumptions!$F$38),0),0) -> 0 | H51: =-IF(H$6>=Assumptions!$F$38,Assumptions!$L23/12*(1+Assumptions!$K$32)^ROUNDDOWN(YEARFRAC(H$6,Assumptions!$F$38),0),0) -> 0 | I51: =-IF(I$6>=Assumptions!$F$38,Assumptions!$L23/12*(1+Assumptions!$K$32)^ROUNDDOWN(YEARFRAC(I$6,Assumptions!$F$38),0),0) -> 0 | J51: =-IF(J$6>=Assumptions!$F$38,Assumptions!$L23/12*(1+Assumptions!$K$32)^ROUNDDOWN(YEARFRAC(J$6,Assumptions!$F$38),0),0) -> 0 | K51: =-IF(K$6>=Assumptions!$F$38,Assumptions!$L23/12*(1+Assumptions!$K$32)^ROUNDDOWN(YEARFRAC(K$6,Assumptions!$F$38),0),0) -> 0 | L51: =-IF(L$6>=Assumptions!$F$38,Assumptions!$L23/12*(1+Assumptions!$K$32)^ROUNDDOWN(YEARFRAC(L$6,Assumptions!$F$38),0),0) -> 0 | M51: =-IF(M$6>=Assumptions!$F$38,Assumptions!$L23/12*(1+Assumptions!$K$32)^ROUNDDOWN(YEARFRAC(M$6,Assumptions!$F$38),0),0) -> 0 | ... ET51: =-IF(ET$6>=Assumptions!$F$38,Assumptions!$L23/12*(1+Assumptions!$K$32)^ROUNDDOWN(YEARFRAC(ET$6,Assumptions!$F$38),0),0) -> -3588.1263
B52: Labor | D52: =SUM(F52:ET52) -> -616368.16 | F52: =-IF(F$6>=Assumptions!$F$38,Assumptions!$L24/12*(1+Assumptions!$K$32)^ROUNDDOWN(YEARFRAC(F$6,Assumptions!$F$38),0),0) -> 0 | G52: =-IF(G$6>=Assumptions!$F$38,Assumptions!$L24/12*(1+Assumptions!$K$32)^ROUNDDOWN(YEARFRAC(G$6,Assumptions!$F$38),0),0) -> 0 | H52: =-IF(H$6>=Assumptions!$F$38,Assumptions!$L24/12*(1+Assumptions!$K$32)^ROUNDDOWN(YEARFRAC(H$6,Assumptions!$F$38),0),0) -> 0 | I52: =-IF(I$6>=Assumptions!$F$38,Assumptions!$L24/12*(1+Assumptions!$K$32)^ROUNDDOWN(YEARFRAC(I$6,Assumptions!$F$38),0),0) -> 0 | J52: =-IF(J$6>=Assumptions!$F$38,Assumptions!$L24/12*(1+Assumptions!$K$32)^ROUNDDOWN(YEARFRAC(J$6,Assumptions!$F$38),0),0) -> 0 | K52: =-IF(K$6>=Assumptions!$F$38,Assumptions!$L24/12*(1+Assumptions!$K$32)^ROUNDDOWN(YEARFRAC(K$6,Assumptions!$F$38),0),0) -> 0 | L52: =-IF(L$6>=Assumptions!$F$38,Assumptions!$L24/12*(1+Assumptions!$K$32)^ROUNDDOWN(YEARFRAC(L$6,Assumptions!$F$38),0),0) -> 0 | M52: =-IF(M$6>=Assumptions!$F$38,Assumptions!$L24/12*(1+Assumptions!$K$32)^ROUNDDOWN(YEARFRAC(M$6,Assumptions!$F$38),0),0) -> 0 | ... ET52: =-IF(ET$6>=Assumptions!$F$38,Assumptions!$L24/12*(1+Assumptions!$K$32)^ROUNDDOWN(YEARFRAC(ET$6,Assumptions!$F$38),0),0) -> -6458.6273
B53: Insurance | D53: =SUM(F53:ET53) -> -239698.73 | F53: =-IF(F$6>=Assumptions!$F$38,Assumptions!$L25/12*(1+Assumptions!$K$32)^ROUNDDOWN(YEARFRAC(F$6,Assumptions!$F$38),0),0) -> 0 | G53: =-IF(G$6>=Assumptions!$F$38,Assumptions!$L25/12*(1+Assumptions!$K$32)^ROUNDDOWN(YEARFRAC(G$6,Assumptions!$F$38),0),0) -> 0 | H53: =-IF(H$6>=Assumptions!$F$38,Assumptions!$L25/12*(1+Assumptions!$K$32)^ROUNDDOWN(YEARFRAC(H$6,Assumptions!$F$38),0),0) -> 0 | I53: =-IF(I$6>=Assumptions!$F$38,Assumptions!$L25/12*(1+Assumptions!$K$32)^ROUNDDOWN(YEARFRAC(I$6,Assumptions!$F$38),0),0) -> 0 | J53: =-IF(J$6>=Assumptions!$F$38,Assumptions!$L25/12*(1+Assumptions!$K$32)^ROUNDDOWN(YEARFRAC(J$6,Assumptions!$F$38),0),0) -> 0 | K53: =-IF(K$6>=Assumptions!$F$38,Assumptions!$L25/12*(1+Assumptions!$K$32)^ROUNDDOWN(YEARFRAC(K$6,Assumptions!$F$38),0),0) -> 0 | L53: =-IF(L$6>=Assumptions!$F$38,Assumptions!$L25/12*(1+Assumptions!$K$32)^ROUNDDOWN(YEARFRAC(L$6,Assumptions!$F$38),0),0) -> 0 | M53: =-IF(M$6>=Assumptions!$F$38,Assumptions!$L25/12*(1+Assumptions!$K$32)^ROUNDDOWN(YEARFRAC(M$6,Assumptions!$F$38),0),0) -> 0 | ... ET53: =-IF(ET$6>=Assumptions!$F$38,Assumptions!$L25/12*(1+Assumptions!$K$32)^ROUNDDOWN(YEARFRAC(ET$6,Assumptions!$F$38),0),0) -> -2511.6884
B54: General & Administrative | D54: =SUM(F54:ET54) -> -239698.73 | F54: =-IF(F$6>=Assumptions!$F$38,Assumptions!$L26/12*(1+Assumptions!$K$32)^ROUNDDOWN(YEARFRAC(F$6,Assumptions!$F$38),0),0) -> 0 | G54: =-IF(G$6>=Assumptions!$F$38,Assumptions!$L26/12*(1+Assumptions!$K$32)^ROUNDDOWN(YEARFRAC(G$6,Assumptions!$F$38),0),0) -> 0 | H54: =-IF(H$6>=Assumptions!$F$38,Assumptions!$L26/12*(1+Assumptions!$K$32)^ROUNDDOWN(YEARFRAC(H$6,Assumptions!$F$38),0),0) -> 0 | I54: =-IF(I$6>=Assumptions!$F$38,Assumptions!$L26/12*(1+Assumptions!$K$32)^ROUNDDOWN(YEARFRAC(I$6,Assumptions!$F$38),0),0) -> 0 | J54: =-IF(J$6>=Assumptions!$F$38,Assumptions!$L26/12*(1+Assumptions!$K$32)^ROUNDDOWN(YEARFRAC(J$6,Assumptions!$F$38),0),0) -> 0 | K54: =-IF(K$6>=Assumptions!$F$38,Assumptions!$L26/12*(1+Assumptions!$K$32)^ROUNDDOWN(YEARFRAC(K$6,Assumptions!$F$38),0),0) -> 0 | L54: =-IF(L$6>=Assumptions!$F$38,Assumptions!$L26/12*(1+Assumptions!$K$32)^ROUNDDOWN(YEARFRAC(L$6,Assumptions!$F$38),0),0) -> 0 | M54: =-IF(M$6>=Assumptions!$F$38,Assumptions!$L26/12*(1+Assumptions!$K$32)^ROUNDDOWN(YEARFRAC(M$6,Assumptions!$F$38),0),0) -> 0 | ... ET54: =-IF(ET$6>=Assumptions!$F$38,Assumptions!$L26/12*(1+Assumptions!$K$32)^ROUNDDOWN(YEARFRAC(ET$6,Assumptions!$F$38),0),0) -> -2511.6884
B55: Marketing/Leasing | D55: =SUM(F55:ET55) -> -205456.05 | F55: =-IF(F$6>=Assumptions!$F$38,Assumptions!$L27/12*(1+Assumptions!$K$32)^ROUNDDOWN(YEARFRAC(F$6,Assumptions!$F$38),0),0) -> 0 | G55: =-IF(G$6>=Assumptions!$F$38,Assumptions!$L27/12*(1+Assumptions!$K$32)^ROUNDDOWN(YEARFRAC(G$6,Assumptions!$F$38),0),0) -> 0 | H55: =-IF(H$6>=Assumptions!$F$38,Assumptions!$L27/12*(1+Assumptions!$K$32)^ROUNDDOWN(YEARFRAC(H$6,Assumptions!$F$38),0),0) -> 0 | I55: =-IF(I$6>=Assumptions!$F$38,Assumptions!$L27/12*(1+Assumptions!$K$32)^ROUNDDOWN(YEARFRAC(I$6,Assumptions!$F$38),0),0) -> 0 | J55: =-IF(J$6>=Assumptions!$F$38,Assumptions!$L27/12*(1+Assumptions!$K$32)^ROUNDDOWN(YEARFRAC(J$6,Assumptions!$F$38),0),0) -> 0 | K55: =-IF(K$6>=Assumptions!$F$38,Assumptions!$L27/12*(1+Assumptions!$K$32)^ROUNDDOWN(YEARFRAC(K$6,Assumptions!$F$38),0),0) -> 0 | L55: =-IF(L$6>=Assumptions!$F$38,Assumptions!$L27/12*(1+Assumptions!$K$32)^ROUNDDOWN(YEARFRAC(L$6,Assumptions!$F$38),0),0) -> 0 | M55: =-IF(M$6>=Assumptions!$F$38,Assumptions!$L27/12*(1+Assumptions!$K$32)^ROUNDDOWN(YEARFRAC(M$6,Assumptions!$F$38),0),0) -> 0 | ... ET55: =-IF(ET$6>=Assumptions!$F$38,Assumptions!$L27/12*(1+Assumptions!$K$32)^ROUNDDOWN(YEARFRAC(ET$6,Assumptions!$F$38),0),0) -> -2152.8758
B56: Turnover | D56: =SUM(F56:ET56) -> 0 | F56: =-IF(F$6>=Assumptions!$F$38,Assumptions!$L28/12*(1+Assumptions!$K$32)^ROUNDDOWN(YEARFRAC(F$6,Assumptions!$F$38),0),0) -> 0 | G56: =-IF(G$6>=Assumptions!$F$38,Assumptions!$L28/12*(1+Assumptions!$K$32)^ROUNDDOWN(YEARFRAC(G$6,Assumptions!$F$38),0),0) -> 0 | H56: =-IF(H$6>=Assumptions!$F$38,Assumptions!$L28/12*(1+Assumptions!$K$32)^ROUNDDOWN(YEARFRAC(H$6,Assumptions!$F$38),0),0) -> 0 | I56: =-IF(I$6>=Assumptions!$F$38,Assumptions!$L28/12*(1+Assumptions!$K$32)^ROUNDDOWN(YEARFRAC(I$6,Assumptions!$F$38),0),0) -> 0 | J56: =-IF(J$6>=Assumptions!$F$38,Assumptions!$L28/12*(1+Assumptions!$K$32)^ROUNDDOWN(YEARFRAC(J$6,Assumptions!$F$38),0),0) -> 0 | K56: =-IF(K$6>=Assumptions!$F$38,Assumptions!$L28/12*(1+Assumptions!$K$32)^ROUNDDOWN(YEARFRAC(K$6,Assumptions!$F$38),0),0) -> 0 | L56: =-IF(L$6>=Assumptions!$F$38,Assumptions!$L28/12*(1+Assumptions!$K$32)^ROUNDDOWN(YEARFRAC(L$6,Assumptions!$F$38),0),0) -> 0 | M56: =-IF(M$6>=Assumptions!$F$38,Assumptions!$L28/12*(1+Assumptions!$K$32)^ROUNDDOWN(YEARFRAC(M$6,Assumptions!$F$38),0),0) -> 0 | ... ET56: =-IF(ET$6>=Assumptions!$F$38,Assumptions!$L28/12*(1+Assumptions!$K$32)^ROUNDDOWN(YEARFRAC(ET$6,Assumptions!$F$38),0),0) -> 0
B57: Management Fee | D57: =SUM(F57:ET57) -> -425309.87 | F57: =-F49*Assumptions!$K$30 -> 0 | G57: =-G49*Assumptions!$K$30 -> 0 | H57: =-H49*Assumptions!$K$30 -> 0 | I57: =-I49*Assumptions!$K$30 -> 0 | J57: =-J49*Assumptions!$K$30 -> 0 | K57: =-K49*Assumptions!$K$30 -> 0 | L57: =-L49*Assumptions!$K$30 -> 0 | M57: =-M49*Assumptions!$K$30 -> 0 | ... ET57: =-ET49*Assumptions!$K$30 -> -4563.1622
B58: Opex Contingency | D58: =SUM(F58:ET58) -> -66154.135 | F58: =SUM(F50:F57,F70)*Assumptions!$K$31 -> 0 | G58: =SUM(G50:G57,G70)*Assumptions!$K$31 -> 0 | H58: =SUM(H50:H57,H70)*Assumptions!$K$31 -> 0 | I58: =SUM(I50:I57,I70)*Assumptions!$K$31 -> 0 | J58: =SUM(J50:J57,J70)*Assumptions!$K$31 -> 0 | K58: =SUM(K50:K57,K70)*Assumptions!$K$31 -> 0 | L58: =SUM(L50:L57,L70)*Assumptions!$K$31 -> 0 | M58: =SUM(M50:M57,M70)*Assumptions!$K$31 -> 0 | ... ET58: =SUM(ET50:ET57,ET70)*Assumptions!$K$31 -> -695.92961
B59: Real Estate Taxes | D59: =SUM(F59:ET59) -> -3963663.4 | F59: =IF(F49>0, -(Taxes!$E$11/12)*(Taxes!$E$26/100), 0) -> 0 | G59: =IF(G49>0, -(Taxes!$E$11/12)*(Taxes!$E$26/100), 0) -> 0 | H59: =IF(H49>0, -(Taxes!$E$11/12)*(Taxes!$E$26/100), 0) -> 0 | I59: =IF(I49>0, -(Taxes!$E$11/12)*(Taxes!$E$26/100), 0) -> 0 | J59: =IF(J49>0, -(Taxes!$E$11/12)*(Taxes!$E$26/100), 0) -> 0 | K59: =IF(K49>0, -(Taxes!$E$11/12)*(Taxes!$E$26/100), 0) -> 0 | L59: =IF(L49>0, -(Taxes!$E$11/12)*(Taxes!$E$26/100), 0) -> 0 | M59: =IF(M49>0, -(Taxes!$E$11/12)*(Taxes!$E$26/100), 0) -> 0 | ... ET59: =IF(ET49>0, -(Taxes!$E$11/12)*(Taxes!$E$26/100), 0) -> -36033.304
B60: CapEx | D60: =SUM(F60:ET60) -> -68485.351 | F60: =-IF(F$6>=Assumptions!$F$38,Assumptions!$L$29/12*(1+Assumptions!$K$32)^ROUNDDOWN(YEARFRAC(F$6,Assumptions!$F$38),0),0) -> 0 | G60: =-IF(G$6>=Assumptions!$F$38,Assumptions!$L$29/12*(1+Assumptions!$K$32)^ROUNDDOWN(YEARFRAC(G$6,Assumptions!$F$38),0),0) -> 0 | H60: =-IF(H$6>=Assumptions!$F$38,Assumptions!$L$29/12*(1+Assumptions!$K$32)^ROUNDDOWN(YEARFRAC(H$6,Assumptions!$F$38),0),0) -> 0 | I60: =-IF(I$6>=Assumptions!$F$38,Assumptions!$L$29/12*(1+Assumptions!$K$32)^ROUNDDOWN(YEARFRAC(I$6,Assumptions!$F$38),0),0) -> 0 | J60: =-IF(J$6>=Assumptions!$F$38,Assumptions!$L$29/12*(1+Assumptions!$K$32)^ROUNDDOWN(YEARFRAC(J$6,Assumptions!$F$38),0),0) -> 0 | K60: =-IF(K$6>=Assumptions!$F$38,Assumptions!$L$29/12*(1+Assumptions!$K$32)^ROUNDDOWN(YEARFRAC(K$6,Assumptions!$F$38),0),0) -> 0 | L60: =-IF(L$6>=Assumptions!$F$38,Assumptions!$L$29/12*(1+Assumptions!$K$32)^ROUNDDOWN(YEARFRAC(L$6,Assumptions!$F$38),0),0) -> 0 | M60: =-IF(M$6>=Assumptions!$F$38,Assumptions!$L$29/12*(1+Assumptions!$K$32)^ROUNDDOWN(YEARFRAC(M$6,Assumptions!$F$38),0),0) -> 0 | ... ET60: =-IF(ET$6>=Assumptions!$F$38,Assumptions!$L$29/12*(1+Assumptions!$K$32)^ROUNDDOWN(YEARFRAC(ET$6,Assumptions!$F$38),0),0) -> -717.62525
B61: Asset Management Fee | D61: =SUM(F61:ET61) -> -84968.816 | F61: =IF(F6>Assumptions!$F$40,0,IF(SUM(F49:F60)>0,-MIN(F49*Assumptions!$K$33,SUM(F49:F60)),0)) -> 0 | G61: =IF(G6>Assumptions!$F$40,0,IF(SUM(G49:G60)>0,-MIN(G49*Assumptions!$K$33,SUM(G49:G60)),0)) -> 0 | H61: =IF(H6>Assumptions!$F$40,0,IF(SUM(H49:H60)>0,-MIN(H49*Assumptions!$K$33,SUM(H49:H60)),0)) -> 0 | I61: =IF(I6>Assumptions!$F$40,0,IF(SUM(I49:I60)>0,-MIN(I49*Assumptions!$K$33,SUM(I49:I60)),0)) -> 0 | J61: =IF(J6>Assumptions!$F$40,0,IF(SUM(J49:J60)>0,-MIN(J49*Assumptions!$K$33,SUM(J49:J60)),0)) -> 0 | K61: =IF(K6>Assumptions!$F$40,0,IF(SUM(K49:K60)>0,-MIN(K49*Assumptions!$K$33,SUM(K49:K60)),0)) -> 0 | L61: =IF(L6>Assumptions!$F$40,0,IF(SUM(L49:L60)>0,-MIN(L49*Assumptions!$K$33,SUM(L49:L60)),0)) -> 0 | M61: =IF(M6>Assumptions!$F$40,0,IF(SUM(M49:M60)>0,-MIN(M49*Assumptions!$K$33,SUM(M49:M60)),0)) -> 0 | ... ET61: =IF(ET6>Assumptions!$F$40,0,IF(SUM(ET49:ET60)>0,-MIN(ET49*Assumptions!$K$33,SUM(ET49:ET60)),0)) -> 0
B62: Total Expenses | D62: =SUM(F62:ET62) -> -6800112.8 | F62: =SUM(F50:F61) -> 0 | G62: =SUM(G50:G61) -> 0 | H62: =SUM(H50:H61) -> 0 | I62: =SUM(I50:I61) -> 0 | J62: =SUM(J50:J61) -> 0 | K62: =SUM(K50:K61) -> 0 | L62: =SUM(L50:L61) -> 0 | M62: =SUM(M50:M61) -> 0 | ... ET62: =SUM(ET50:ET61) -> -64974.029
B63: Rental NOI | D63: =SUM(F63:ET63) -> 14465381 | F63: =F49+F62 -> 0 | G63: =G49+G62 -> 0 | H63: =H49+H62 -> 0 | I63: =I49+I62 -> 0 | J63: =J49+J62 -> 0 | K63: =K49+K62 -> 0 | L63: =L49+L62 -> 0 | M63: =M49+M62 -> 0 | ... ET63: =ET49+ET62 -> 163184.08
BB64: =BB62/Assumptions!F17*12 -> -14.936427 | BC64: =BC62/BC49 -> -0.33690767
B65: Tax Reassessment at Sale | F65: =IF(Assumptions!$L$43="Yes",IF(F6=Assumptions!$F$40,MIN(-(F80+F82)*Assumptions!$L$44*Assumptions!$L$45*(1-Assumptions!$L$46),SUM(G59:R59)),0),IF(F6=Assumptions!$F$40,SUM(G59:R59),0)) -> 0 | G65: =IF(Assumptions!$L$43="Yes",IF(G6=Assumptions!$F$40,MIN(-(G80+G82)*Assumptions!$L$44*Assumptions!$L$45*(1-Assumptions!$L$46),SUM(H59:S59)),0),IF(G6=Assumptions!$F$40,SUM(H59:S59),0)) -> 0 | H65: =IF(Assumptions!$L$43="Yes",IF(H6=Assumptions!$F$40,MIN(-(H80+H82)*Assumptions!$L$44*Assumptions!$L$45*(1-Assumptions!$L$46),SUM(I59:T59)),0),IF(H6=Assumptions!$F$40,SUM(I59:T59),0)) -> 0 | I65: =IF(Assumptions!$L$43="Yes",IF(I6=Assumptions!$F$40,MIN(-(I80+I82)*Assumptions!$L$44*Assumptions!$L$45*(1-Assumptions!$L$46),SUM(J59:U59)),0),IF(I6=Assumptions!$F$40,SUM(J59:U59),0)) -> 0 | J65: =IF(Assumptions!$L$43="Yes",IF(J6=Assumptions!$F$40,MIN(-(J80+J82)*Assumptions!$L$44*Assumptions!$L$45*(1-Assumptions!$L$46),SUM(K59:V59)),0),IF(J6=Assumptions!$F$40,SUM(K59:V59),0)) -> 0 | K65: =IF(Assumptions!$L$43="Yes",IF(K6=Assumptions!$F$40,MIN(-(K80+K82)*Assumptions!$L$44*Assumptions!$L$45*(1-Assumptions!$L$46),SUM(L59:W59)),0),IF(K6=Assumptions!$F$40,SUM(L59:W59),0)) -> 0 | L65: =IF(Assumptions!$L$43="Yes",IF(L6=Assumptions!$F$40,MIN(-(L80+L82)*Assumptions!$L$44*Assumptions!$L$45*(1-Assumptions!$L$46),SUM(M59:X59)),0),IF(L6=Assumptions!$F$40,SUM(M59:X59),0)) -> 0 | M65: =IF(Assumptions!$L$43="Yes",IF(M6=Assumptions!$F$40,MIN(-(M80+M82)*Assumptions!$L$44*Assumptions!$L$45*(1-Assumptions!$L$46),SUM(N59:Y59)),0),IF(M6=Assumptions!$F$40,SUM(N59:Y59),0)) -> 0 | ... ET65: =IF(Assumptions!$L$43="Yes",IF(ET6=Assumptions!$F$40,MIN(-(ET80+ET82)*Assumptions!$L$44*Assumptions!$L$45*(1-Assumptions!$L$46),SUM(EU59:FF59)),0),IF(ET6=Assumptions!$F$40,SUM(EU59:FF59),0)) -> 0
B66: Forward 12 Months Rental NOI Post Reassessment | F66: =IF(Assumptions!$L$43="Yes",IF(F6=Assumptions!$F$40,SUM('Draw Schedule'!G63:R63)-SUM('Draw Schedule'!G60:R60)-SUM('Draw Schedule'!G59:R59)+'Draw Schedule'!F65,0),IF(F6=Assumptions!$F$40,SUM('Draw Schedule'!G63:R63)-SUM('Draw Schedule'!G60:R60),0)) -> 0 | G66: =IF(Assumptions!$L$43="Yes",IF(G6=Assumptions!$F$40,SUM('Draw Schedule'!H63:S63)-SUM('Draw Schedule'!H60:S60)-SUM('Draw Schedule'!H59:S59)+'Draw Schedule'!G65,0),IF(G6=Assumptions!$F$40,SUM('Draw Schedule'!H63:S63)-SUM('Draw Schedule'!H60:S60),0)) -> 0 | H66: =IF(Assumptions!$L$43="Yes",IF(H6=Assumptions!$F$40,SUM('Draw Schedule'!I63:T63)-SUM('Draw Schedule'!I60:T60)-SUM('Draw Schedule'!I59:T59)+'Draw Schedule'!H65,0),IF(H6=Assumptions!$F$40,SUM('Draw Schedule'!I63:T63)-SUM('Draw Schedule'!I60:T60),0)) -> 0 | I66: =IF(Assumptions!$L$43="Yes",IF(I6=Assumptions!$F$40,SUM('Draw Schedule'!J63:U63)-SUM('Draw Schedule'!J60:U60)-SUM('Draw Schedule'!J59:U59)+'Draw Schedule'!I65,0),IF(I6=Assumptions!$F$40,SUM('Draw Schedule'!J63:U63)-SUM('Draw Schedule'!J60:U60),0)) -> 0 | J66: =IF(Assumptions!$L$43="Yes",IF(J6=Assumptions!$F$40,SUM('Draw Schedule'!K63:V63)-SUM('Draw Schedule'!K60:V60)-SUM('Draw Schedule'!K59:V59)+'Draw Schedule'!J65,0),IF(J6=Assumptions!$F$40,SUM('Draw Schedule'!K63:V63)-SUM('Draw Schedule'!K60:V60),0)) -> 0 | K66: =IF(Assumptions!$L$43="Yes",IF(K6=Assumptions!$F$40,SUM('Draw Schedule'!L63:W63)-SUM('Draw Schedule'!L60:W60)-SUM('Draw Schedule'!L59:W59)+'Draw Schedule'!K65,0),IF(K6=Assumptions!$F$40,SUM('Draw Schedule'!L63:W63)-SUM('Draw Schedule'!L60:W60),0)) -> 0 | L66: =IF(Assumptions!$L$43="Yes",IF(L6=Assumptions!$F$40,SUM('Draw Schedule'!M63:X63)-SUM('Draw Schedule'!M60:X60)-SUM('Draw Schedule'!M59:X59)+'Draw Schedule'!L65,0),IF(L6=Assumptions!$F$40,SUM('Draw Schedule'!M63:X63)-SUM('Draw Schedule'!M60:X60),0)) -> 0 | M66: =IF(Assumptions!$L$43="Yes",IF(M6=Assumptions!$F$40,SUM('Draw Schedule'!N63:Y63)-SUM('Draw Schedule'!N60:Y60)-SUM('Draw Schedule'!N59:Y59)+'Draw Schedule'!M65,0),IF(M6=Assumptions!$F$40,SUM('Draw Schedule'!N63:Y63)-SUM('Draw Schedule'!N60:Y60),0)) -> 0 | ... ET66: =IF(Assumptions!$L$43="Yes",IF(ET6=Assumptions!$F$40,SUM('Draw Schedule'!EU63:FF63)-SUM('Draw Schedule'!EU60:FF60)-SUM('Draw Schedule'!EU59:FF59)+'Draw Schedule'!ET65,0),IF(ET6=Assumptions!$F$40,SUM('Draw Schedule'!EU63:FF63)-SUM('Draw Schedule'!EU60:FF60),0)) -> 0
B68: Retail Income | F68: =F40*Assumptions!$F$16 -> 0 | G68: =G40*Assumptions!$F$16 -> 0 | H68: =H40*Assumptions!$F$16 -> 0 | I68: =I40*Assumptions!$F$16 -> 0 | J68: =J40*Assumptions!$F$16 -> 0 | K68: =K40*Assumptions!$F$16 -> 0 | L68: =L40*Assumptions!$F$16 -> 0 | M68: =M40*Assumptions!$F$16 -> 0 | ... ET68: =ET40*Assumptions!$F$16 -> 15500.705
B69: Vacancy Loss | F69: =-F68*(1-F35) -> 0 | G69: =-G68*(1-G35) -> 0 | H69: =-H68*(1-H35) -> 0 | I69: =-I68*(1-I35) -> 0 | J69: =-J68*(1-J35) -> 0 | K69: =-K68*(1-K35) -> 0 | L69: =-L68*(1-L35) -> 0 | M69: =-M68*(1-M35) -> 0 | ... ET69: =-ET68*(1-ET35) -> 0
B70: Management Fee | F70: =-SUM(F68:F69)*Assumptions!$K$30 -> 0 | G70: =-SUM(G68:G69)*Assumptions!$K$30 -> 0 | H70: =-SUM(H68:H69)*Assumptions!$K$30 -> 0 | I70: =-SUM(I68:I69)*Assumptions!$K$30 -> 0 | J70: =-SUM(J68:J69)*Assumptions!$K$30 -> 0 | K70: =-SUM(K68:K69)*Assumptions!$K$30 -> 0 | L70: =-SUM(L68:L69)*Assumptions!$K$30 -> 0 | M70: =-SUM(M68:M69)*Assumptions!$K$30 -> 0 | ... ET70: =-SUM(ET68:ET69)*Assumptions!$K$30 -> -310.01411
B71: Retail Concessions | F71: =IF(AND(F6<=EDATE(Assumptions!$F$38,Assumptions!$L$35-1),Assumptions!$L$35>=1),-SUM(F68:F70),0) -> 0 | G71: =IF(AND(G6<=EDATE(Assumptions!$F$38,Assumptions!$L$35-1),Assumptions!$L$35>=1),-SUM(G68:G70),0) -> 0 | H71: =IF(AND(H6<=EDATE(Assumptions!$F$38,Assumptions!$L$35-1),Assumptions!$L$35>=1),-SUM(H68:H70),0) -> 0 | I71: =IF(AND(I6<=EDATE(Assumptions!$F$38,Assumptions!$L$35-1),Assumptions!$L$35>=1),-SUM(I68:I70),0) -> 0 | J71: =IF(AND(J6<=EDATE(Assumptions!$F$38,Assumptions!$L$35-1),Assumptions!$L$35>=1),-SUM(J68:J70),0) -> 0 | K71: =IF(AND(K6<=EDATE(Assumptions!$F$38,Assumptions!$L$35-1),Assumptions!$L$35>=1),-SUM(K68:K70),0) -> 0 | L71: =IF(AND(L6<=EDATE(Assumptions!$F$38,Assumptions!$L$35-1),Assumptions!$L$35>=1),-SUM(L68:L70),0) -> 0 | M71: =IF(AND(M6<=EDATE(Assumptions!$F$38,Assumptions!$L$35-1),Assumptions!$L$35>=1),-SUM(M68:M70),0) -> 0 | ... ET71: =IF(AND(ET6<=EDATE(Assumptions!$F$38,Assumptions!$L$35-1),Assumptions!$L$35>=1),-SUM(ET68:ET70),0) -> 0
B72: Asset Management Fee | D72: =SUM(F72:ET72) -> -5860.2891 | F72: =IF(F6>Assumptions!$F$40,0,IF(SUM(F68:F71)>0,-MIN(F68*Assumptions!$K$33,SUM(F68:F71)),0)) -> 0 | G72: =IF(G6>Assumptions!$F$40,0,IF(SUM(G68:G71)>0,-MIN(G68*Assumptions!$K$33,SUM(G68:G71)),0)) -> 0 | H72: =IF(H6>Assumptions!$F$40,0,IF(SUM(H68:H71)>0,-MIN(H68*Assumptions!$K$33,SUM(H68:H71)),0)) -> 0 | I72: =IF(I6>Assumptions!$F$40,0,IF(SUM(I68:I71)>0,-MIN(I68*Assumptions!$K$33,SUM(I68:I71)),0)) -> 0 | J72: =IF(J6>Assumptions!$F$40,0,IF(SUM(J68:J71)>0,-MIN(J68*Assumptions!$K$33,SUM(J68:J71)),0)) -> 0 | K72: =IF(K6>Assumptions!$F$40,0,IF(SUM(K68:K71)>0,-MIN(K68*Assumptions!$K$33,SUM(K68:K71)),0)) -> 0 | L72: =IF(L6>Assumptions!$F$40,0,IF(SUM(L68:L71)>0,-MIN(L68*Assumptions!$K$33,SUM(L68:L71)),0)) -> 0 | M72: =IF(M6>Assumptions!$F$40,0,IF(SUM(M68:M71)>0,-MIN(M68*Assumptions!$K$33,SUM(M68:M71)),0)) -> 0 | ... ET72: =IF(ET6>Assumptions!$F$40,0,IF(SUM(ET68:ET71)>0,-MIN(ET68*Assumptions!$K$33,SUM(ET68:ET71)),0)) -> 0
B73: Retail NOI | D73: =SUM(F73:ET73) -> 1417642.2 | F73: =SUM(F68:F72) -> 0 | G73: =SUM(G68:G72) -> 0 | H73: =SUM(H68:H72) -> 0 | I73: =SUM(I68:I72) -> 0 | J73: =SUM(J68:J72) -> 0 | K73: =SUM(K68:K72) -> 0 | L73: =SUM(L68:L72) -> 0 | M73: =SUM(M68:M72) -> 0 | ... ET73: =SUM(ET68:ET72) -> 15190.691
B75: Ground Lease Rent | F75: =IF(Assumptions!$Q$24="Yes",-IF(F6<Assumptions!$P$26,0,(-SUM($F$101:F101)*Assumptions!$Q$29/12)*(1+Assumptions!$Q$27)^ROUNDDOWN(YEARFRAC(F6,Assumptions!$P$26),0)),0) -> 0 | G75: =IF(Assumptions!$Q$24="Yes",-IF(G6<Assumptions!$P$26,0,(-SUM($F$101:G101)*Assumptions!$Q$29/12)*(1+Assumptions!$Q$27)^ROUNDDOWN(YEARFRAC(G6,Assumptions!$P$26),0)),0) -> 0 | H75: =IF(Assumptions!$Q$24="Yes",-IF(H6<Assumptions!$P$26,0,(-SUM($F$101:H101)*Assumptions!$Q$29/12)*(1+Assumptions!$Q$27)^ROUNDDOWN(YEARFRAC(H6,Assumptions!$P$26),0)),0) -> 0 | I75: =IF(Assumptions!$Q$24="Yes",-IF(I6<Assumptions!$P$26,0,(-SUM($F$101:I101)*Assumptions!$Q$29/12)*(1+Assumptions!$Q$27)^ROUNDDOWN(YEARFRAC(I6,Assumptions!$P$26),0)),0) -> 0 | J75: =IF(Assumptions!$Q$24="Yes",-IF(J6<Assumptions!$P$26,0,(-SUM($F$101:J101)*Assumptions!$Q$29/12)*(1+Assumptions!$Q$27)^ROUNDDOWN(YEARFRAC(J6,Assumptions!$P$26),0)),0) -> 0 | K75: =IF(Assumptions!$Q$24="Yes",-IF(K6<Assumptions!$P$26,0,(-SUM($F$101:K101)*Assumptions!$Q$29/12)*(1+Assumptions!$Q$27)^ROUNDDOWN(YEARFRAC(K6,Assumptions!$P$26),0)),0) -> 0 | L75: =IF(Assumptions!$Q$24="Yes",-IF(L6<Assumptions!$P$26,0,(-SUM($F$101:L101)*Assumptions!$Q$29/12)*(1+Assumptions!$Q$27)^ROUNDDOWN(YEARFRAC(L6,Assumptions!$P$26),0)),0) -> 0 | M75: =IF(Assumptions!$Q$24="Yes",-IF(M6<Assumptions!$P$26,0,(-SUM($F$101:M101)*Assumptions!$Q$29/12)*(1+Assumptions!$Q$27)^ROUNDDOWN(YEARFRAC(M6,Assumptions!$P$26),0)),0) -> 0 | ... ET75: =IF(Assumptions!$Q$24="Yes",-IF(ET6<Assumptions!$P$26,0,(-SUM($F$101:ET101)*Assumptions!$Q$29/12)*(1+Assumptions!$Q$27)^ROUNDDOWN(YEARFRAC(ET6,Assumptions!$P$26),0)),0) -> 0
B77: Total NOI After Ground Lease | F77: =F63+F73+F75 -> 0 | G77: =G63+G73+G75 -> 0 | H77: =H63+H73+H75 -> 0 | I77: =I63+I73+I75 -> 0 | J77: =J63+J73+J75 -> 0 | K77: =K63+K73+K75 -> 0 | L77: =L63+L73+L75 -> 0 | M77: =M63+M73+M75 -> 0 | ... ET77: =ET63+ET73+ET75 -> 178374.77
B79: Rental Sales Proceeds
B80: Gross Resi Sales Proceeds | D80: =SUM(F80:ET80) -> 32737809 | F80: =IF(F6=Assumptions!$F$40,(F66+SUM(G75:R75)*(SUM(G63:R63)/SUM(G63:R63,G73:R73)))/IF(Assumptions!$Q$24="No",Assumptions!$K$12,Assumptions!$K$12+Assumptions!$Q$30),0) -> 0 | G80: =IF(G6=Assumptions!$F$40,(G66+SUM(H75:S75)*(SUM(H63:S63)/SUM(H63:S63,H73:S73)))/IF(Assumptions!$Q$24="No",Assumptions!$K$12,Assumptions!$K$12+Assumptions!$Q$30),0) -> 0 | H80: =IF(H6=Assumptions!$F$40,(H66+SUM(I75:T75)*(SUM(I63:T63)/SUM(I63:T63,I73:T73)))/IF(Assumptions!$Q$24="No",Assumptions!$K$12,Assumptions!$K$12+Assumptions!$Q$30),0) -> 0 | I80: =IF(I6=Assumptions!$F$40,(I66+SUM(J75:U75)*(SUM(J63:U63)/SUM(J63:U63,J73:U73)))/IF(Assumptions!$Q$24="No",Assumptions!$K$12,Assumptions!$K$12+Assumptions!$Q$30),0) -> 0 | J80: =IF(J6=Assumptions!$F$40,(J66+SUM(K75:V75)*(SUM(K63:V63)/SUM(K63:V63,K73:V73)))/IF(Assumptions!$Q$24="No",Assumptions!$K$12,Assumptions!$K$12+Assumptions!$Q$30),0) -> 0 | K80: =IF(K6=Assumptions!$F$40,(K66+SUM(L75:W75)*(SUM(L63:W63)/SUM(L63:W63,L73:W73)))/IF(Assumptions!$Q$24="No",Assumptions!$K$12,Assumptions!$K$12+Assumptions!$Q$30),0) -> 0 | L80: =IF(L6=Assumptions!$F$40,(L66+SUM(M75:X75)*(SUM(M63:X63)/SUM(M63:X63,M73:X73)))/IF(Assumptions!$Q$24="No",Assumptions!$K$12,Assumptions!$K$12+Assumptions!$Q$30),0) -> 0 | M80: =IF(M6=Assumptions!$F$40,(M66+SUM(N75:Y75)*(SUM(N63:Y63)/SUM(N63:Y63,N73:Y73)))/IF(Assumptions!$Q$24="No",Assumptions!$K$12,Assumptions!$K$12+Assumptions!$Q$30),0) -> 0 | ... ET80: =IF(ET6=Assumptions!$F$40,(ET66+SUM(EU75:FF75)*(SUM(EU63:FF63)/SUM(EU63:FF63,EU73:FF73)))/IF(Assumptions!$Q$24="No",Assumptions!$K$12,Assumptions!$K$12+Assumptions!$Q$30),0) -> 0
B81: Resi Sales Costs | D81: =SUM(F81:ET81) -> -327378.09 | F81: =-F80*Assumptions!$L$12 -> 0 | G81: =-G80*Assumptions!$L$12 -> 0 | H81: =-H80*Assumptions!$L$12 -> 0 | I81: =-I80*Assumptions!$L$12 -> 0 | J81: =-J80*Assumptions!$L$12 -> 0 | K81: =-K80*Assumptions!$L$12 -> 0 | L81: =-L80*Assumptions!$L$12 -> 0 | M81: =-M80*Assumptions!$L$12 -> 0 | ... ET81: =-ET80*Assumptions!$L$12 -> 0
B82: Gross Retail Sales Proceeds | D82: =SUM(F82:ET82) -> 2866119.9 | F82: =IF(F6=Assumptions!$F$41,(SUM(G73:R73)+SUM(G75:R75)*(SUM(G73:R73)/SUM(G63:R63,G73:R73)))/IF(Assumptions!$Q$24="No",Assumptions!$K$13,Assumptions!$K$13+Assumptions!$Q$30),0) -> 0 | G82: =IF(G6=Assumptions!$F$41,(SUM(H73:S73)+SUM(H75:S75)*(SUM(H73:S73)/SUM(H63:S63,H73:S73)))/IF(Assumptions!$Q$24="No",Assumptions!$K$13,Assumptions!$K$13+Assumptions!$Q$30),0) -> 0 | H82: =IF(H6=Assumptions!$F$41,(SUM(I73:T73)+SUM(I75:T75)*(SUM(I73:T73)/SUM(I63:T63,I73:T73)))/IF(Assumptions!$Q$24="No",Assumptions!$K$13,Assumptions!$K$13+Assumptions!$Q$30),0) -> 0 | I82: =IF(I6=Assumptions!$F$41,(SUM(J73:U73)+SUM(J75:U75)*(SUM(J73:U73)/SUM(J63:U63,J73:U73)))/IF(Assumptions!$Q$24="No",Assumptions!$K$13,Assumptions!$K$13+Assumptions!$Q$30),0) -> 0 | J82: =IF(J6=Assumptions!$F$41,(SUM(K73:V73)+SUM(K75:V75)*(SUM(K73:V73)/SUM(K63:V63,K73:V73)))/IF(Assumptions!$Q$24="No",Assumptions!$K$13,Assumptions!$K$13+Assumptions!$Q$30),0) -> 0 | K82: =IF(K6=Assumptions!$F$41,(SUM(L73:W73)+SUM(L75:W75)*(SUM(L73:W73)/SUM(L63:W63,L73:W73)))/IF(Assumptions!$Q$24="No",Assumptions!$K$13,Assumptions!$K$13+Assumptions!$Q$30),0) -> 0 | L82: =IF(L6=Assumptions!$F$41,(SUM(M73:X73)+SUM(M75:X75)*(SUM(M73:X73)/SUM(M63:X63,M73:X73)))/IF(Assumptions!$Q$24="No",Assumptions!$K$13,Assumptions!$K$13+Assumptions!$Q$30),0) -> 0 | M82: =IF(M6=Assumptions!$F$41,(SUM(N73:Y73)+SUM(N75:Y75)*(SUM(N73:Y73)/SUM(N63:Y63,N73:Y73)))/IF(Assumptions!$Q$24="No",Assumptions!$K$13,Assumptions!$K$13+Assumptions!$Q$30),0) -> 0 | ... ET82: =IF(ET6=Assumptions!$F$41,(SUM(EU73:FF73)+SUM(EU75:FF75)*(SUM(EU73:FF73)/SUM(EU63:FF63,EU73:FF73)))/IF(Assumptions!$Q$24="No",Assumptions!$K$13,Assumptions!$K$13+Assumptions!$Q$30),0) -> 0
B83: Retail Sales Costs | D83: =SUM(F83:ET83) -> -100314.2 | F83: =-F82*Assumptions!$L$13 -> 0 | G83: =-G82*Assumptions!$L$13 -> 0 | H83: =-H82*Assumptions!$L$13 -> 0 | I83: =-I82*Assumptions!$L$13 -> 0 | J83: =-J82*Assumptions!$L$13 -> 0 | K83: =-K82*Assumptions!$L$13 -> 0 | L83: =-L82*Assumptions!$L$13 -> 0 | M83: =-M82*Assumptions!$L$13 -> 0 | ... ET83: =-ET82*Assumptions!$L$13 -> 0
B84: Total Net Sales Proceeds | D84: =SUM(F84:ET84) -> 35176236 | F84: =SUM(F80:F83) -> 0 | G84: =SUM(G80:G83) -> 0 | H84: =SUM(H80:H83) -> 0 | I84: =SUM(I80:I83) -> 0 | J84: =SUM(J80:J83) -> 0 | K84: =SUM(K80:K83) -> 0 | L84: =SUM(L80:L83) -> 0 | M84: =SUM(M80:M83) -> 0 | ... ET84: =SUM(ET80:ET83) -> 0
B87: Equity Balance
B88: Beginning Balance | F88: =Assumptions!T17 -> 7546033.5 | G88: =F90 -> 5524457.7 | H88: =G90 -> 5391381.8 | I88: =H90 -> 5258306 | J88: =I90 -> 5125230.1 | K88: =J90 -> 4992154.2 | L88: =K90 -> 4859078.4 | M88: =L90 -> 4726002.5 | N88: =M90 -> 4592926.7 | ... ET88: =ES90 -> 0
B89: Draw | F89: =-MIN(F88,-F17-F114) -> -2021575.9 | G89: =-MIN(G88,-G17-G114) -> -133075.86 | H89: =-MIN(H88,-H17-H114) -> -133075.86 | I89: =-MIN(I88,-I17-I114) -> -133075.86 | J89: =-MIN(J88,-J17-J114) -> -133075.86 | K89: =-MIN(K88,-K17-K114) -> -133075.86 | L89: =-MIN(L88,-L17-L114) -> -133075.86 | M89: =-MIN(M88,-M17-M114) -> -133075.86 | ... ET89: =-MIN(ET88,-ET17-ET114) -> 0
B90: Ending Balance | F90: =SUM(F88:F89) -> 5524457.7 | G90: =SUM(G88:G89) -> 5391381.8 | H90: =SUM(H88:H89) -> 5258306 | I90: =SUM(I88:I89) -> 5125230.1 | J90: =SUM(J88:J89) -> 4992154.2 | K90: =SUM(K88:K89) -> 4859078.4 | L90: =SUM(L88:L89) -> 4726002.5 | M90: =SUM(M88:M89) -> 4592926.7 | ... ET90: =SUM(ET88:ET89) -> 0
B92: Mezz Loan Reserve
B93: Beginning Balance | F93: =E96 -> 0 | G93: =F96 -> 0 | H93: =G96 -> 0 | I93: =H96 -> 0 | J93: =I96 -> 0 | K93: =J96 -> 0 | L93: =K96 -> 0 | M93: =L96 -> 0 | ... ET93: =ES96 -> 0
B94: Closing | F94: =IF(F$6=Assumptions!$P$18,Assumptions!$Q$17,0) -> 0 | G94: =IF(G$6=Assumptions!$P$18,Assumptions!$Q$17,0) -> 0 | H94: =IF(H$6=Assumptions!$P$18,Assumptions!$Q$17,0) -> 0 | I94: =IF(I$6=Assumptions!$P$18,Assumptions!$Q$17,0) -> 0 | J94: =IF(J$6=Assumptions!$P$18,Assumptions!$Q$17,0) -> 0 | K94: =IF(K$6=Assumptions!$P$18,Assumptions!$Q$17,0) -> 0 | L94: =IF(L$6=Assumptions!$P$18,Assumptions!$Q$17,0) -> 0 | M94: =IF(M$6=Assumptions!$P$18,Assumptions!$Q$17,0) -> 0 | ... ET94: =IF(ET$6=Assumptions!$P$18,Assumptions!$Q$17,0) -> 0
B95: Draw | F95: =IF(F6<Assumptions!$P$18,0,-MIN(-F17+F89+F114,F93+F94)) -> 0 | G95: =IF(G6<Assumptions!$P$18,0,-MIN(-G17+G89+G114,G93+G94)) -> 0 | H95: =IF(H6<Assumptions!$P$18,0,-MIN(-H17+H89+H114,H93+H94)) -> 0 | I95: =IF(I6<Assumptions!$P$18,0,-MIN(-I17+I89+I114,I93+I94)) -> 0 | J95: =IF(J6<Assumptions!$P$18,0,-MIN(-J17+J89+J114,J93+J94)) -> 0 | K95: =IF(K6<Assumptions!$P$18,0,-MIN(-K17+K89+K114,K93+K94)) -> 0 | L95: =IF(L6<Assumptions!$P$18,0,-MIN(-L17+L89+L114,L93+L94)) -> 0 | M95: =IF(M6<Assumptions!$P$18,0,-MIN(-M17+M89+M114,M93+M94)) -> 0 | ... ET95: =IF(ET6<Assumptions!$P$18,0,-MIN(-ET17+ET89+ET114,ET93+ET94)) -> 0
B96: Ending Balance | F96: =SUM(F93:F95) -> 0 | G96: =SUM(G93:G95) -> 0 | H96: =SUM(H93:H95) -> 0 | I96: =SUM(I93:I95) -> 0 | J96: =SUM(J93:J95) -> 0 | K96: =SUM(K93:K95) -> 0 | L96: =SUM(L93:L95) -> 0 | M96: =SUM(M93:M95) -> 0 | ... ET96: =SUM(ET93:ET95) -> 0
B98: Ground Lease Draw Schedule
B99: Beginning Balance | F99: =E102 -> 0 | G99: =F102 -> 0 | H99: =G102 -> 0 | I99: =H102 -> 0 | J99: =I102 -> 0 | K99: =J102 -> 0 | L99: =K102 -> 0 | M99: =L102 -> 0 | ... ET99: =ES102 -> 0
B100: Closing | F100: =IF(Assumptions!$Q$24="Yes",IF(F$6=Assumptions!$P$26,Assumptions!$Q$25,0),0) -> 0 | G100: =IF(Assumptions!$Q$24="Yes",IF(G$6=Assumptions!$P$26,Assumptions!$Q$25,0),0) -> 0 | H100: =IF(Assumptions!$Q$24="Yes",IF(H$6=Assumptions!$P$26,Assumptions!$Q$25,0),0) -> 0 | I100: =IF(Assumptions!$Q$24="Yes",IF(I$6=Assumptions!$P$26,Assumptions!$Q$25,0),0) -> 0 | J100: =IF(Assumptions!$Q$24="Yes",IF(J$6=Assumptions!$P$26,Assumptions!$Q$25,0),0) -> 0 | K100: =IF(Assumptions!$Q$24="Yes",IF(K$6=Assumptions!$P$26,Assumptions!$Q$25,0),0) -> 0 | L100: =IF(Assumptions!$Q$24="Yes",IF(L$6=Assumptions!$P$26,Assumptions!$Q$25,0),0) -> 0 | M100: =IF(Assumptions!$Q$24="Yes",IF(M$6=Assumptions!$P$26,Assumptions!$Q$25,0),0) -> 0 | ... ET100: =IF(Assumptions!$Q$24="Yes",IF(ET$6=Assumptions!$P$26,Assumptions!$Q$25,0),0) -> 0
B101: Draw | F101: =IF(F6<Assumptions!$P$26,0,-MIN(-F17+F89+F114,F99+F100)) -> 0 | G101: =IF(G6<Assumptions!$P$26,0,-MIN(-G17+G89+G114,G99+G100)) -> 0 | H101: =IF(H6<Assumptions!$P$26,0,-MIN(-H17+H89+H114,H99+H100)) -> 0 | I101: =IF(I6<Assumptions!$P$26,0,-MIN(-I17+I89+I114,I99+I100)) -> 0 | J101: =IF(J6<Assumptions!$P$26,0,-MIN(-J17+J89+J114,J99+J100)) -> 0 | K101: =IF(K6<Assumptions!$P$26,0,-MIN(-K17+K89+K114,K99+K100)) -> 0 | L101: =IF(L6<Assumptions!$P$26,0,-MIN(-L17+L89+L114,L99+L100)) -> 0 | M101: =IF(M6<Assumptions!$P$26,0,-MIN(-M17+M89+M114,M99+M100)) -> 0 | ... ET101: =IF(ET6<Assumptions!$P$26,0,-MIN(-ET17+ET89+ET114,ET99+ET100)) -> 0
B102: Ending Balance | F102: =SUM(F99:F101) -> 0 | G102: =SUM(G99:G101) -> 0 | H102: =SUM(H99:H101) -> 0 | I102: =SUM(I99:I101) -> 0 | J102: =SUM(J99:J101) -> 0 | K102: =SUM(K99:K101) -> 0 | L102: =SUM(L99:L101) -> 0 | M102: =SUM(M99:M101) -> 0 | ... ET102: =SUM(ET99:ET101) -> 0
B104: Construction Loan Reserve
B105: Beginning Balance | F105: =E109 -> 0 | G105: =F109 -> 0 | H105: =G109 -> 0 | I105: =H109 -> 0 | J105: =I109 -> 0 | K105: =J109 -> 0 | L105: =K109 -> 0 | M105: =L109 -> 0 | ... ET105: =ES109 -> 0.00015985392
B106: Closing | F106: =IF(F6=Assumptions!$P$12,Assumptions!$Q$4+Assumptions!$Q$11,0) -> 0 | G106: =IF(G6=Assumptions!$P$12,Assumptions!$Q$4+Assumptions!$Q$11,0) -> 0 | H106: =IF(H6=Assumptions!$P$12,Assumptions!$Q$4+Assumptions!$Q$11,0) -> 0 | I106: =IF(I6=Assumptions!$P$12,Assumptions!$Q$4+Assumptions!$Q$11,0) -> 0 | J106: =IF(J6=Assumptions!$P$12,Assumptions!$Q$4+Assumptions!$Q$11,0) -> 0 | K106: =IF(K6=Assumptions!$P$12,Assumptions!$Q$4+Assumptions!$Q$11,0) -> 0 | L106: =IF(L6=Assumptions!$P$12,Assumptions!$Q$4+Assumptions!$Q$11,0) -> 0 | M106: =IF(M6=Assumptions!$P$12,Assumptions!$Q$4+Assumptions!$Q$11,0) -> 0 | ... ET106: =IF(ET6=Assumptions!$P$12,Assumptions!$Q$4+Assumptions!$Q$11,0) -> 0
B107: Acquisition Loan Refi | F107: =F116 -> 0 | G107: =G116 -> 0 | H107: =H116 -> 0 | I107: =I116 -> 0 | J107: =J116 -> 0 | K107: =K116 -> 0 | L107: =L116 -> 0 | M107: =M116 -> 0 | ... ET107: =ET116 -> 0
B108: Draw | F108: =-MIN(SUM(F105:F106),-F17+F89+F95+F101-F114) -> 0 | G108: =-MIN(SUM(G105:G106),-G17+G89+G95+G101-G114) -> 0 | H108: =-MIN(SUM(H105:H106),-H17+H89+H95+H101-H114) -> 0 | I108: =-MIN(SUM(I105:I106),-I17+I89+I95+I101-I114) -> 0 | J108: =-MIN(SUM(J105:J106),-J17+J89+J95+J101-J114) -> 0 | K108: =-MIN(SUM(K105:K106),-K17+K89+K95+K101-K114) -> 0 | L108: =-MIN(SUM(L105:L106),-L17+L89+L95+L101-L114) -> 0 | M108: =-MIN(SUM(M105:M106),-M17+M89+M95+M101-M114) -> 0 | ... ET108: =-MIN(SUM(ET105:ET106),-ET17+ET89+ET95+ET101-ET114) -> 0
B109: Ending Balance | F109: =SUM(F105:F108) -> 0 | G109: =SUM(G105:G108) -> 0 | H109: =SUM(H105:H108) -> 0 | I109: =SUM(I105:I108) -> 0 | J109: =SUM(J105:J108) -> 0 | K109: =SUM(K105:K108) -> 0 | L109: =SUM(L105:L108) -> 0 | M109: =SUM(M105:M108) -> 0 | ... ET109: =SUM(ET105:ET108) -> 0.00015985392
B112: Acquisition Loan Balance
B113: Beginning Balance | F113: =E117 -> 0 | G113: =F117 -> 1750000 | H113: =G117 -> 1750000 | I113: =H117 -> 1750000 | J113: =I117 -> 1750000 | K113: =J117 -> 1750000 | L113: =K117 -> 1750000 | M113: =L117 -> 1750000 | ... ET113: =ES117 -> 0
B114: Draw | F114: =IF(F$6=Assumptions!$P$5,Assumptions!$Q$4,0) -> 1750000 | G114: =IF(G$6=Assumptions!$P$5,Assumptions!$Q$4,0) -> 0 | H114: =IF(H$6=Assumptions!$P$5,Assumptions!$Q$4,0) -> 0 | I114: =IF(I$6=Assumptions!$P$5,Assumptions!$Q$4,0) -> 0 | J114: =IF(J$6=Assumptions!$P$5,Assumptions!$Q$4,0) -> 0 | K114: =IF(K$6=Assumptions!$P$5,Assumptions!$Q$4,0) -> 0 | L114: =IF(L$6=Assumptions!$P$5,Assumptions!$Q$4,0) -> 0 | M114: =IF(M$6=Assumptions!$P$5,Assumptions!$Q$4,0) -> 0 | ... ET114: =IF(ET$6=Assumptions!$P$5,Assumptions!$Q$4,0) -> 0
B115: Capitalized Interest | F115: =F113*Assumptions!$Q$7/12 -> 0 | G115: =G113*Assumptions!$Q$7/12 -> 8750 | H115: =H113*Assumptions!$Q$7/12 -> 8750 | I115: =I113*Assumptions!$Q$7/12 -> 8750 | J115: =J113*Assumptions!$Q$7/12 -> 8750 | K115: =K113*Assumptions!$Q$7/12 -> 8750 | L115: =L113*Assumptions!$Q$7/12 -> 8750 | M115: =M113*Assumptions!$Q$7/12 -> 8750 | ... ET115: =ET113*Assumptions!$Q$7/12 -> 0
B116: Paydown at Construction Loan | F116: =IF(F$6=Assumptions!$P$8,-SUM(F113:F114),0) -> 0 | G116: =IF(G$6=Assumptions!$P$8,-SUM(G113:G114),0) -> 0 | H116: =IF(H$6=Assumptions!$P$8,-SUM(H113:H114),0) -> 0 | I116: =IF(I$6=Assumptions!$P$8,-SUM(I113:I114),0) -> 0 | J116: =IF(J$6=Assumptions!$P$8,-SUM(J113:J114),0) -> 0 | K116: =IF(K$6=Assumptions!$P$8,-SUM(K113:K114),0) -> 0 | L116: =IF(L$6=Assumptions!$P$8,-SUM(L113:L114),0) -> 0 | M116: =IF(M$6=Assumptions!$P$8,-SUM(M113:M114),0) -> 0 | ... ET116: =IF(ET$6=Assumptions!$P$8,-SUM(ET113:ET114),0) -> 0
B117: Ending Balance | F117: =F113+F114+F116 -> 1750000 | G117: =G113+G114+G116 -> 1750000 | H117: =H113+H114+H116 -> 1750000 | I117: =I113+I114+I116 -> 1750000 | J117: =J113+J114+J116 -> 1750000 | K117: =K113+K114+K116 -> 1750000 | L117: =L113+L114+L116 -> 1750000 | M117: =M113+M114+M116 -> 1750000 | ... ET117: =ET113+ET114+ET116 -> 0
B119: Construction Loan Balance
B120: Beginning Balance | F120: =E128 -> 0 | G120: =F128 -> 0 | H120: =G128 -> 0 | I120: =H128 -> 0 | J120: =I128 -> 0 | K120: =J128 -> 0 | L120: =K128 -> 0 | M120: =L128 -> 0 | ... ET120: =ES128 -> 0
B121: Acquisition Loan Refi | F121: =-F116 -> 0 | G121: =-G116 -> 0 | H121: =-H116 -> 0 | I121: =-I116 -> 0 | J121: =-J116 -> 0 | K121: =-K116 -> 0 | L121: =-L116 -> 0 | M121: =-M116 -> 0 | ... ET121: =-ET116 -> 0
...

Sheet Levered CF
B2: Timeline | D2: 1 | E2: =D2+1 -> 2 | F2: =E2+1 -> 3 | G2: =F2+1 -> 4 | H2: =G2+1 -> 5 | I2: =H2+1 -> 6 | J2: =I2+1 -> 7 | K2: =J2+1 -> 8 | L2: =K2+1 -> 9 | M2: =L2+1 -> 10
B3: Uses Schedule | C3: Total | D3: =CONCATENATE(YEAR(Assumptions!$F$35)+D2-1," - ",YEAR(Assumptions!$F$35)+D2) -> 2026 - 2027 | E3: =CONCATENATE(YEAR(Assumptions!$F$35)+E2-1," - ",YEAR(Assumptions!$F$35)+E2) -> 2027 - 2028 | F3: =CONCATENATE(YEAR(Assumptions!$F$35)+F2-1," - ",YEAR(Assumptions!$F$35)+F2) -> 2028 - 2029 | G3: =CONCATENATE(YEAR(Assumptions!$F$35)+G2-1," - ",YEAR(Assumptions!$F$35)+G2) -> 2029 - 2030 | H3: =CONCATENATE(YEAR(Assumptions!$F$35)+H2-1," - ",YEAR(Assumptions!$F$35)+H2) -> 2030 - 2031 | I3: =CONCATENATE(YEAR(Assumptions!$F$35)+I2-1," - ",YEAR(Assumptions!$F$35)+I2) -> 2031 - 2032 | J3: =CONCATENATE(YEAR(Assumptions!$F$35)+J2-1," - ",YEAR(Assumptions!$F$35)+J2) -> 2032 - 2033 | K3: =CONCATENATE(YEAR(Assumptions!$F$35)+K2-1," - ",YEAR(Assumptions!$F$35)+K2) -> 2033 - 2034 | ... M3: =CONCATENATE(YEAR(Assumptions!$F$35)+M2-1," - ",YEAR(Assumptions!$F$35)+M2) -> 2035 - 2036
B4: Acquisition | C4: =SUM(D4:M4) -> -3500000 | D4: =SUMIF('Draw Schedule'!$F$4:$ET$4,'Levered CF'!D$2,'Draw Schedule'!$F$9:$ET$9) -> -3500000 | E4: =SUMIF('Draw Schedule'!$F$4:$ET$4,'Levered CF'!E$2,'Draw Schedule'!$F$9:$ET$9) -> 0 | F4: =SUMIF('Draw Schedule'!$F$4:$ET$4,'Levered CF'!F$2,'Draw Schedule'!$F$9:$ET$9) -> 0 | G4: =SUMIF('Draw Schedule'!$F$4:$ET$4,'Levered CF'!G$2,'Draw Schedule'!$F$9:$ET$9) -> 0 | H4: =SUMIF('Draw Schedule'!$F$4:$ET$4,'Levered CF'!H$2,'Draw Schedule'!$F$9:$ET$9) -> 0 | I4: =SUMIF('Draw Schedule'!$F$4:$ET$4,'Levered CF'!I$2,'Draw Schedule'!$F$9:$ET$9) -> 0 | J4: =SUMIF('Draw Schedule'!$F$4:$ET$4,'Levered CF'!J$2,'Draw Schedule'!$F$9:$ET$9) -> 0 | K4: =SUMIF('Draw Schedule'!$F$4:$ET$4,'Levered CF'!K$2,'Draw Schedule'!$F$9:$ET$9) -> 0 | ... M4: =SUMIF('Draw Schedule'!$F$4:$ET$4,'Levered CF'!M$2,'Draw Schedule'!$F$9:$ET$9) -> 0
B5: Soft Costs | C5: =SUM(D5:M5) -> -5033193.3 | D5: =SUMIF('Draw Schedule'!$F$4:$ET$4,'Levered CF'!D$2,'Draw Schedule'!$F$10:$ET$10)+SUMIF('Draw Schedule'!$F$4:$ET$4,'Levered CF'!D$2,'Draw Schedule'!$F$11:$ET$11)+SUMIF('Draw Schedule'!$F$4:$ET$4,'Levered CF'!D$2,'Draw Schedule'!$F$12:$ET$12) -> -1639160.3 | E5: =SUMIF('Draw Schedule'!$F$4:$ET$4,'Levered CF'!E$2,'Draw Schedule'!$F$10:$ET$10)+SUMIF('Draw Schedule'!$F$4:$ET$4,'Levered CF'!E$2,'Draw Schedule'!$F$11:$ET$11)+SUMIF('Draw Schedule'!$F$4:$ET$4,'Levered CF'!E$2,'Draw Schedule'!$F$12:$ET$12) -> -2026448.5 | F5: =SUMIF('Draw Schedule'!$F$4:$ET$4,'Levered CF'!F$2,'Draw Schedule'!$F$10:$ET$10)+SUMIF('Draw Schedule'!$F$4:$ET$4,'Levered CF'!F$2,'Draw Schedule'!$F$11:$ET$11)+SUMIF('Draw Schedule'!$F$4:$ET$4,'Levered CF'!F$2,'Draw Schedule'!$F$12:$ET$12) -> -1367584.5 | G5: =SUMIF('Draw Schedule'!$F$4:$ET$4,'Levered CF'!G$2,'Draw Schedule'!$F$10:$ET$10)+SUMIF('Draw Schedule'!$F$4:$ET$4,'Levered CF'!G$2,'Draw Schedule'!$F$11:$ET$11)+SUMIF('Draw Schedule'!$F$4:$ET$4,'Levered CF'!G$2,'Draw Schedule'!$F$12:$ET$12) -> 0 | H5: =SUMIF('Draw Schedule'!$F$4:$ET$4,'Levered CF'!H$2,'Draw Schedule'!$F$10:$ET$10)+SUMIF('Draw Schedule'!$F$4:$ET$4,'Levered CF'!H$2,'Draw Schedule'!$F$11:$ET$11)+SUMIF('Draw Schedule'!$F$4:$ET$4,'Levered CF'!H$2,'Draw Schedule'!$F$12:$ET$12) -> 0 | I5: =SUMIF('Draw Schedule'!$F$4:$ET$4,'Levered CF'!I$2,'Draw Schedule'!$F$10:$ET$10)+SUMIF('Draw Schedule'!$F$4:$ET$4,'Levered CF'!I$2,'Draw Schedule'!$F$11:$ET$11)+SUMIF('Draw Schedule'!$F$4:$ET$4,'Levered CF'!I$2,'Draw Schedule'!$F$12:$ET$12) -> 0 | J5: =SUMIF('Draw Schedule'!$F$4:$ET$4,'Levered CF'!J$2,'Draw Schedule'!$F$10:$ET$10)+SUMIF('Draw Schedule'!$F$4:$ET$4,'Levered CF'!J$2,'Draw Schedule'!$F$11:$ET$11)+SUMIF('Draw Schedule'!$F$4:$ET$4,'Levered CF'!J$2,'Draw Schedule'!$F$12:$ET$12) -> 0 | K5: =SUMIF('Draw Schedule'!$F$4:$ET$4,'Levered CF'!K$2,'Draw Schedule'!$F$10:$ET$10)+SUMIF('Draw Schedule'!$F$4:$ET$4,'Levered CF'!K$2,'Draw Schedule'!$F$11:$ET$11)+SUMIF('Draw Schedule'!$F$4:$ET$4,'Levered CF'!K$2,'Draw Schedule'!$F$12:$ET$12) -> 0 | ... M5: =SUMIF('Draw Schedule'!$F$4:$ET$4,'Levered CF'!M$2,'Draw Schedule'!$F$10:$ET$10)+SUMIF('Draw Schedule'!$F$4:$ET$4,'Levered CF'!M$2,'Draw Schedule'!$F$11:$ET$11)+SUMIF('Draw Schedule'!$F$4:$ET$4,'Levered CF'!M$2,'Draw Schedule'!$F$12:$ET$12) -> 0
B6: Hard Costs | C6: =SUM(D6:M6) -> -19519500 | D6: =SUMIF('Draw Schedule'!$F$4:$ET$4,'Levered CF'!D$2,'Draw Schedule'!$F$13:$ET$13) -> 0 | E6: =SUMIF('Draw Schedule'!$F$4:$ET$4,'Levered CF'!E$2,'Draw Schedule'!$F$13:$ET$13) -> -8783775 | F6: =SUMIF('Draw Schedule'!$F$4:$ET$4,'Levered CF'!F$2,'Draw Schedule'!$F$13:$ET$13) -> -10735725 | G6: =SUMIF('Draw Schedule'!$F$4:$ET$4,'Levered CF'!G$2,'Draw Schedule'!$F$13:$ET$13) -> 0 | H6: =SUMIF('Draw Schedule'!$F$4:$ET$4,'Levered CF'!H$2,'Draw Schedule'!$F$13:$ET$13) -> 0 | I6: =SUMIF('Draw Schedule'!$F$4:$ET$4,'Levered CF'!I$2,'Draw Schedule'!$F$13:$ET$13) -> 0 | J6: =SUMIF('Draw Schedule'!$F$4:$ET$4,'Levered CF'!J$2,'Draw Schedule'!$F$13:$ET$13) -> 0 | K6: =SUMIF('Draw Schedule'!$F$4:$ET$4,'Levered CF'!K$2,'Draw Schedule'!$F$13:$ET$13) -> 0 | ... M6: =SUMIF('Draw Schedule'!$F$4:$ET$4,'Levered CF'!M$2,'Draw Schedule'!$F$13:$ET$13) -> 0
B7: NOI Shortfall | C7: =SUM(D7:M7) -> 0 | D7: =SUMIF('Draw Schedule'!$F$4:$ET$4,'Levered CF'!D$2,'Draw Schedule'!$F$14:$ET$14) -> 0 | E7: =SUMIF('Draw Schedule'!$F$4:$ET$4,'Levered CF'!E$2,'Draw Schedule'!$F$14:$ET$14) -> 0 | F7: =SUMIF('Draw Schedule'!$F$4:$ET$4,'Levered CF'!F$2,'Draw Schedule'!$F$14:$ET$14) -> 0 | G7: =SUMIF('Draw Schedule'!$F$4:$ET$4,'Levered CF'!G$2,'Draw Schedule'!$F$14:$ET$14) -> 0 | H7: =SUMIF('Draw Schedule'!$F$4:$ET$4,'Levered CF'!H$2,'Draw Schedule'!$F$14:$ET$14) -> 0 | I7: =SUMIF('Draw Schedule'!$F$4:$ET$4,'Levered CF'!I$2,'Draw Schedule'!$F$14:$ET$14) -> 0 | J7: =SUMIF('Draw Schedule'!$F$4:$ET$4,'Levered CF'!J$2,'Draw Schedule'!$F$14:$ET$14) -> 0 | K7: =SUMIF('Draw Schedule'!$F$4:$ET$4,'Levered CF'!K$2,'Draw Schedule'!$F$14:$ET$14) -> 0 | ... M7: =SUMIF('Draw Schedule'!$F$4:$ET$4,'Levered CF'!M$2,'Draw Schedule'!$F$14:$ET$14) -> 0
B8: Capitalized Ground Rent | C8: =SUM(D8:M8) -> 0 | D8: =SUMIF('Draw Schedule'!$F$4:$ET$4,'Levered CF'!D$2,'Draw Schedule'!$F$15:$ET$15) -> 0 | E8: =SUMIF('Draw Schedule'!$F$4:$ET$4,'Levered CF'!E$2,'Draw Schedule'!$F$15:$ET$15) -> 0 | F8: =SUMIF('Draw Schedule'!$F$4:$ET$4,'Levered CF'!F$2,'Draw Schedule'!$F$15:$ET$15) -> 0 | G8: =SUMIF('Draw Schedule'!$F$4:$ET$4,'Levered CF'!G$2,'Draw Schedule'!$F$15:$ET$15) -> 0 | H8: =SUMIF('Draw Schedule'!$F$4:$ET$4,'Levered CF'!H$2,'Draw Schedule'!$F$15:$ET$15) -> 0 | I8: =SUMIF('Draw Schedule'!$F$4:$ET$4,'Levered CF'!I$2,'Draw Schedule'!$F$15:$ET$15) -> 0 | J8: =SUMIF('Draw Schedule'!$F$4:$ET$4,'Levered CF'!J$2,'Draw Schedule'!$F$15:$ET$15) -> 0 | K8: =SUMIF('Draw Schedule'!$F$4:$ET$4,'Levered CF'!K$2,'Draw Schedule'!$F$15:$ET$15) -> 0 | ... M8: =SUMIF('Draw Schedule'!$F$4:$ET$4,'Levered CF'!M$2,'Draw Schedule'!$F$15:$ET$15) -> 0
B9: Capitalized Interest | C9: =SUM(D9:M9) -> -2131440.8 | D9: =SUMIF('Draw Schedule'!$F$4:$ET$4,'Levered CF'!D$2,'Draw Schedule'!$F$16:$ET$16) -> -96250 | E9: =SUMIF('Draw Schedule'!$F$4:$ET$4,'Levered CF'!E$2,'Draw Schedule'!$F$16:$ET$16) -> -222785.59 | F9: =SUMIF('Draw Schedule'!$F$4:$ET$4,'Levered CF'!F$2,'Draw Schedule'!$F$16:$ET$16) -> -1139555.9 | G9: =SUMIF('Draw Schedule'!$F$4:$ET$4,'Levered CF'!G$2,'Draw Schedule'!$F$16:$ET$16) -> -500229.42 | H9: =SUMIF('Draw Schedule'!$F$4:$ET$4,'Levered CF'!H$2,'Draw Schedule'!$F$16:$ET$16) -> -113097.9 | I9: =SUMIF('Draw Schedule'!$F$4:$ET$4,'Levered CF'!I$2,'Draw Schedule'!$F$16:$ET$16) -> -59521.983 | J9: =SUMIF('Draw Schedule'!$F$4:$ET$4,'Levered CF'!J$2,'Draw Schedule'!$F$16:$ET$16) -> 0 | K9: =SUMIF('Draw Schedule'!$F$4:$ET$4,'Levered CF'!K$2,'Draw Schedule'!$F$16:$ET$16) -> 0 | ... M9: =SUMIF('Draw Schedule'!$F$4:$ET$4,'Levered CF'!M$2,'Draw Schedule'!$F$16:$ET$16) -> 0
B10: Total Uses | C10: =SUM(C4:C9) -> -30184134 | D10: =SUM(D4:D9) -> -5235410.3 | E10: =SUM(E4:E9) -> -11033009 | F10: =SUM(F4:F9) -> -13242865 | G10: =SUM(G4:G9) -> -500229.42 | H10: =SUM(H4:H9) -> -113097.9 | I10: =SUM(I4:I9) -> -59521.983 | J10: =SUM(J4:J9) -> 0 | ... M10: =SUM(M4:M9) -> 0
B12: Sources Schedule | C12: Total | D12: =D3 -> 2026 - 2027 | E12: =E3 -> 2027 - 2028 | F12: =F3 -> 2028 - 2029 | G12: =G3 -> 2029 - 2030 | H12: =H3 -> 2030 - 2031 | I12: =I3 -> 2031 - 2032 | J12: =J3 -> 2032 - 2033 | K12: =K3 -> 2033 - 2034 | ... M12: =M3 -> 2035 - 2036
B13: Equity Contribution | C13: =SUM(D13:M13) -> 7546033.5 | D13: =SUMIF('Draw Schedule'!$F$4:$ET$4,'Levered CF'!D$2,'Draw Schedule'!$F$20:$ET$20) -> 3485410.3 | E13: =SUMIF('Draw Schedule'!$F$4:$ET$4,'Levered CF'!E$2,'Draw Schedule'!$F$20:$ET$20) -> 4060623.2 | F13: =SUMIF('Draw Schedule'!$F$4:$ET$4,'Levered CF'!F$2,'Draw Schedule'!$F$20:$ET$20) -> 0 | G13: =SUMIF('Draw Schedule'!$F$4:$ET$4,'Levered CF'!G$2,'Draw Schedule'!$F$20:$ET$20) -> 0 | H13: =SUMIF('Draw Schedule'!$F$4:$ET$4,'Levered CF'!H$2,'Draw Schedule'!$F$20:$ET$20) -> 0 | I13: =SUMIF('Draw Schedule'!$F$4:$ET$4,'Levered CF'!I$2,'Draw Schedule'!$F$20:$ET$20) -> 0 | J13: =SUMIF('Draw Schedule'!$F$4:$ET$4,'Levered CF'!J$2,'Draw Schedule'!$F$20:$ET$20) -> 0 | K13: =SUMIF('Draw Schedule'!$F$4:$ET$4,'Levered CF'!K$2,'Draw Schedule'!$F$20:$ET$20) -> 0 | ... M13: =SUMIF('Draw Schedule'!$F$4:$ET$4,'Levered CF'!M$2,'Draw Schedule'!$F$20:$ET$20) -> 0
B14: Mezz Loan | C14: =SUM(D14:M14) -> 0 | D14: =SUMIF('Draw Schedule'!$F$4:$ET$4,'Levered CF'!D$2,'Draw Schedule'!$F$21:$ET$21) -> 0 | E14: =SUMIF('Draw Schedule'!$F$4:$ET$4,'Levered CF'!E$2,'Draw Schedule'!$F$21:$ET$21) -> 0 | F14: =SUMIF('Draw Schedule'!$F$4:$ET$4,'Levered CF'!F$2,'Draw Schedule'!$F$21:$ET$21) -> 0 | G14: =SUMIF('Draw Schedule'!$F$4:$ET$4,'Levered CF'!G$2,'Draw Schedule'!$F$21:$ET$21) -> 0 | H14: =SUMIF('Draw Schedule'!$F$4:$ET$4,'Levered CF'!H$2,'Draw Schedule'!$F$21:$ET$21) -> 0 | I14: =SUMIF('Draw Schedule'!$F$4:$ET$4,'Levered CF'!I$2,'Draw Schedule'!$F$21:$ET$21) -> 0 | J14: =SUMIF('Draw Schedule'!$F$4:$ET$4,'Levered CF'!J$2,'Draw Schedule'!$F$21:$ET$21) -> 0 | K14: =SUMIF('Draw Schedule'!$F$4:$ET$4,'Levered CF'!K$2,'Draw Schedule'!$F$21:$ET$21) -> 0 | ... M14: =SUMIF('Draw Schedule'!$F$4:$ET$4,'Levered CF'!M$2,'Draw Schedule'!$F$21:$ET$21) -> 0
B15: Ground Lease Contribution | C15: =SUM(D15:M15) -> 0 | D15: =SUMIF('Draw Schedule'!$F$4:$ET$4,'Levered CF'!D$2,'Draw Schedule'!$F$22:$ET$22) -> 0 | E15: =SUMIF('Draw Schedule'!$F$4:$ET$4,'Levered CF'!E$2,'Draw Schedule'!$F$22:$ET$22) -> 0 | F15: =SUMIF('Draw Schedule'!$F$4:$ET$4,'Levered CF'!F$2,'Draw Schedule'!$F$22:$ET$22) -> 0 | G15: =SUMIF('Draw Schedule'!$F$4:$ET$4,'Levered CF'!G$2,'Draw Schedule'!$F$22:$ET$22) -> 0 | H15: =SUMIF('Draw Schedule'!$F$4:$ET$4,'Levered CF'!H$2,'Draw Schedule'!$F$22:$ET$22) -> 0 | I15: =SUMIF('Draw Schedule'!$F$4:$ET$4,'Levered CF'!I$2,'Draw Schedule'!$F$22:$ET$22) -> 0 | J15: =SUMIF('Draw Schedule'!$F$4:$ET$4,'Levered CF'!J$2,'Draw Schedule'!$F$22:$ET$22) -> 0 | K15: =SUMIF('Draw Schedule'!$F$4:$ET$4,'Levered CF'!K$2,'Draw Schedule'!$F$22:$ET$22) -> 0 | ... M15: =SUMIF('Draw Schedule'!$F$4:$ET$4,'Levered CF'!M$2,'Draw Schedule'!$F$22:$ET$22) -> 0
B16: Senior Loan | C16: =SUM(D16:M16) -> 22638101 | D16: =SUMIF('Draw Schedule'!$F$4:$ET$4,'Levered CF'!D$2,'Draw Schedule'!$F$23:$ET$23) -> 1750000 | E16: =SUMIF('Draw Schedule'!$F$4:$ET$4,'Levered CF'!E$2,'Draw Schedule'!$F$23:$ET$23) -> 6972385.9 | F16: =SUMIF('Draw Schedule'!$F$4:$ET$4,'Levered CF'!F$2,'Draw Schedule'!$F$23:$ET$23) -> 13242865 | G16: =SUMIF('Draw Schedule'!$F$4:$ET$4,'Levered CF'!G$2,'Draw Schedule'!$F$23:$ET$23) -> 500229.42 | H16: =SUMIF('Draw Schedule'!$F$4:$ET$4,'Levered CF'!H$2,'Draw Schedule'!$F$23:$ET$23) -> 113097.9 | I16: =SUMIF('Draw Schedule'!$F$4:$ET$4,'Levered CF'!I$2,'Draw Schedule'!$F$23:$ET$23) -> 59521.983 | J16: =SUMIF('Draw Schedule'!$F$4:$ET$4,'Levered CF'!J$2,'Draw Schedule'!$F$23:$ET$23) -> 0 | K16: =SUMIF('Draw Schedule'!$F$4:$ET$4,'Levered CF'!K$2,'Draw Schedule'!$F$23:$ET$23) -> 0 | ... M16: =SUMIF('Draw Schedule'!$F$4:$ET$4,'Levered CF'!M$2,'Draw Schedule'!$F$23:$ET$23) -> 0
B17: Total Sources | C17: =SUM(D17:M17) -> 30184134 | D17: =SUM(D13:D16) -> 5235410.3 | E17: =SUM(E13:E16) -> 11033009 | F17: =SUM(F13:F16) -> 13242865 | G17: =SUM(G13:G16) -> 500229.42 | H17: =SUM(H13:H16) -> 113097.9 | I17: =SUM(I13:I16) -> 59521.983 | J17: =SUM(J13:J16) -> 0 | K17: =SUM(K13:K16) -> 0 | ... M17: =SUM(M13:M16) -> 0
B19: Levered Cash Flow | C19: Total | D19: =D12 -> 2026 - 2027 | E19: =E12 -> 2027 - 2028 | F19: =F12 -> 2028 - 2029 | G19: =G12 -> 2029 - 2030 | H19: =H12 -> 2030 - 2031 | I19: =I12 -> 2031 - 2032 | J19: =J12 -> 2032 - 2033 | K19: =K12 -> 2033 - 2034 | ... M19: =M12 -> 2035 - 2036
B20: ='Draw Schedule'!B154 -> Equity Deployment | C20: =SUM(D20:M20) -> -7546033.5 | D20: =SUMIF('Draw Schedule'!$F$4:$ET$4,'Levered CF'!D$2,'Draw Schedule'!$F154:$ET154) -> -3485410.3 | E20: =SUMIF('Draw Schedule'!$F$4:$ET$4,'Levered CF'!E$2,'Draw Schedule'!$F154:$ET154) -> -4060623.2 | F20: =SUMIF('Draw Schedule'!$F$4:$ET$4,'Levered CF'!F$2,'Draw Schedule'!$F154:$ET154) -> 0 | G20: =SUMIF('Draw Schedule'!$F$4:$ET$4,'Levered CF'!G$2,'Draw Schedule'!$F154:$ET154) -> 0 | H20: =SUMIF('Draw Schedule'!$F$4:$ET$4,'Levered CF'!H$2,'Draw Schedule'!$F154:$ET154) -> 0 | I20: =SUMIF('Draw Schedule'!$F$4:$ET$4,'Levered CF'!I$2,'Draw Schedule'!$F154:$ET154) -> 0 | J20: =SUMIF('Draw Schedule'!$F$4:$ET$4,'Levered CF'!J$2,'Draw Schedule'!$F154:$ET154) -> 0 | K20: =SUMIF('Draw Schedule'!$F$4:$ET$4,'Levered CF'!K$2,'Draw Schedule'!$F154:$ET154) -> 0 | ... M20: =SUMIF('Draw Schedule'!$F$4:$ET$4,'Levered CF'!M$2,'Draw Schedule'!$F154:$ET154) -> 0
B21: ='Draw Schedule'!B155 -> Residential Net Operating Income | C21: =SUM(D21:M21) -> 5517589.7 | D21: =SUMIF('Draw Schedule'!$F$4:$ET$4,'Levered CF'!D$2,'Draw Schedule'!$F155:$ET155) -> 0 | E21: =SUMIF('Draw Schedule'!$F$4:$ET$4,'Levered CF'!E$2,'Draw Schedule'!$F155:$ET155) -> 0 | F21: =SUMIF('Draw Schedule'!$F$4:$ET$4,'Levered CF'!F$2,'Draw Schedule'!$F155:$ET155) -> 1049.6639 | G21: =SUMIF('Draw Schedule'!$F$4:$ET$4,'Levered CF'!G$2,'Draw Schedule'!$F155:$ET155) -> 1048399.3 | H21: =SUMIF('Draw Schedule'!$F$4:$ET$4,'Levered CF'!H$2,'Draw Schedule'!$F155:$ET155) -> 1432862.8 | I21: =SUMIF('Draw Schedule'!$F$4:$ET$4,'Levered CF'!I$2,'Draw Schedule'!$F155:$ET155) -> 1488820.7 | J21: =SUMIF('Draw Schedule'!$F$4:$ET$4,'Levered CF'!J$2,'Draw Schedule'!$F155:$ET155) -> 1546457.3 | K21: =SUMIF('Draw Schedule'!$F$4:$ET$4,'Levered CF'!K$2,'Draw Schedule'!$F155:$ET155) -> 0 | ... M21: =SUMIF('Draw Schedule'!$F$4:$ET$4,'Levered CF'!M$2,'Draw Schedule'!$F155:$ET155) -> 0
B22: ='Draw Schedule'!B156 -> Retail Net Operating Income | C22: =SUM(D22:M22) -> 565537.44 | D22: =SUMIF('Draw Schedule'!$F$4:$ET$4,'Levered CF'!D$2,'Draw Schedule'!$F156:$ET156) -> 0 | E22: =SUMIF('Draw Schedule'!$F$4:$ET$4,'Levered CF'!E$2,'Draw Schedule'!$F156:$ET156) -> 0 | F22: =SUMIF('Draw Schedule'!$F$4:$ET$4,'Levered CF'!F$2,'Draw Schedule'!$F156:$ET156) -> 0 | G22: =SUMIF('Draw Schedule'!$F$4:$ET$4,'Levered CF'!G$2,'Draw Schedule'!$F156:$ET156) -> 124194.71 | H22: =SUMIF('Draw Schedule'!$F$4:$ET$4,'Levered CF'!H$2,'Draw Schedule'!$F156:$ET156) -> 142787.78 | I22: =SUMIF('Draw Schedule'!$F$4:$ET$4,'Levered CF'!I$2,'Draw Schedule'!$F156:$ET156) -> 147071.41 | J22: =SUMIF('Draw Schedule'!$F$4:$ET$4,'Levered CF'!J$2,'Draw Schedule'!$F156:$ET156) -> 151483.55 | K22: =SUMIF('Draw Schedule'!$F$4:$ET$4,'Levered CF'!K$2,'Draw Schedule'!$F156:$ET156) -> 0 | ... M22: =SUMIF('Draw Schedule'!$F$4:$ET$4,'Levered CF'!M$2,'Draw Schedule'!$F156:$ET156) -> 0
B23: ='Draw Schedule'!B157 -> Residential Gross Sale Proceeds | C23: =SUM(D23:M23) -> 32737809 | D23: =SUMIF('Draw Schedule'!$F$4:$ET$4,'Levered CF'!D$2,'Draw Schedule'!$F157:$ET157) -> 0 | E23: =SUMIF('Draw Schedule'!$F$4:$ET$4,'Levered CF'!E$2,'Draw Schedule'!$F157:$ET157) -> 0 | F23: =SUMIF('Draw Schedule'!$F$4:$ET$4,'Levered CF'!F$2,'Draw Schedule'!$F157:$ET157) -> 0 | G23: =SUMIF('Draw Schedule'!$F$4:$ET$4,'Levered CF'!G$2,'Draw Schedule'!$F157:$ET157) -> 0 | H23: =SUMIF('Draw Schedule'!$F$4:$ET$4,'Levered CF'!H$2,'Draw Schedule'!$F157:$ET157) -> 0 | I23: =SUMIF('Draw Schedule'!$F$4:$ET$4,'Levered CF'!I$2,'Draw Schedule'!$F157:$ET157) -> 0 | J23: =SUMIF('Draw Schedule'!$F$4:$ET$4,'Levered CF'!J$2,'Draw Schedule'!$F157:$ET157) -> 32737809 | K23: =SUMIF('Draw Schedule'!$F$4:$ET$4,'Levered CF'!K$2,'Draw Schedule'!$F157:$ET157) -> 0 | ... M23: =SUMIF('Draw Schedule'!$F$4:$ET$4,'Levered CF'!M$2,'Draw Schedule'!$F157:$ET157) -> 0
B24: ='Draw Schedule'!B158 -> Retail Gross Sale Proceeds | C24: =SUM(D24:M24) -> 2866119.9 | D24: =SUMIF('Draw Schedule'!$F$4:$ET$4,'Levered CF'!D$2,'Draw Schedule'!$F158:$ET158) -> 0 | E24: =SUMIF('Draw Schedule'!$F$4:$ET$4,'Levered CF'!E$2,'Draw Schedule'!$F158:$ET158) -> 0 | F24: =SUMIF('Draw Schedule'!$F$4:$ET$4,'Levered CF'!F$2,'Draw Schedule'!$F158:$ET158) -> 0 | G24: =SUMIF('Draw Schedule'!$F$4:$ET$4,'Levered CF'!G$2,'Draw Schedule'!$F158:$ET158) -> 0 | H24: =SUMIF('Draw Schedule'!$F$4:$ET$4,'Levered CF'!H$2,'Draw Schedule'!$F158:$ET158) -> 0 | I24: =SUMIF('Draw Schedule'!$F$4:$ET$4,'Levered CF'!I$2,'Draw Schedule'!$F158:$ET158) -> 0 | J24: =SUMIF('Draw Schedule'!$F$4:$ET$4,'Levered CF'!J$2,'Draw Schedule'!$F158:$ET158) -> 2866119.9 | K24: =SUMIF('Draw Schedule'!$F$4:$ET$4,'Levered CF'!K$2,'Draw Schedule'!$F158:$ET158) -> 0 | ... M24: =SUMIF('Draw Schedule'!$F$4:$ET$4,'Levered CF'!M$2,'Draw Schedule'!$F158:$ET158) -> 0
B25: ='Draw Schedule'!B159 -> Residential Sale Costs | C25: =SUM(D25:M25) -> -327378.09 | D25: =SUMIF('Draw Schedule'!$F$4:$ET$4,'Levered CF'!D$2,'Draw Schedule'!$F159:$ET159) -> 0 | E25: =SUMIF('Draw Schedule'!$F$4:$ET$4,'Levered CF'!E$2,'Draw Schedule'!$F159:$ET159) -> 0 | F25: =SUMIF('Draw Schedule'!$F$4:$ET$4,'Levered CF'!F$2,'Draw Schedule'!$F159:$ET159) -> 0 | G25: =SUMIF('Draw Schedule'!$F$4:$ET$4,'Levered CF'!G$2,'Draw Schedule'!$F159:$ET159) -> 0 | H25: =SUMIF('Draw Schedule'!$F$4:$ET$4,'Levered CF'!H$2,'Draw Schedule'!$F159:$ET159) -> 0 | I25: =SUMIF('Draw Schedule'!$F$4:$ET$4,'Levered CF'!I$2,'Draw Schedule'!$F159:$ET159) -> 0 | J25: =SUMIF('Draw Schedule'!$F$4:$ET$4,'Levered CF'!J$2,'Draw Schedule'!$F159:$ET159) -> -327378.09 | K25: =SUMIF('Draw Schedule'!$F$4:$ET$4,'Levered CF'!K$2,'Draw Schedule'!$F159:$ET159) -> 0 | ... M25: =SUMIF('Draw Schedule'!$F$4:$ET$4,'Levered CF'!M$2,'Draw Schedule'!$F159:$ET159) -> 0
B26: ='Draw Schedule'!B160 -> Retail Sale Costs | C26: =SUM(D26:M26) -> -100314.2 | D26: =SUMIF('Draw Schedule'!$F$4:$ET$4,'Levered CF'!D$2,'Draw Schedule'!$F160:$ET160) -> 0 | E26: =SUMIF('Draw Schedule'!$F$4:$ET$4,'Levered CF'!E$2,'Draw Schedule'!$F160:$ET160) -> 0 | F26: =SUMIF('Draw Schedule'!$F$4:$ET$4,'Levered CF'!F$2,'Draw Schedule'!$F160:$ET160) -> 0 | G26: =SUMIF('Draw Schedule'!$F$4:$ET$4,'Levered CF'!G$2,'Draw Schedule'!$F160:$ET160) -> 0 | H26: =SUMIF('Draw Schedule'!$F$4:$ET$4,'Levered CF'!H$2,'Draw Schedule'!$F160:$ET160) -> 0 | I26: =SUMIF('Draw Schedule'!$F$4:$ET$4,'Levered CF'!I$2,'Draw Schedule'!$F160:$ET160) -> 0 | J26: =SUMIF('Draw Schedule'!$F$4:$ET$4,'Levered CF'!J$2,'Draw Schedule'!$F160:$ET160) -> -100314.2 | K26: =SUMIF('Draw Schedule'!$F$4:$ET$4,'Levered CF'!K$2,'Draw Schedule'!$F160:$ET160) -> 0 | ... M26: =SUMIF('Draw Schedule'!$F$4:$ET$4,'Levered CF'!M$2,'Draw Schedule'!$F160:$ET160) -> 0
B27: ='Draw Schedule'!B161 -> Ground Lease Rent Paid from NOI | C27: =SUM(D27:M27) -> 0 | D27: =SUMIF('Draw Schedule'!$F$4:$ET$4,'Levered CF'!D$2,'Draw Schedule'!$F161:$ET161) -> 0 | E27: =SUMIF('Draw Schedule'!$F$4:$ET$4,'Levered CF'!E$2,'Draw Schedule'!$F161:$ET161) -> 0 | F27: =SUMIF('Draw Schedule'!$F$4:$ET$4,'Levered CF'!F$2,'Draw Schedule'!$F161:$ET161) -> 0 | G27: =SUMIF('Draw Schedule'!$F$4:$ET$4,'Levered CF'!G$2,'Draw Schedule'!$F161:$ET161) -> 0 | H27: =SUMIF('Draw Schedule'!$F$4:$ET$4,'Levered CF'!H$2,'Draw Schedule'!$F161:$ET161) -> 0 | I27: =SUMIF('Draw Schedule'!$F$4:$ET$4,'Levered CF'!I$2,'Draw Schedule'!$F161:$ET161) -> 0 | J27: =SUMIF('Draw Schedule'!$F$4:$ET$4,'Levered CF'!J$2,'Draw Schedule'!$F161:$ET161) -> 0 | K27: =SUMIF('Draw Schedule'!$F$4:$ET$4,'Levered CF'!K$2,'Draw Schedule'!$F161:$ET161) -> 0 | ... M27: =SUMIF('Draw Schedule'!$F$4:$ET$4,'Levered CF'!M$2,'Draw Schedule'!$F161:$ET161) -> 0
B28: ='Draw Schedule'!B162 -> Construction Loan Interest Paid from NOI | C28: =SUM(D28:M28) -> -6083043.9 | D28: =SUMIF('Draw Schedule'!$F$4:$ET$4,'Levered CF'!D$2,'Draw Schedule'!$F162:$ET162) -> 0 | E28: =SUMIF('Draw Schedule'!$F$4:$ET$4,'Levered CF'!E$2,'Draw Schedule'!$F162:$ET162) -> 0 | F28: =SUMIF('Draw Schedule'!$F$4:$ET$4,'Levered CF'!F$2,'Draw Schedule'!$F162:$ET162) -> -1049.6639 | G28: =SUMIF('Draw Schedule'!$F$4:$ET$4,'Levered CF'!G$2,'Draw Schedule'!$F162:$ET162) -> -1172594 | H28: =SUMIF('Draw Schedule'!$F$4:$ET$4,'Levered CF'!H$2,'Draw Schedule'!$F162:$ET162) -> -1575650.6 | I28: =SUMIF('Draw Schedule'!$F$4:$ET$4,'Levered CF'!I$2,'Draw Schedule'!$F162:$ET162) -> -1635892.1 | J28: =SUMIF('Draw Schedule'!$F$4:$ET$4,'Levered CF'!J$2,'Draw Schedule'!$F162:$ET162) -> -1697857.5 | K28: =SUMIF('Draw Schedule'!$F$4:$ET$4,'Levered CF'!K$2,'Draw Schedule'!$F162:$ET162) -> 0 | ... M28: =SUMIF('Draw Schedule'!$F$4:$ET$4,'Levered CF'!M$2,'Draw Schedule'!$F162:$ET162) -> 0
B29: ='Draw Schedule'!B163 -> Construction Loan Paydown | C29: =SUM(D29:M29) -> -22638101 | D29: =SUMIF('Draw Schedule'!$F$4:$ET$4,'Levered CF'!D$2,'Draw Schedule'!$F163:$ET163) -> 0 | E29: =SUMIF('Draw Schedule'!$F$4:$ET$4,'Levered CF'!E$2,'Draw Schedule'!$F163:$ET163) -> 0 | F29: =SUMIF('Draw Schedule'!$F$4:$ET$4,'Levered CF'!F$2,'Draw Schedule'!$F163:$ET163) -> 0 | G29: =SUMIF('Draw Schedule'!$F$4:$ET$4,'Levered CF'!G$2,'Draw Schedule'!$F163:$ET163) -> 0 | H29: =SUMIF('Draw Schedule'!$F$4:$ET$4,'Levered CF'!H$2,'Draw Schedule'!$F163:$ET163) -> 0 | I29: =SUMIF('Draw Schedule'!$F$4:$ET$4,'Levered CF'!I$2,'Draw Schedule'!$F163:$ET163) -> 0 | J29: =SUMIF('Draw Schedule'!$F$4:$ET$4,'Levered CF'!J$2,'Draw Schedule'!$F163:$ET163) -> -22638101 | K29: =SUMIF('Draw Schedule'!$F$4:$ET$4,'Levered CF'!K$2,'Draw Schedule'!$F163:$ET163) -> 0 | ... M29: =SUMIF('Draw Schedule'!$F$4:$ET$4,'Levered CF'!M$2,'Draw Schedule'!$F163:$ET163) -> 0
B30: ='Draw Schedule'!B164 -> Mezz Loan Paydown | C30: =SUM(D30:M30) -> 0 | D30: =SUMIF('Draw Schedule'!$F$4:$ET$4,'Levered CF'!D$2,'Draw Schedule'!$F164:$ET164) -> 0 | E30: =SUMIF('Draw Schedule'!$F$4:$ET$4,'Levered CF'!E$2,'Draw Schedule'!$F164:$ET164) -> 0 | F30: =SUMIF('Draw Schedule'!$F$4:$ET$4,'Levered CF'!F$2,'Draw Schedule'!$F164:$ET164) -> 0 | G30: =SUMIF('Draw Schedule'!$F$4:$ET$4,'Levered CF'!G$2,'Draw Schedule'!$F164:$ET164) -> 0 | H30: =SUMIF('Draw Schedule'!$F$4:$ET$4,'Levered CF'!H$2,'Draw Schedule'!$F164:$ET164) -> 0 | I30: =SUMIF('Draw Schedule'!$F$4:$ET$4,'Levered CF'!I$2,'Draw Schedule'!$F164:$ET164) -> 0 | J30: =SUMIF('Draw Schedule'!$F$4:$ET$4,'Levered CF'!J$2,'Draw Schedule'!$F164:$ET164) -> 0 | K30: =SUMIF('Draw Schedule'!$F$4:$ET$4,'Levered CF'!K$2,'Draw Schedule'!$F164:$ET164) -> 0 | ... M30: =SUMIF('Draw Schedule'!$F$4:$ET$4,'Levered CF'!M$2,'Draw Schedule'!$F164:$ET164) -> 0
B31: ='Draw Schedule'!B165 -> Permament Loan Proceeds After Closing Costs | C31: =SUM(D31:M31) -> 0 | D31: =SUMIF('Draw Schedule'!$F$4:$ET$4,'Levered CF'!D$2,'Draw Schedule'!$F165:$ET165) -> 0 | E31: =SUMIF('Draw Schedule'!$F$4:$ET$4,'Levered CF'!E$2,'Draw Schedule'!$F165:$ET165) -> 0 | F31: =SUMIF('Draw Schedule'!$F$4:$ET$4,'Levered CF'!F$2,'Draw Schedule'!$F165:$ET165) -> 0 | G31: =SUMIF('Draw Schedule'!$F$4:$ET$4,'Levered CF'!G$2,'Draw Schedule'!$F165:$ET165) -> 0 | H31: =SUMIF('Draw Schedule'!$F$4:$ET$4,'Levered CF'!H$2,'Draw Schedule'!$F165:$ET165) -> 0 | I31: =SUMIF('Draw Schedule'!$F$4:$ET$4,'Levered CF'!I$2,'Draw Schedule'!$F165:$ET165) -> 0 | J31: =SUMIF('Draw Schedule'!$F$4:$ET$4,'Levered CF'!J$2,'Draw Schedule'!$F165:$ET165) -> 0 | K31: =SUMIF('Draw Schedule'!$F$4:$ET$4,'Levered CF'!K$2,'Draw Schedule'!$F165:$ET165) -> 0 | ... M31: =SUMIF('Draw Schedule'!$F$4:$ET$4,'Levered CF'!M$2,'Draw Schedule'!$F165:$ET165) -> 0
... B33: ='Draw Schedule'!B167 -> Permament Loan Payoff | C33: =SUM(D33:M33) -> 0 | D33: =SUMIF('Draw Schedule'!$F$4:$ET$4,'Levered CF'!D$2,'Draw Schedule'!$F167:$ET167) -> 0 | E33: =SUMIF('Draw Schedule'!$F$4:$ET$4,'Levered CF'!E$2,'Draw Schedule'!$F167:$ET167) -> 0 | F33: =SUMIF('Draw Schedule'!$F$4:$ET$4,'Levered CF'!F$2,'Draw Schedule'!$F167:$ET167) -> 0 | G33: =SUMIF('Draw Schedule'!$F$4:$ET$4,'Levered CF'!G$2,'Draw Schedule'!$F167:$ET167) -> 0 | H33: =SUMIF('Draw Schedule'!$F$4:$ET$4,'Levered CF'!H$2,'Draw Schedule'!$F167:$ET167) -> 0 | I33: =SUMIF('Draw Schedule'!$F$4:$ET$4,'Levered CF'!I$2,'Draw Schedule'!$F167:$ET167) -> 0 | J33: =SUMIF('Draw Schedule'!$F$4:$ET$4,'Levered CF'!J$2,'Draw Schedule'!$F167:$ET167) -> 0 | K33: =SUMIF('Draw Schedule'!$F$4:$ET$4,'Levered CF'!K$2,'Draw Schedule'!$F167:$ET167) -> 0 | ... M33: =SUMIF('Draw Schedule'!$F$4:$ET$4,'Levered CF'!M$2,'Draw Schedule'!$F167:$ET167) -> 0
B34: ='Draw Schedule'!B168 -> Total Levered Cash Flow | C34: =SUM(D34:M34) -> 4992185.3 | D34: =SUM(D20:D33) -> -3485410.3 | E34: =SUM(E20:E33) -> -4060623.2 | F34: =SUM(F20:F33) -> 0 | G34: =SUM(G20:G33) -> 2.3283064e-10 | H34: =SUM(H20:H33) -> 2.3283064e-10 | I34: =SUM(I20:I33) -> -2.3283064e-10 | J34: =SUM(J20:J33) -> 12538219 | K34: =SUM(K20:K33) -> 0 | ... M34: =SUM(M20:M33) -> 0

Sheet Net CF Post TCO
B2: Year Post TCO | C2: 1 | D2: =C2+1 -> 2 | E2: =D2+1 -> 3 | F2: =E2+1 -> 4 | G2: =F2+1 -> 5 | H2: =G2+1 -> 6 | I2: =H2+1 -> 7 | J2: =I2+1 -> 8
B4: Gross Potential Residential Income | C4: =SUMIF('Draw Schedule'!$F$5:$ET$5,'Net CF Post TCO'!C$2,'Draw Schedule'!$F44:$ET44) -> 2084938 | D4: =SUMIF('Draw Schedule'!$F$5:$ET$5,'Net CF Post TCO'!D$2,'Draw Schedule'!$F44:$ET44) -> 2147486.2 | E4: =SUMIF('Draw Schedule'!$F$5:$ET$5,'Net CF Post TCO'!E$2,'Draw Schedule'!$F44:$ET44) -> 2211910.7 | F4: =SUMIF('Draw Schedule'!$F$5:$ET$5,'Net CF Post TCO'!F$2,'Draw Schedule'!$F44:$ET44) -> 2278268.1 | G4: =SUMIF('Draw Schedule'!$F$5:$ET$5,'Net CF Post TCO'!G$2,'Draw Schedule'!$F44:$ET44) -> 2346616.1 | H4: =SUMIF('Draw Schedule'!$F$5:$ET$5,'Net CF Post TCO'!H$2,'Draw Schedule'!$F44:$ET44) -> 2417014.6 | I4: =SUMIF('Draw Schedule'!$F$5:$ET$5,'Net CF Post TCO'!I$2,'Draw Schedule'!$F44:$ET44) -> 2489525 | J4: =SUMIF('Draw Schedule'!$F$5:$ET$5,'Net CF Post TCO'!J$2,'Draw Schedule'!$F44:$ET44) -> 2564210.8
B5: Gross Potential Parking Income | C5: =SUMIF('Draw Schedule'!$F$5:$ET$5,'Net CF Post TCO'!C$2,'Draw Schedule'!$F45:$ET45) -> 0 | D5: =SUMIF('Draw Schedule'!$F$5:$ET$5,'Net CF Post TCO'!D$2,'Draw Schedule'!$F45:$ET45) -> 0 | E5: =SUMIF('Draw Schedule'!$F$5:$ET$5,'Net CF Post TCO'!E$2,'Draw Schedule'!$F45:$ET45) -> 0 | F5: =SUMIF('Draw Schedule'!$F$5:$ET$5,'Net CF Post TCO'!F$2,'Draw Schedule'!$F45:$ET45) -> 0 | G5: =SUMIF('Draw Schedule'!$F$5:$ET$5,'Net CF Post TCO'!G$2,'Draw Schedule'!$F45:$ET45) -> 0 | H5: =SUMIF('Draw Schedule'!$F$5:$ET$5,'Net CF Post TCO'!H$2,'Draw Schedule'!$F45:$ET45) -> 0 | I5: =SUMIF('Draw Schedule'!$F$5:$ET$5,'Net CF Post TCO'!I$2,'Draw Schedule'!$F45:$ET45) -> 0 | J5: =SUMIF('Draw Schedule'!$F$5:$ET$5,'Net CF Post TCO'!J$2,'Draw Schedule'!$F45:$ET45) -> 0
B6: Gross Potential Misc Income | C6: =SUMIF('Draw Schedule'!$F$5:$ET$5,'Net CF Post TCO'!C$2,'Draw Schedule'!$F46:$ET46) -> 118800 | D6: =SUMIF('Draw Schedule'!$F$5:$ET$5,'Net CF Post TCO'!D$2,'Draw Schedule'!$F46:$ET46) -> 122364 | E6: =SUMIF('Draw Schedule'!$F$5:$ET$5,'Net CF Post TCO'!E$2,'Draw Schedule'!$F46:$ET46) -> 126034.92 | F6: =SUMIF('Draw Schedule'!$F$5:$ET$5,'Net CF Post TCO'!F$2,'Draw Schedule'!$F46:$ET46) -> 129815.97 | G6: =SUMIF('Draw Schedule'!$F$5:$ET$5,'Net CF Post TCO'!G$2,'Draw Schedule'!$F46:$ET46) -> 133710.45 | H6: =SUMIF('Draw Schedule'!$F$5:$ET$5,'Net CF Post TCO'!H$2,'Draw Schedule'!$F46:$ET46) -> 137721.76 | I6: =SUMIF('Draw Schedule'!$F$5:$ET$5,'Net CF Post TCO'!I$2,'Draw Schedule'!$F46:$ET46) -> 141853.41 | J6: =SUMIF('Draw Schedule'!$F$5:$ET$5,'Net CF Post TCO'!J$2,'Draw Schedule'!$F46:$ET46) -> 146109.02
B7: Gross Potential Retail Income | C7: =SUMIF('Draw Schedule'!$F$5:$ET$5,'Net CF Post TCO'!C$2,'Draw Schedule'!$F68:$ET68) -> 142560 | D7: =SUMIF('Draw Schedule'!$F$5:$ET$5,'Net CF Post TCO'!D$2,'Draw Schedule'!$F68:$ET68) -> 146836.8 | E7: =SUMIF('Draw Schedule'!$F$5:$ET$5,'Net CF Post TCO'!E$2,'Draw Schedule'!$F68:$ET68) -> 151241.9 | F7: =SUMIF('Draw Schedule'!$F$5:$ET$5,'Net CF Post TCO'!F$2,'Draw Schedule'!$F68:$ET68) -> 155779.16 | G7: =SUMIF('Draw Schedule'!$F$5:$ET$5,'Net CF Post TCO'!G$2,'Draw Schedule'!$F68:$ET68) -> 160452.54 | H7: =SUMIF('Draw Schedule'!$F$5:$ET$5,'Net CF Post TCO'!H$2,'Draw Schedule'!$F68:$ET68) -> 165266.11 | I7: =SUMIF('Draw Schedule'!$F$5:$ET$5,'Net CF Post TCO'!I$2,'Draw Schedule'!$F68:$ET68) -> 170224.1 | J7: =SUMIF('Draw Schedule'!$F$5:$ET$5,'Net CF Post TCO'!J$2,'Draw Schedule'!$F68:$ET68) -> 175330.82
B8: Vacancy Loss | C8: =SUMIF('Draw Schedule'!$F$5:$ET$5,'Net CF Post TCO'!C$2,'Draw Schedule'!$F47:$ET47)+SUMIF('Draw Schedule'!$F$5:$ET$5,'Net CF Post TCO'!C$2,'Draw Schedule'!$F69:$ET69) -> -506753.09 | D8: =SUMIF('Draw Schedule'!$F$5:$ET$5,'Net CF Post TCO'!D$2,'Draw Schedule'!$F47:$ET47)+SUMIF('Draw Schedule'!$F$5:$ET$5,'Net CF Post TCO'!D$2,'Draw Schedule'!$F69:$ET69) -> -113492.51 | E8: =SUMIF('Draw Schedule'!$F$5:$ET$5,'Net CF Post TCO'!E$2,'Draw Schedule'!$F47:$ET47)+SUMIF('Draw Schedule'!$F$5:$ET$5,'Net CF Post TCO'!E$2,'Draw Schedule'!$F69:$ET69) -> -116897.28 | F8: =SUMIF('Draw Schedule'!$F$5:$ET$5,'Net CF Post TCO'!F$2,'Draw Schedule'!$F47:$ET47)+SUMIF('Draw Schedule'!$F$5:$ET$5,'Net CF Post TCO'!F$2,'Draw Schedule'!$F69:$ET69) -> -120404.2 | G8: =SUMIF('Draw Schedule'!$F$5:$ET$5,'Net CF Post TCO'!G$2,'Draw Schedule'!$F47:$ET47)+SUMIF('Draw Schedule'!$F$5:$ET$5,'Net CF Post TCO'!G$2,'Draw Schedule'!$F69:$ET69) -> -124016.33 | H8: =SUMIF('Draw Schedule'!$F$5:$ET$5,'Net CF Post TCO'!H$2,'Draw Schedule'!$F47:$ET47)+SUMIF('Draw Schedule'!$F$5:$ET$5,'Net CF Post TCO'!H$2,'Draw Schedule'!$F69:$ET69) -> -127736.82 | I8: =SUMIF('Draw Schedule'!$F$5:$ET$5,'Net CF Post TCO'!I$2,'Draw Schedule'!$F47:$ET47)+SUMIF('Draw Schedule'!$F$5:$ET$5,'Net CF Post TCO'!I$2,'Draw Schedule'!$F69:$ET69) -> -131568.92 | J8: =SUMIF('Draw Schedule'!$F$5:$ET$5,'Net CF Post TCO'!J$2,'Draw Schedule'!$F47:$ET47)+SUMIF('Draw Schedule'!$F$5:$ET$5,'Net CF Post TCO'!J$2,'Draw Schedule'!$F69:$ET69) -> -135515.99
B9: Residential Concessions | C9: =SUMIF('Draw Schedule'!$F$5:$ET$5,'Net CF Post TCO'!C$2,'Draw Schedule'!$F48:$ET48) -> -69644.329 | D9: =SUMIF('Draw Schedule'!$F$5:$ET$5,'Net CF Post TCO'!D$2,'Draw Schedule'!$F48:$ET48) -> 0 | E9: =SUMIF('Draw Schedule'!$F$5:$ET$5,'Net CF Post TCO'!E$2,'Draw Schedule'!$F48:$ET48) -> 0 | F9: =SUMIF('Draw Schedule'!$F$5:$ET$5,'Net CF Post TCO'!F$2,'Draw Schedule'!$F48:$ET48) -> 0 | G9: =SUMIF('Draw Schedule'!$F$5:$ET$5,'Net CF Post TCO'!G$2,'Draw Schedule'!$F48:$ET48) -> 0 | H9: =SUMIF('Draw Schedule'!$F$5:$ET$5,'Net CF Post TCO'!H$2,'Draw Schedule'!$F48:$ET48) -> 0 | I9: =SUMIF('Draw Schedule'!$F$5:$ET$5,'Net CF Post TCO'!I$2,'Draw Schedule'!$F48:$ET48) -> 0 | J9: =SUMIF('Draw Schedule'!$F$5:$ET$5,'Net CF Post TCO'!J$2,'Draw Schedule'!$F48:$ET48) -> 0
B10: Net Effective Revenue | C10: =SUM(C4:C9) -> 1769900.6 | D10: =SUM(D4:D9) -> 2303194.4 | E10: =SUM(E4:E9) -> 2372290.3 | F10: =SUM(F4:F9) -> 2443459 | G10: =SUM(G4:G9) -> 2516762.8 | H10: =SUM(H4:H9) -> 2592265.6 | I10: =SUM(I4:I9) -> 2670033.6 | J10: =SUM(J4:J9) -> 2750134.6
B11: Utilities | C11: =SUMIF('Draw Schedule'!$F$5:$ET$5,'Net CF Post TCO'!C$2,'Draw Schedule'!$F50:$ET50) -> -52800 | D11: =SUMIF('Draw Schedule'!$F$5:$ET$5,'Net CF Post TCO'!D$2,'Draw Schedule'!$F50:$ET50) -> -54384 | E11: =SUMIF('Draw Schedule'!$F$5:$ET$5,'Net CF Post TCO'!E$2,'Draw Schedule'!$F50:$ET50) -> -56015.52 | F11: =SUMIF('Draw Schedule'!$F$5:$ET$5,'Net CF Post TCO'!F$2,'Draw Schedule'!$F50:$ET50) -> -57695.986 | G11: =SUMIF('Draw Schedule'!$F$5:$ET$5,'Net CF Post TCO'!G$2,'Draw Schedule'!$F50:$ET50) -> -59426.865 | H11: =SUMIF('Draw Schedule'!$F$5:$ET$5,'Net CF Post TCO'!H$2,'Draw Schedule'!$F50:$ET50) -> -61209.671 | I11: =SUMIF('Draw Schedule'!$F$5:$ET$5,'Net CF Post TCO'!I$2,'Draw Schedule'!$F50:$ET50) -> -63045.961 | J11: =SUMIF('Draw Schedule'!$F$5:$ET$5,'Net CF Post TCO'!J$2,'Draw Schedule'!$F50:$ET50) -> -64937.34
B12: Repairs and Maintenance | C12: =SUMIF('Draw Schedule'!$F$5:$ET$5,'Net CF Post TCO'!C$2,'Draw Schedule'!$F51:$ET51) -> -33000 | D12: =SUMIF('Draw Schedule'!$F$5:$ET$5,'Net CF Post TCO'!D$2,'Draw Schedule'!$F51:$ET51) -> -33990 | E12: =SUMIF('Draw Schedule'!$F$5:$ET$5,'Net CF Post TCO'!E$2,'Draw Schedule'!$F51:$ET51) -> -35009.7 | F12: =SUMIF('Draw Schedule'!$F$5:$ET$5,'Net CF Post TCO'!F$2,'Draw Schedule'!$F51:$ET51) -> -36059.991 | G12: =SUMIF('Draw Schedule'!$F$5:$ET$5,'Net CF Post TCO'!G$2,'Draw Schedule'!$F51:$ET51) -> -37141.791 | H12: =SUMIF('Draw Schedule'!$F$5:$ET$5,'Net CF Post TCO'!H$2,'Draw Schedule'!$F51:$ET51) -> -38256.044 | I12: =SUMIF('Draw Schedule'!$F$5:$ET$5,'Net CF Post TCO'!I$2,'Draw Schedule'!$F51:$ET51) -> -39403.726 | J12: =SUMIF('Draw Schedule'!$F$5:$ET$5,'Net CF Post TCO'!J$2,'Draw Schedule'!$F51:$ET51) -> -40585.838
B13: Labor | C13: =SUMIF('Draw Schedule'!$F$5:$ET$5,'Net CF Post TCO'!C$2,'Draw Schedule'!$F52:$ET52) -> -59400 | D13: =SUMIF('Draw Schedule'!$F$5:$ET$5,'Net CF Post TCO'!D$2,'Draw Schedule'!$F52:$ET52) -> -61182 | E13: =SUMIF('Draw Schedule'!$F$5:$ET$5,'Net CF Post TCO'!E$2,'Draw Schedule'!$F52:$ET52) -> -63017.46 | F13: =SUMIF('Draw Schedule'!$F$5:$ET$5,'Net CF Post TCO'!F$2,'Draw Schedule'!$F52:$ET52) -> -64907.984 | G13: =SUMIF('Draw Schedule'!$F$5:$ET$5,'Net CF Post TCO'!G$2,'Draw Schedule'!$F52:$ET52) -> -66855.223 | H13: =SUMIF('Draw Schedule'!$F$5:$ET$5,'Net CF Post TCO'!H$2,'Draw Schedule'!$F52:$ET52) -> -68860.88 | I13: =SUMIF('Draw Schedule'!$F$5:$ET$5,'Net CF Post TCO'!I$2,'Draw Schedule'!$F52:$ET52) -> -70926.706 | J13: =SUMIF('Draw Schedule'!$F$5:$ET$5,'Net CF Post TCO'!J$2,'Draw Schedule'!$F52:$ET52) -> -73054.508
B14: Insurance | C14: =SUMIF('Draw Schedule'!$F$5:$ET$5,'Net CF Post TCO'!C$2,'Draw Schedule'!$F53:$ET53) -> -23100 | D14: =SUMIF('Draw Schedule'!$F$5:$ET$5,'Net CF Post TCO'!D$2,'Draw Schedule'!$F53:$ET53) -> -23793 | E14: =SUMIF('Draw Schedule'!$F$5:$ET$5,'Net CF Post TCO'!E$2,'Draw Schedule'!$F53:$ET53) -> -24506.79 | F14: =SUMIF('Draw Schedule'!$F$5:$ET$5,'Net CF Post TCO'!F$2,'Draw Schedule'!$F53:$ET53) -> -25241.994 | G14: =SUMIF('Draw Schedule'!$F$5:$ET$5,'Net CF Post TCO'!G$2,'Draw Schedule'!$F53:$ET53) -> -25999.254 | H14: =SUMIF('Draw Schedule'!$F$5:$ET$5,'Net CF Post TCO'!H$2,'Draw Schedule'!$F53:$ET53) -> -26779.231 | I14: =SUMIF('Draw Schedule'!$F$5:$ET$5,'Net CF Post TCO'!I$2,'Draw Schedule'!$F53:$ET53) -> -27582.608 | J14: =SUMIF('Draw Schedule'!$F$5:$ET$5,'Net CF Post TCO'!J$2,'Draw Schedule'!$F53:$ET53) -> -28410.086
B15: General & Administrative | C15: =SUMIF('Draw Schedule'!$F$5:$ET$5,'Net CF Post TCO'!C$2,'Draw Schedule'!$F54:$ET54) -> -23100 | D15: =SUMIF('Draw Schedule'!$F$5:$ET$5,'Net CF Post TCO'!D$2,'Draw Schedule'!$F54:$ET54) -> -23793 | E15: =SUMIF('Draw Schedule'!$F$5:$ET$5,'Net CF Post TCO'!E$2,'Draw Schedule'!$F54:$ET54) -> -24506.79 | F15: =SUMIF('Draw Schedule'!$F$5:$ET$5,'Net CF Post TCO'!F$2,'Draw Schedule'!$F54:$ET54) -> -25241.994 | G15: =SUMIF('Draw Schedule'!$F$5:$ET$5,'Net CF Post TCO'!G$2,'Draw Schedule'!$F54:$ET54) -> -25999.254 | H15: =SUMIF('Draw Schedule'!$F$5:$ET$5,'Net CF Post TCO'!H$2,'Draw Schedule'!$F54:$ET54) -> -26779.231 | I15: =SUMIF('Draw Schedule'!$F$5:$ET$5,'Net CF Post TCO'!I$2,'Draw Schedule'!$F54:$ET54) -> -27582.608 | J15: =SUMIF('Draw Schedule'!$F$5:$ET$5,'Net CF Post TCO'!J$2,'Draw Schedule'!$F54:$ET54) -> -28410.086
B16: Marketing/Leasing | C16: =SUMIF('Draw Schedule'!$F$5:$ET$5,'Net CF Post TCO'!C$2,'Draw Schedule'!$F55:$ET55) -> -19800 | D16: =SUMIF('Draw Schedule'!$F$5:$ET$5,'Net CF Post TCO'!D$2,'Draw Schedule'!$F55:$ET55) -> -20394 | E16: =SUMIF('Draw Schedule'!$F$5:$ET$5,'Net CF Post TCO'!E$2,'Draw Schedule'!$F55:$ET55) -> -21005.82 | F16: =SUMIF('Draw Schedule'!$F$5:$ET$5,'Net CF Post TCO'!F$2,'Draw Schedule'!$F55:$ET55) -> -21635.995 | G16: =SUMIF('Draw Schedule'!$F$5:$ET$5,'Net CF Post TCO'!G$2,'Draw Schedule'!$F55:$ET55) -> -22285.074 | H16: =SUMIF('Draw Schedule'!$F$5:$ET$5,'Net CF Post TCO'!H$2,'Draw Schedule'!$F55:$ET55) -> -22953.627 | I16: =SUMIF('Draw Schedule'!$F$5:$ET$5,'Net CF Post TCO'!I$2,'Draw Schedule'!$F55:$ET55) -> -23642.235 | J16: =SUMIF('Draw Schedule'!$F$5:$ET$5,'Net CF Post TCO'!J$2,'Draw Schedule'!$F55:$ET55) -> -24351.503
B17: Turnover | C17: =SUMIF('Draw Schedule'!$F$5:$ET$5,'Net CF Post TCO'!C$2,'Draw Schedule'!$F56:$ET56) -> 0 | D17: =SUMIF('Draw Schedule'!$F$5:$ET$5,'Net CF Post TCO'!D$2,'Draw Schedule'!$F56:$ET56) -> 0 | E17: =SUMIF('Draw Schedule'!$F$5:$ET$5,'Net CF Post TCO'!E$2,'Draw Schedule'!$F56:$ET56) -> 0 | F17: =SUMIF('Draw Schedule'!$F$5:$ET$5,'Net CF Post TCO'!F$2,'Draw Schedule'!$F56:$ET56) -> 0 | G17: =SUMIF('Draw Schedule'!$F$5:$ET$5,'Net CF Post TCO'!G$2,'Draw Schedule'!$F56:$ET56) -> 0 | H17: =SUMIF('Draw Schedule'!$F$5:$ET$5,'Net CF Post TCO'!H$2,'Draw Schedule'!$F56:$ET56) -> 0 | I17: =SUMIF('Draw Schedule'!$F$5:$ET$5,'Net CF Post TCO'!I$2,'Draw Schedule'!$F56:$ET56) -> 0 | J17: =SUMIF('Draw Schedule'!$F$5:$ET$5,'Net CF Post TCO'!J$2,'Draw Schedule'!$F56:$ET56) -> 0
B18: Management Fee | C18: =SUMIF('Draw Schedule'!$F$5:$ET$5,'Net CF Post TCO'!C$2,'Draw Schedule'!$F57:$ET57)+SUMIF('Draw Schedule'!$F$5:$ET$5,'Net CF Post TCO'!C$2,'Draw Schedule'!$F70:$ET70) -> -35398.012 | D18: =SUMIF('Draw Schedule'!$F$5:$ET$5,'Net CF Post TCO'!D$2,'Draw Schedule'!$F57:$ET57)+SUMIF('Draw Schedule'!$F$5:$ET$5,'Net CF Post TCO'!D$2,'Draw Schedule'!$F70:$ET70) -> -46063.889 | E18: =SUMIF('Draw Schedule'!$F$5:$ET$5,'Net CF Post TCO'!E$2,'Draw Schedule'!$F57:$ET57)+SUMIF('Draw Schedule'!$F$5:$ET$5,'Net CF Post TCO'!E$2,'Draw Schedule'!$F70:$ET70) -> -47445.806 | F18: =SUMIF('Draw Schedule'!$F$5:$ET$5,'Net CF Post TCO'!F$2,'Draw Schedule'!$F57:$ET57)+SUMIF('Draw Schedule'!$F$5:$ET$5,'Net CF Post TCO'!F$2,'Draw Schedule'!$F70:$ET70) -> -48869.18 | G18: =SUMIF('Draw Schedule'!$F$5:$ET$5,'Net CF Post TCO'!G$2,'Draw Schedule'!$F57:$ET57)+SUMIF('Draw Schedule'!$F$5:$ET$5,'Net CF Post TCO'!G$2,'Draw Schedule'!$F70:$ET70) -> -50335.255 | H18: =SUMIF('Draw Schedule'!$F$5:$ET$5,'Net CF Post TCO'!H$2,'Draw Schedule'!$F57:$ET57)+SUMIF('Draw Schedule'!$F$5:$ET$5,'Net CF Post TCO'!H$2,'Draw Schedule'!$F70:$ET70) -> -51845.313 | I18: =SUMIF('Draw Schedule'!$F$5:$ET$5,'Net CF Post TCO'!I$2,'Draw Schedule'!$F57:$ET57)+SUMIF('Draw Schedule'!$F$5:$ET$5,'Net CF Post TCO'!I$2,'Draw Schedule'!$F70:$ET70) -> -53400.672 | J18: =SUMIF('Draw Schedule'!$F$5:$ET$5,'Net CF Post TCO'!J$2,'Draw Schedule'!$F57:$ET57)+SUMIF('Draw Schedule'!$F$5:$ET$5,'Net CF Post TCO'!J$2,'Draw Schedule'!$F70:$ET70) -> -55002.692
B19: Opex Contingency | C19: =SUMIF('Draw Schedule'!$F$5:$ET$5,'Net CF Post TCO'!C$2,'Draw Schedule'!$F58:$ET58) -> -6164.9503 | D19: =SUMIF('Draw Schedule'!$F$5:$ET$5,'Net CF Post TCO'!D$2,'Draw Schedule'!$F58:$ET58) -> -6589.9972 | E19: =SUMIF('Draw Schedule'!$F$5:$ET$5,'Net CF Post TCO'!E$2,'Draw Schedule'!$F58:$ET58) -> -6787.6971 | F19: =SUMIF('Draw Schedule'!$F$5:$ET$5,'Net CF Post TCO'!F$2,'Draw Schedule'!$F58:$ET58) -> -6991.3281 | G19: =SUMIF('Draw Schedule'!$F$5:$ET$5,'Net CF Post TCO'!G$2,'Draw Schedule'!$F58:$ET58) -> -7201.0679 | H19: =SUMIF('Draw Schedule'!$F$5:$ET$5,'Net CF Post TCO'!H$2,'Draw Schedule'!$F58:$ET58) -> -7417.0999 | I19: =SUMIF('Draw Schedule'!$F$5:$ET$5,'Net CF Post TCO'!I$2,'Draw Schedule'!$F58:$ET58) -> -7639.6129 | J19: =SUMIF('Draw Schedule'!$F$5:$ET$5,'Net CF Post TCO'!J$2,'Draw Schedule'!$F58:$ET58) -> -7868.8013
B20: Real Estate Taxes | C20: =SUMIF('Draw Schedule'!$F$5:$ET$5,'Net CF Post TCO'!C$2,'Draw Schedule'!$F59:$ET59) -> -432399.64 | D20: =SUMIF('Draw Schedule'!$F$5:$ET$5,'Net CF Post TCO'!D$2,'Draw Schedule'!$F59:$ET59) -> -432399.64 | E20: =SUMIF('Draw Schedule'!$F$5:$ET$5,'Net CF Post TCO'!E$2,'Draw Schedule'!$F59:$ET59) -> -432399.64 | F20: =SUMIF('Draw Schedule'!$F$5:$ET$5,'Net CF Post TCO'!F$2,'Draw Schedule'!$F59:$ET59) -> -432399.64 | G20: =SUMIF('Draw Schedule'!$F$5:$ET$5,'Net CF Post TCO'!G$2,'Draw Schedule'!$F59:$ET59) -> -432399.64 | H20: =SUMIF('Draw Schedule'!$F$5:$ET$5,'Net CF Post TCO'!H$2,'Draw Schedule'!$F59:$ET59) -> -432399.64 | I20: =SUMIF('Draw Schedule'!$F$5:$ET$5,'Net CF Post TCO'!I$2,'Draw Schedule'!$F59:$ET59) -> -432399.64 | J20: =SUMIF('Draw Schedule'!$F$5:$ET$5,'Net CF Post TCO'!J$2,'Draw Schedule'!$F59:$ET59) -> -432399.64
B21: Total Expenses | C21: =SUM(C11:C20) -> -685162.61 | D21: =SUM(D11:D20) -> -702589.53 | E21: =SUM(E11:E20) -> -710695.23 | F21: =SUM(F11:F20) -> -719044.09 | G21: =SUM(G11:G20) -> -727643.43 | H21: =SUM(H11:H20) -> -736500.74 | I21: =SUM(I11:I20) -> -745623.77 | J21: =SUM(J11:J20) -> -755020.5
B22: Net Operating Income | C22: =C10+C21 -> 1084738 | D22: =D10+D21 -> 1600604.9 | E22: =E10+E21 -> 1661595.1 | F22: =F10+F21 -> 1724414.9 | G22: =G10+G21 -> 1789119.3 | H22: =H10+H21 -> 1855764.9 | I22: =I10+I21 -> 1924409.8 | J22: =J10+J21 -> 1995114.1
B23: Ground Lease | C23: =SUMIF('Draw Schedule'!$F$5:$ET$5,'Net CF Post TCO'!C$2,'Draw Schedule'!$F75:$ET75) -> 0 | D23: =SUMIF('Draw Schedule'!$F$5:$ET$5,'Net CF Post TCO'!D$2,'Draw Schedule'!$F75:$ET75) -> 0 | E23: =SUMIF('Draw Schedule'!$F$5:$ET$5,'Net CF Post TCO'!E$2,'Draw Schedule'!$F75:$ET75) -> 0 | F23: =SUMIF('Draw Schedule'!$F$5:$ET$5,'Net CF Post TCO'!F$2,'Draw Schedule'!$F75:$ET75) -> 0 | G23: =SUMIF('Draw Schedule'!$F$5:$ET$5,'Net CF Post TCO'!G$2,'Draw Schedule'!$F75:$ET75) -> 0 | H23: =SUMIF('Draw Schedule'!$F$5:$ET$5,'Net CF Post TCO'!H$2,'Draw Schedule'!$F75:$ET75) -> 0 | I23: =SUMIF('Draw Schedule'!$F$5:$ET$5,'Net CF Post TCO'!I$2,'Draw Schedule'!$F75:$ET75) -> 0 | J23: =SUMIF('Draw Schedule'!$F$5:$ET$5,'Net CF Post TCO'!J$2,'Draw Schedule'!$F75:$ET75) -> 0
B24: Net Operating Income (After GL) | C24: =C22+C23 -> 1084738 | D24: =D22+D23 -> 1600604.9 | E24: =E22+E23 -> 1661595.1 | F24: =F22+F23 -> 1724414.9 | G24: =G22+G23 -> 1789119.3 | H24: =H22+H23 -> 1855764.9 | I24: =I22+I23 -> 1924409.8 | J24: =J22+J23 -> 1995114.1
B25: CapEx | C25: =SUMIF('Draw Schedule'!$F$5:$ET$5,'Net CF Post TCO'!C$2,'Draw Schedule'!$F60:$ET60) -> -6600 | D25: =SUMIF('Draw Schedule'!$F$5:$ET$5,'Net CF Post TCO'!D$2,'Draw Schedule'!$F60:$ET60) -> -6798 | E25: =SUMIF('Draw Schedule'!$F$5:$ET$5,'Net CF Post TCO'!E$2,'Draw Schedule'!$F60:$ET60) -> -7001.94 | F25: =SUMIF('Draw Schedule'!$F$5:$ET$5,'Net CF Post TCO'!F$2,'Draw Schedule'!$F60:$ET60) -> -7211.9982 | G25: =SUMIF('Draw Schedule'!$F$5:$ET$5,'Net CF Post TCO'!G$2,'Draw Schedule'!$F60:$ET60) -> -7428.3581 | H25: =SUMIF('Draw Schedule'!$F$5:$ET$5,'Net CF Post TCO'!H$2,'Draw Schedule'!$F60:$ET60) -> -7651.2089 | I25: =SUMIF('Draw Schedule'!$F$5:$ET$5,'Net CF Post TCO'!I$2,'Draw Schedule'!$F60:$ET60) -> -7880.7452 | J25: =SUMIF('Draw Schedule'!$F$5:$ET$5,'Net CF Post TCO'!J$2,'Draw Schedule'!$F60:$ET60) -> -8117.1675
B26: Asset Management Fee | C26: =SUMIF('Draw Schedule'!$F$5:$ET$5,'Net CF Post TCO'!C$2,'Draw Schedule'!$F61:$ET61)+SUMIF('Draw Schedule'!$F$5:$ET$5,'Net CF Post TCO'!C$2,'Draw Schedule'!$F72:$ET72) -> -17592.086 | D26: =SUMIF('Draw Schedule'!$F$5:$ET$5,'Net CF Post TCO'!D$2,'Draw Schedule'!$F61:$ET61)+SUMIF('Draw Schedule'!$F$5:$ET$5,'Net CF Post TCO'!D$2,'Draw Schedule'!$F72:$ET72) -> -23031.944 | E26: =SUMIF('Draw Schedule'!$F$5:$ET$5,'Net CF Post TCO'!E$2,'Draw Schedule'!$F61:$ET61)+SUMIF('Draw Schedule'!$F$5:$ET$5,'Net CF Post TCO'!E$2,'Draw Schedule'!$F72:$ET72) -> -23722.903 | F26: =SUMIF('Draw Schedule'!$F$5:$ET$5,'Net CF Post TCO'!F$2,'Draw Schedule'!$F61:$ET61)+SUMIF('Draw Schedule'!$F$5:$ET$5,'Net CF Post TCO'!F$2,'Draw Schedule'!$F72:$ET72) -> -24434.59 | G26: =SUMIF('Draw Schedule'!$F$5:$ET$5,'Net CF Post TCO'!G$2,'Draw Schedule'!$F61:$ET61)+SUMIF('Draw Schedule'!$F$5:$ET$5,'Net CF Post TCO'!G$2,'Draw Schedule'!$F72:$ET72) -> -2047.5818 | H26: =SUMIF('Draw Schedule'!$F$5:$ET$5,'Net CF Post TCO'!H$2,'Draw Schedule'!$F61:$ET61)+SUMIF('Draw Schedule'!$F$5:$ET$5,'Net CF Post TCO'!H$2,'Draw Schedule'!$F72:$ET72) -> 0 | I26: =SUMIF('Draw Schedule'!$F$5:$ET$5,'Net CF Post TCO'!I$2,'Draw Schedule'!$F61:$ET61)+SUMIF('Draw Schedule'!$F$5:$ET$5,'Net CF Post TCO'!I$2,'Draw Schedule'!$F72:$ET72) -> 0 | J26: =SUMIF('Draw Schedule'!$F$5:$ET$5,'Net CF Post TCO'!J$2,'Draw Schedule'!$F61:$ET61)+SUMIF('Draw Schedule'!$F$5:$ET$5,'Net CF Post TCO'!J$2,'Draw Schedule'!$F72:$ET72) -> 0
B27: Net Cash Flow Before Debt Service | C27: =SUM(C24:C26) -> 1060545.9 | D27: =SUM(D24:D26) -> 1570775 | E27: =SUM(E24:E26) -> 1630870.2 | F27: =SUM(F24:F26) -> 1692768.3 | G27: =SUM(G24:G26) -> 1779643.4 | H27: =SUM(H24:H26) -> 1848113.7 | I27: =SUM(I24:I26) -> 1916529.1 | J27: =SUM(J24:J26) -> 1986996.9
B28: Debt Service | C28: =-SUMIF('Draw Schedule'!$F$5:$ET$5,'Net CF Post TCO'!C$2,'Draw Schedule'!$F123:$ET123)-SUMIF('Draw Schedule'!$F$5:$ET$5,'Net CF Post TCO'!C$2,'Draw Schedule'!$F115:$ET115) -> -1668937.3 | D28: =-SUMIF('Draw Schedule'!$F$5:$ET$5,'Net CF Post TCO'!D$2,'Draw Schedule'!$F123:$ET123)-SUMIF('Draw Schedule'!$F$5:$ET$5,'Net CF Post TCO'!D$2,'Draw Schedule'!$F115:$ET115) -> -1688015.7 | E28: =-SUMIF('Draw Schedule'!$F$5:$ET$5,'Net CF Post TCO'!E$2,'Draw Schedule'!$F123:$ET123)-SUMIF('Draw Schedule'!$F$5:$ET$5,'Net CF Post TCO'!E$2,'Draw Schedule'!$F115:$ET115) -> -1695013.2 | F28: =-SUMIF('Draw Schedule'!$F$5:$ET$5,'Net CF Post TCO'!F$2,'Draw Schedule'!$F123:$ET123)-SUMIF('Draw Schedule'!$F$5:$ET$5,'Net CF Post TCO'!F$2,'Draw Schedule'!$F115:$ET115) -> -1697825.8 | G28: =-SUMIF('Draw Schedule'!$F$5:$ET$5,'Net CF Post TCO'!G$2,'Draw Schedule'!$F123:$ET123)-SUMIF('Draw Schedule'!$F$5:$ET$5,'Net CF Post TCO'!G$2,'Draw Schedule'!$F115:$ET115) -> -141488.13 | H28: =-SUMIF('Draw Schedule'!$F$5:$ET$5,'Net CF Post TCO'!H$2,'Draw Schedule'!$F123:$ET123)-SUMIF('Draw Schedule'!$F$5:$ET$5,'Net CF Post TCO'!H$2,'Draw Schedule'!$F115:$ET115) -> 0 | I28: =-SUMIF('Draw Schedule'!$F$5:$ET$5,'Net CF Post TCO'!I$2,'Draw Schedule'!$F123:$ET123)-SUMIF('Draw Schedule'!$F$5:$ET$5,'Net CF Post TCO'!I$2,'Draw Schedule'!$F115:$ET115) -> 0 | J28: =-SUMIF('Draw Schedule'!$F$5:$ET$5,'Net CF Post TCO'!J$2,'Draw Schedule'!$F123:$ET123)-SUMIF('Draw Schedule'!$F$5:$ET$5,'Net CF Post TCO'!J$2,'Draw Schedule'!$F115:$ET115) -> 0
B29: Net Cash Flow | C29: =SUM(C27:C28) -> -608391.43 | D29: =SUM(D27:D28) -> -117240.74 | E29: =SUM(E27:E28) -> -64142.954 | F29: =SUM(F27:F28) -> -5057.54 | G29: =SUM(G27:G28) -> 1638155.3 | H29: =SUM(H27:H28) -> 1848113.7 | I29: =SUM(I27:I28) -> 1916529.1 | J29: =SUM(J27:J28) -> 1986996.9
B31: OpEx Per SF | C31: =(C21+C25)/Assumptions!$F$20 -> -13.015044 | D31: =(D21+D25)/Assumptions!$F$20 -> -13.346645 | E31: =(E21+E25)/Assumptions!$F$20 -> -13.502985 | F31: =(F21+F25)/Assumptions!$F$20 -> -13.664016 | G31: =(G21+G25)/Assumptions!$F$20 -> -13.829877 | H31: =(H21+H25)/Assumptions!$F$20 -> -14.000714 | I31: =(I21+I25)/Assumptions!$F$20 -> -14.176676 | J31: =(J21+J25)/Assumptions!$F$20 -> -14.357917
B33: Yield on Cost | D33: =IF(Assumptions!$Q$24="No",D24/Overview!$C$25,D24/(Overview!$C$25-Overview!$C$31)) -> 0.053028021 | E33: =IF(Assumptions!$Q$24="No",E24/Overview!$C$25,E24/(Overview!$C$25-Overview!$C$31)) -> 0.055048624 | F33: =IF(Assumptions!$Q$24="No",F24/Overview!$C$25,F24/(Overview!$C$25-Overview!$C$31)) -> 0.057129845 | G33: =IF(Assumptions!$Q$24="No",G24/Overview!$C$25,G24/(Overview!$C$25-Overview!$C$31)) -> 0.059273502 | H33: =IF(Assumptions!$Q$24="No",H24/Overview!$C$25,H24/(Overview!$C$25-Overview!$C$31)) -> 0.061481469 | I33: =IF(Assumptions!$Q$24="No",I24/Overview!$C$25,I24/(Overview!$C$25-Overview!$C$31)) -> 0.063755675 | J33: =IF(Assumptions!$Q$24="No",J24/Overview!$C$25,J24/(Overview!$C$25-Overview!$C$31)) -> 0.066098107
B36: Expense Ratio | D36: =D21/D10 -> -0.30505003 | E36: =E21/E10 -> -0.2995819 | F36: =F21/F10 -> -0.29427304 | G36: =G21/G10 -> -0.2891188 | H36: =H21/H10 -> -0.28411469 | I36: =I21/I10 -> -0.27925633 | J36: =J21/J10 -> -0.27453947
B37: Debt Yield | D37: =D24/SUM(Overview!$C$28:$C$30) -> 0.070704029 | E37: =E24/SUM(Overview!$C$28:$C$30) -> 0.073398165 | F37: =F24/SUM(Overview!$C$28:$C$30) -> 0.076173126 | G37: =G24/SUM(Overview!$C$28:$C$30) -> 0.079031336 | H37: =H24/SUM(Overview!$C$28:$C$30) -> 0.081975291 | I37: =I24/SUM(Overview!$C$28:$C$30) -> 0.085007566 | J37: =J24/SUM(Overview!$C$28:$C$30) -> 0.088130809

Sheet Opex Comps
B2: Operating Expense Comps ($ Amount) | H2: Operating Expense Comps (Per Unit)
C3: AARE UW | D3: Greystar | E3: Lincoln | F3: RKW | I3: AARE UW | J3: Greystar | K3: Lincoln | L3: RKW
B4: =Assumptions!H22 -> Utilities | C4: =Assumptions!L22 -> 52800 | D4: =J4*Assumptions!$C$29 -> 48444 | E4: =K4*Assumptions!$C$29 -> 66000 | F4: =L4*Assumptions!$C$29 -> 51150 | H4: =Assumptions!H22 -> Utilities | I4: =Assumptions!L22/Assumptions!C29 -> 800 | J4: 734 | K4: 1000 | L4: 775
B5: =Assumptions!H23 -> Repairs and Maintenance | C5: =Assumptions!L23 -> 33000 | D5: =J5*Assumptions!$C$29 -> 26400 | E5: =K5*Assumptions!$C$29 -> 23100 | F5: =L5*Assumptions!$C$29 -> 8382 | H5: =Assumptions!H23 -> Repairs and Maintenance | I5: =Assumptions!K23 -> 500 | J5: 400 | K5: 350 | L5: 127
B6: =Assumptions!H24 -> Labor | C6: =Assumptions!L24 -> 59400 | D6: =J6*Assumptions!$C$29 -> 118800 | E6: =K6*Assumptions!$C$29 -> 178200 | F6: =L6*Assumptions!$C$29 -> 117084 | H6: =Assumptions!H24 -> Labor | I6: =Assumptions!K24 -> 900 | J6: 1800 | K6: 2700 | L6: 1774
B7: =Assumptions!H25 -> Insurance | C7: =Assumptions!L25 -> 23100 | D7: =J7*Assumptions!$C$29 -> 79200 | E7: =K7*Assumptions!$C$29 -> 72600 | F7: =L7*Assumptions!$C$29 -> 71280 | H7: =Assumptions!H25 -> Insurance | I7: =Assumptions!K25 -> 350 | J7: 1200 | K7: 1100 | L7: 1080
B8: =Assumptions!H26 -> G&A / Service Contracts | C8: =Assumptions!L26 -> 23100 | D8: =J8*Assumptions!$C$29 -> 99000 | E8: =K8*Assumptions!$C$29 -> 59400 | F8: =L8*Assumptions!$C$29 -> 102300 | H8: =Assumptions!H26 -> G&A / Service Contracts | I8: =Assumptions!K26 -> 350 | J8: 1500 | K8: 900 | L8: =1150+400 -> 1550
B9: =Assumptions!H27 -> Marketing/Leasing | C9: =Assumptions!L27 -> 19800 | D9: =J9*Assumptions!$C$29 -> 33000 | E9: =K9*Assumptions!$C$29 -> 23760 | F9: =L9*Assumptions!$C$29 -> 30030 | H9: =Assumptions!H27 -> Marketing/Leasing | I9: =Assumptions!K27 -> 300 | J9: 500 | K9: 360 | L9: 455
B10: =Assumptions!H28 -> Turnover | C10: =Assumptions!L28 -> 0 | D10: =J10*Assumptions!$C$29 -> 13200 | E10: =K10*Assumptions!$C$29 -> 14850 | F10: =L10*Assumptions!$C$29 -> 16500 | H10: =Assumptions!H28 -> Turnover | I10: =Assumptions!K28 -> 0 | J10: 200 | K10: 225 | L10: 250
B11: =Assumptions!H29 -> Capital Reserves | C11: =Assumptions!L29 -> 6600 | D11: =J11*Assumptions!$C$29 -> 13200 | E11: =K11*Assumptions!$C$29 -> 9900 | F11: =L11*Assumptions!$C$29 -> 0 | H11: =Assumptions!H29 -> Capital Reserves | I11: =Assumptions!K29 -> 100 | J11: 200 | K11: 150 | L11: 0
B12: =Assumptions!H37 -> Real Estate Taxes | C12: =Assumptions!L38 -> 432399.64 | D12: =J12*Assumptions!$C$29 -> 336600 | E12: =K12*Assumptions!$C$29 -> 330000 | F12: =L12*Assumptions!$C$29 -> 264000 | H12: =Assumptions!H37 -> Real Estate Taxes | I12: =Assumptions!L38/Assumptions!C29 -> 6551.5098 | J12: 5100 | K12: 5000 | L12: 4000
B13: =Assumptions!H30 -> Management Fee | C13: =Assumptions!K30 -> 0.02 | D13: =J13 -> 0.025 | E13: =K13 -> 0.02 | F13: =L13 -> 0.0275 | H13: =Assumptions!H30 -> Management Fee | I13: =Assumptions!K30 -> 0.02 | J13: 0.025 | K13: 0.02 | L13: 0.0275
B14: =Assumptions!H31 -> Opex Contingency | C14: =Assumptions!K31 -> 0.025 | D14: =J14 -> 0 | E14: =K14 -> 0 | F14: =L14 -> 0 | H14: =Assumptions!H31 -> Opex Contingency | I14: =Assumptions!K31 -> 0.025 | J14: 0 | K14: 0 | L14: 0
B16: Misc Income Comps ($ Amount) | H16: Misc Income Comps (Per Unit Per Month)
C17: AARE UW | D17: Greystar | E17: Lincoln | F17: RKW | I17: AARE UW | J17: Greystar | K17: Lincoln | L17: RKW
B18: Parking Income | C18: =Assumptions!K6*Assumptions!F30*Assumptions!I6*12 -> 0 | D18: =J18*Assumptions!$I$6*Assumptions!$F$30*12 -> 94500 | E18: =K18*Assumptions!$I$6*Assumptions!$F$30*12 -> 94500 | F18: =L18*Assumptions!$I$6*Assumptions!$F$30*12 -> 75600 | H18: Parking Income | I18: =Assumptions!K6 -> 0 | J18: 125 | K18: 125 | L18: 100
B19: Misc Income | C19: =Assumptions!K7*Assumptions!C29*12 -> 118800 | D19: =J19*Assumptions!$C$29 -> 6050 | E19: =K19*Assumptions!$C$29 -> 6600 | F19: =L19*Assumptions!$C$29 -> 5500 | H19: Misc Income (Per Month) | I19: =Assumptions!K7 -> 150 | J19: =1100/12 -> 91.666667 | K19: =1200/12 -> 100 | L19: =1000/12 -> 83.333333
B21: Date Received | D21: 44664 | E21: 44719 | F21: 44715
B23: Confirmed Tax Calculation? | F23: No
B25: Confirmed Insurance | F25: No

Sheet Unit Comps
B2: Building 1 Name
B3: Unit Type | C3: Range | D3: Avg Rent | E3: Avg SF | F3: $/SF
B4: 1 BR | C4: 0 | D4: 0 | E4: 0 | F4: =D4/E4 -> #DIV/0!
B5: 2 BR | C5: 0 | D5: 0 | E5: 0 | F5: =D5/E5 -> #DIV/0!
B6: 3 BR | C6: 0 | D6: 0 | E6: 0 | F6: =D6/E6 -> #DIV/0!
B7: 4 BR | C7: 0 | D7: 0 | E7: 0 | F7: =D7/E7 -> #DIV/0!
B9: Notes:
B17: Building 2 Name
B18: Unit Type | C18: Range | D18: Avg Rent | E18: Avg SF | F18: $/SF
B19: 1 BR | C19: 0 | D19: 0 | E19: 0 | F19: =D19/E19 -> #DIV/0!
B20: 2 BR | C20: 0 | D20: 0 | E20: 0 | F20: =D20/E20 -> #DIV/0!
B21: 3 BR | C21: 0 | D21: 0 | E21: 0 | F21: =D21/E21 -> #DIV/0!
B22: 4 BR | C22: 0 | D22: 0 | E22: 0 | F22: =D22/E22 -> #DIV/0!
B24: Notes:

Sheet Promote
E2: Equity | F2: Pref | G2: Tier 2 | H2: Catch Up?
D3: GP | E3: 0.15 | F3: 0.08 | G3: 0.3 | H3: Yes
B4: GP Returns | D4: LP | E4: 0.85 | F4: 0.08 | G4: 0.7
B6: Timeline | D6: 1 | E6: =D6+1 -> 2 | F6: =E6+1 -> 3 | G6: =F6+1 -> 4 | H6: =G6+1 -> 5 | I6: =H6+1 -> 6
B7: Investment | D7: =-SUMIF('Draw Schedule'!$F$4:$BZ$4,D$6,'Draw Schedule'!$F184:$BZ184) -> -522811.55 | E7: =-SUMIF('Draw Schedule'!$F$4:$BZ$4,E$6,'Draw Schedule'!$F184:$BZ184) -> -609093.48 | F7: =-SUMIF('Draw Schedule'!$F$4:$BZ$4,F$6,'Draw Schedule'!$F184:$BZ184) -> 0 | G7: =-SUMIF('Draw Schedule'!$F$4:$BZ$4,G$6,'Draw Schedule'!$F184:$BZ184) -> 0 | H7: =-SUMIF('Draw Schedule'!$F$4:$BZ$4,H$6,'Draw Schedule'!$F184:$BZ184) -> 0 | I7: =-SUMIF('Draw Schedule'!$F$4:$BZ$4,I$6,'Draw Schedule'!$F184:$BZ184) -> 0
B8: Return of Capital / Pref | D8: =SUMIF('Draw Schedule'!$F$4:$BZ$4,D$6,'Draw Schedule'!$F185:$BZ185) -> 0 | E8: =SUMIF('Draw Schedule'!$F$4:$BZ$4,E$6,'Draw Schedule'!$F185:$BZ185) -> 0 | F8: =SUMIF('Draw Schedule'!$F$4:$BZ$4,F$6,'Draw Schedule'!$F185:$BZ185) -> 0 | G8: =SUMIF('Draw Schedule'!$F$4:$BZ$4,G$6,'Draw Schedule'!$F185:$BZ185) -> 0 | H8: =SUMIF('Draw Schedule'!$F$4:$BZ$4,H$6,'Draw Schedule'!$F185:$BZ185) -> 0 | I8: =SUMIF('Draw Schedule'!$F$4:$BZ$4,I$6,'Draw Schedule'!$F185:$BZ185) -> 0
B9: Tier 2 Cash Flow | D9: =SUMIF('Draw Schedule'!$F$4:$BZ$4,D$6,'Draw Schedule'!$F198:$BZ198) -> 0 | E9: =SUMIF('Draw Schedule'!$F$4:$BZ$4,E$6,'Draw Schedule'!$F198:$BZ198) -> 0 | F9: =SUMIF('Draw Schedule'!$F$4:$BZ$4,F$6,'Draw Schedule'!$F198:$BZ198) -> 0 | G9: =SUMIF('Draw Schedule'!$F$4:$BZ$4,G$6,'Draw Schedule'!$F198:$BZ198) -> 0 | H9: =SUMIF('Draw Schedule'!$F$4:$BZ$4,H$6,'Draw Schedule'!$F198:$BZ198) -> 0 | I9: =SUMIF('Draw Schedule'!$F$4:$BZ$4,I$6,'Draw Schedule'!$F198:$BZ198) -> 0
B10: Promote | D10: =-SUMIF('Draw Schedule'!$F$4:$BZ$4,D$6,'Draw Schedule'!$F193:$BZ193)+SUMIF('Draw Schedule'!$F$4:$BZ$4,D$6,'Draw Schedule'!$F199:$BZ199) -> 0 | E10: =-SUMIF('Draw Schedule'!$F$4:$BZ$4,E$6,'Draw Schedule'!$F193:$BZ193)+SUMIF('Draw Schedule'!$F$4:$BZ$4,E$6,'Draw Schedule'!$F199:$BZ199) -> 0 | F10: =-SUMIF('Draw Schedule'!$F$4:$BZ$4,F$6,'Draw Schedule'!$F193:$BZ193)+SUMIF('Draw Schedule'!$F$4:$BZ$4,F$6,'Draw Schedule'!$F199:$BZ199) -> 0 | G10: =-SUMIF('Draw Schedule'!$F$4:$BZ$4,G$6,'Draw Schedule'!$F193:$BZ193)+SUMIF('Draw Schedule'!$F$4:$BZ$4,G$6,'Draw Schedule'!$F199:$BZ199) -> 0 | H10: =-SUMIF('Draw Schedule'!$F$4:$BZ$4,H$6,'Draw Schedule'!$F193:$BZ193)+SUMIF('Draw Schedule'!$F$4:$BZ$4,H$6,'Draw Schedule'!$F199:$BZ199) -> 0 | I10: =-SUMIF('Draw Schedule'!$F$4:$BZ$4,I$6,'Draw Schedule'!$F193:$BZ193)+SUMIF('Draw Schedule'!$F$4:$BZ$4,I$6,'Draw Schedule'!$F199:$BZ199) -> 0
B11: Total GP Cash Flow | D11: =SUM(D7:D10) -> -522811.55 | E11: =SUM(E7:E10) -> -609093.48 | F11: =SUM(F7:F10) -> 0 | G11: =SUM(G7:G10) -> 0 | H11: =SUM(H7:H10) -> 0 | I11: =SUM(I7:I10) -> 0
B13: GP Profit | D13: ='Draw Schedule'!D209 -> 955689.1
B14: GP Equity Multiple | D14: ='Draw Schedule'!D210 -> 1.8443192
B15: GP IRR | D15: ='Draw Schedule'!D211 -> 0.10497403
B17: LP Returns
B19: Timeline | D19: 1 | E19: =D19+1 -> 2 | F19: =E19+1 -> 3 | G19: =F19+1 -> 4 | H19: =G19+1 -> 5 | I19: =H19+1 -> 6
B20: Investment | D20: =-SUMIF('Draw Schedule'!$F$4:$BZ$4,D$19,'Draw Schedule'!$F$186:$BZ$186) -> -2962598.8 | E20: =-SUMIF('Draw Schedule'!$F$4:$BZ$4,E$19,'Draw Schedule'!$F$186:$BZ$186) -> -3451529.7 | F20: =-SUMIF('Draw Schedule'!$F$4:$BZ$4,F$19,'Draw Schedule'!$F$186:$BZ$186) -> 0 | G20: =-SUMIF('Draw Schedule'!$F$4:$BZ$4,G$19,'Draw Schedule'!$F$186:$BZ$186) -> 0 | H20: =-SUMIF('Draw Schedule'!$F$4:$BZ$4,H$19,'Draw Schedule'!$F$186:$BZ$186) -> 0 | I20: =-SUMIF('Draw Schedule'!$F$4:$BZ$4,I$19,'Draw Schedule'!$F$186:$BZ$186) -> 0
B21: Return of Capital / Pref | D21: =SUMIF('Draw Schedule'!$F$4:$BZ$4,D$6,'Draw Schedule'!$F187:$BZ187) -> 0 | E21: =SUMIF('Draw Schedule'!$F$4:$BZ$4,E$6,'Draw Schedule'!$F187:$BZ187) -> 0 | F21: =SUMIF('Draw Schedule'!$F$4:$BZ$4,F$6,'Draw Schedule'!$F187:$BZ187) -> 0 | G21: =SUMIF('Draw Schedule'!$F$4:$BZ$4,G$6,'Draw Schedule'!$F187:$BZ187) -> 0 | H21: =SUMIF('Draw Schedule'!$F$4:$BZ$4,H$6,'Draw Schedule'!$F187:$BZ187) -> 0 | I21: =SUMIF('Draw Schedule'!$F$4:$BZ$4,I$6,'Draw Schedule'!$F187:$BZ187) -> 0
B22: Tier 2 Cash Flow | D22: =SUMIF('Draw Schedule'!$F$4:$BZ$4,D$6,'Draw Schedule'!$F200:$BZ200) -> 0 | E22: =SUMIF('Draw Schedule'!$F$4:$BZ$4,E$6,'Draw Schedule'!$F200:$BZ200) -> 0 | F22: =SUMIF('Draw Schedule'!$F$4:$BZ$4,F$6,'Draw Schedule'!$F200:$BZ200) -> 0 | G22: =SUMIF('Draw Schedule'!$F$4:$BZ$4,G$6,'Draw Schedule'!$F200:$BZ200) -> 0 | H22: =SUMIF('Draw Schedule'!$F$4:$BZ$4,H$6,'Draw Schedule'!$F200:$BZ200) -> 0 | I22: =SUMIF('Draw Schedule'!$F$4:$BZ$4,I$6,'Draw Schedule'!$F200:$BZ200) -> 0
B23: Total LP Cash Flow | D23: =SUM(D20:D22) -> -2962598.8 | E23: =SUM(E20:E22) -> -3451529.7 | F23: =SUM(F20:F22) -> 0 | G23: =SUM(G20:G22) -> 0 | H23: =SUM(H20:H22) -> 0 | I23: =SUM(I20:I22) -> 0
B25: LP Profit | D25: ='Draw Schedule'!D214 -> 4036496.2
B26: LP Equity Multiple | D26: ='Draw Schedule'!D215 -> 1.6293133
B27: LP IRR | D27: ='Draw Schedule'!D216 -> 0.082913378

Sheet Project Comps
A1: Escrow | B1: Midtown Highline | C1: Midtown Highline | D1: 604 E Highland Mall Boulevard | E1: Austin | F1: 78752 | G1: 163 | H1: 2024 | I1: 31800000 | J1: 195092.02 | K1: 276.74554 | L1: 114907
A2: 9/15/2025 | B2: Burnet Flats | C2: Burnet Flats | D2: 5453 Burnet Road | E2: Austin | F2: 78756 | G2: 179 | H2: 2014 | I2: 39100000 | J2: 218436 | K2: 274.67 | L2: 142352
A3: 8/19/2025 | B3: Kenzie at the Domain (New HFC) | C3: Bridge at Kenzie | D3: 3201 Esperanza Crossing | E3: Austin | F3: 78758 | G3: 279 | H3: 2014 | I3: 83515000 | J3: 299337 | K3: 351.9 | L3: 237329
A4: 6/4/2025 | B4: Revl on Lamar | C4: Revl on Lamar | D4: 5629 N. Lamar Boulevard | E4: Austin | F4: 78751 | G4: 279 | H4: 2021 | I4: 62400000 | J4: 223656 | K4: 282.39 | L4: 220968
A5: 5/27/2025 | B5: Lotus Village | C5: Lotus Village | D5: 300 Ferguson Drive | E5: Austin | F5: 78753 | G5: 222 | H5: 2012 | I5: 33000000 | J5: 148649 | K5: 161.4 | L5: 204462
A6: 3/12/2025 | B6: Midtown Commons at Crestview Station (New PFC) | C6: Bridge at Midtown Commons | D6: 810 W. Saint Johns Avenue | E6: Austin | F6: 78752 | G6: 562 | H6: 2013 | I6: 135000000 | J6: 240214 | K6: 316.32 | L6: 426777
A7: 12/21/2023 | B7: The Grand at Domain (Loan Assumption) | C7: The Grand at Domain | D7: 11009 Alterra Parkway | E7: Austin | F7: 78758 | G7: 180 | H7: 2019 | I7: 68250000 | J7: 379167 | K7: 408.46 | L7: 167090
A8: 10/20/2023 | B8: The Braxton (1031 Exchange) | C8: The Braxton | D8: 4811 Woodrow Avenue | E8: Austin | F8: 78756 | G8: 53 | H8: 2019 | I8: 17500000 | J8: 330189 | K8: 392.57 | L8: 44578
A9: 8/21/2023 | B9: AMLI 5350 | C9: Haus 5350 | D9: 5350 Burnet Road | E9: Austin | F9: 78756 | G9: 175 | H9: 2010 | I9: 46250000 | J9: 264286 | K9: 318.14 | L9: 145375
